Workbook

Sheet 说明
B1: 说明
B3: 银行名称区 | E3: 数字区 | H3: 测试数据表
B5: 样式 | C5: 含义 | E5: 样式 | F5: 含义 | H5: 名称 | I5: 含义
B6: 名称填充色 | C6: 健康的。未填充颜色 | E6: 数字填充色 | F6: 未变化的 | H6: 形如右边： | I6: “我设定的Bank之过程-20220307”、“我设定的Bank Interbank之过程-20220306”等数据表内容，分别表示各银行主要变量变动情况、和银行间主要变量变动情况。
B7: 名称填充色 | C7: 资不抵债相关的。 | E7: 数字填充色 | F7: 变化的，因为外部冲击 | H7: XX之过程-参数Y | I7: 银行变量或者银行间主要变量变动过程，当初始设定参数Y时。
B8: 名称填充色 | C8: 流动性短缺相关的。 | E8: 数字填充色 | F8: 变化的，因为银行间违约冲击
B9: 名称填充色 | C9: 破产相关的。 | E9: 数字填充色 | F9: 变化的，因为流动性短缺银行之银行间流动挤兑冲击
B10: 名称填充色 | C10: 退出的。 | E10: 数字填充色 | F10: 变化的，因为破产银行之银行间流动挤兑冲击
E11: 数字填充色 | F11: 变化的，因为破产银行清算影响
E12: 数字填充色 | F12: 变化的，因为回合结束前，手动清零部分冲击，这些冲击不影响下一回合运行
B13: 说明 | C13: 深色表示相关状态的，浅色表示被影响的，更深色表示已经处理完毕的。 | E13: 字体颜色 | F13: 在银行只变量集之内的，手动设定的数字
E14: 字体颜色 | F14: 在银行之变量集之内的，由Excel公式计算设定的数字
E15: 字体颜色 | F15: 在银行之变量集之外的，由Excel公式计算设定的数字
E16: 字体颜色 | F16: 有疑问的，需要解决的
E19: 说明 | F19: 深色表示相关状态的，浅色表示被影响的，更深色表示已经处理完毕的。

Sheet 参数
A1: 贷款损失率； | B1: 可担保资产用于获取回购资金时的折价率； | C1: 召回流动资产以获取流动性，召回比例 | D1: 外生给定现金储备率； | E1: 所有者权益占比； | F1: 可担保资产占比； | G1: 各银行之同业资产之和比上各银行之总资产之和；
A2: LGD | B2: HR | C2: WR | D2: CRR | E2: ER | F2: CAR | G2: TIBAR
A3: 0.4 | B3: 0.1 | C3: 0.2 | D3: 0.02 | E3: 0.05 | F3: 0.1 | G3: 0.3

Sheet BB之过程-theta_Shock_exBI_t=1
A1: 子过程 | B1: tau | C1: t | D1: id | E1: name | F1: A_R | G1: A_Q | H1: A_P | I1: A_other | J1: A_exBI | K1: A_BI_all | L1: A_all | M1: Z_D | N1: Z_other | O1: Z_exBI | P1: Z_BI_all | Q1: Z_all | R1: E_all | S1: Bo_D | T1: Li_P | U1: Lo_BI_all | V1: Li_BI_all | W1: Bi_BI_all | X1: Bo_BI_all | Y1: Shock_B_A | Z1: Shock_B_Z | AA1: Shock_B_def_t | AB1: Shock_B_run_t | AC1: BB.Shock_P_def_t | AD1: BB.Shock_D_def_s | AE1: BB.Shock_D_run_t | AF1: BB.Shock_P_run_s | AG1: BB.Shock_BI_def_s | AH1: BB.Shock_BI_def_t | AI1: BB.Shock_BI_run_ilq_s | AJ1: BB.Shock_BI_run_ilq_t | AK1: BB.Shock_BI_run_br_s | AL1: BB.Shock_BI_run_br_t | AM1: BB.Shock_BI_run_s | AN1: BB.Shock_BI_run_t | AO1: BB.Shock_BI_s | AP1: BB.Shock_BI_t | AR1: name | AS1: A_R | AT1: A_Q | AU1: A_P | AV1: A_other | AW1: A_exBI | AX1: A_BI_all | AY1: A_all | AZ1: Z_D | BA1: Z_other | BB1: Z_exBI | BC1: Z_BI_all | BD1: Z_all | BE1: E_all | BF1: Shock_B_A | BG1: Shock_B_Z | BH1: BB.Shock_L_exBI_s | BI1: BB.Shock_D_s | BJ1: BB.Shock_BI_def_s | BK1: BB.Shock_BI_run_ilq_s | BL1: BB.Shock_BI_run_br_s | BM1: BB.Shock_BI_def_t | BN1: BB.Shock_BI_run_ilq_t | BO1: BB.Shock_BI_run_br_t | BP1: BB.Shock_BI_run_s | BQ1: BB.Shock_BI_run_t | BR1: BB.Shock_BI_s | BS1: BB.Shock_BI_t
A2: 1 | B2: 1 | C2: 0 | D2: 1 | E2: BK1 | F2: 0 | G2: 477.125 | H2: 1631.73 | I2: 0 | J2: =F2+G2+H2+I2 -> 2108.855 | K2: 2185.24 | L2: =J2+K2 -> 4294.095 | M2: 3160.99 | N2: 0 | O2: =M2+N2 -> 3160.99 | P2: 959.6 | Q2: =P2+O2 -> 4120.59 | R2: =MAX(L2-Q2,0) -> 173.505 | S2: 0 | T2: 0 | U2: 0 | V2: 0 | W2: 0 | X2: 0 | Y2: 0 | Z2: 0 | AA2: =AC2+AH2 -> 1631.73 | AB2: =AE2+AN2 -> 0 | AC2: 1631.73 | AD2: 0 | AE2: 0 | AF2: 0 | AG2: 0 | AH2: 0 | AI2: 0 | AJ2: 0 | AK2: 0 | AL2: 0 | AM2: =AI2+AK2 -> 0 | AN2: =AJ2+AL2 -> 0 | AO2: =AG2+AM2 -> 0 | AP2: =AH2+AN2 -> 0
D3: 2 | E3: BK2 | F3: 0 | G3: 587.693 | H3: 4303.24 | I3: 0 | J3: =F3+G3+H3+I3 -> 4890.933 | K3: 398.37 | L3: =J3+K3 -> 5289.303 | M3: 3231.37 | N3: 0 | O3: =M3+N3 -> 3231.37 | P3: 1844.24 | Q3: =P3+O3 -> 5075.61 | R3: =MAX(L3-Q3,0) -> 213.693 | S3: 0 | T3: 0 | U3: 0 | V3: 0 | W3: 0 | X3: 0 | Y3: 0 | Z3: 0 | AA3: =AC3+AH3 -> 0 | AB3: =AE3+AN3 -> 0 | AC3: 0 | AD3: 0 | AE3: 0 | AF3: 0 | AG3: 0 | AH3: 0 | AI3: 0 | AJ3: 0 | AK3: 0 | AL3: 0 | AM3: =AI3+AK3 -> 0 | AN3: =AJ3+AL3 -> 0 | AO3: =AG3+AM3 -> 0 | AP3: =AH3+AN3 -> 0
D4: 3 | E4: BK3 | F4: 0 | G4: 513.847 | H4: 3379.72 | I4: 0 | J4: =F4+G4+H4+I4 -> 3893.567 | K4: 730.99 | L4: =J4+K4 -> 4624.557 | M4: 3184.36 | N4: 0 | O4: =M4+N4 -> 3184.36 | P4: 1253.34 | Q4: =P4+O4 -> 4437.7 | R4: =MAX(L4-Q4,0) -> 186.857 | S4: 0 | T4: 0 | U4: 0 | V4: 0 | W4: 0 | X4: 0 | Y4: 0 | Z4: 0 | AA4: =AC4+AH4 -> 0 | AB4: =AE4+AN4 -> 0 | AC4: 0 | AD4: 0 | AE4: 0 | AF4: 0 | AG4: 0 | AH4: 0 | AI4: 0 | AJ4: 0 | AK4: 0 | AL4: 0 | AM4: =AI4+AK4 -> 0 | AN4: =AJ4+AL4 -> 0 | AO4: =AG4+AM4 -> 0 | AP4: =AH4+AN4 -> 0
D5: 4 | E5: BK4 | F5: 0 | G5: 713.662 | H5: 4351.47 | I5: 0 | J5: =F5+G5+H5+I5 -> 5065.132 | K5: 1357.75 | L5: =J5+K5 -> 6422.882 | M5: 3311.51 | N5: 0 | O5: =M5+N5 -> 3311.51 | P5: 2851.85 | Q5: =P5+O5 -> 6163.36 | R5: =MAX(L5-Q5,0) -> 259.522 | S5: 0 | T5: 0 | U5: 0 | V5: 0 | W5: 0 | X5: 0 | Y5: 0 | Z5: 0 | AA5: =AC5+AH5 -> 0 | AB5: =AE5+AN5 -> 0 | AC5: 0 | AD5: 0 | AE5: 0 | AF5: 0 | AG5: 0 | AH5: 0 | AI5: 0 | AJ5: 0 | AK5: 0 | AL5: 0 | AM5: =AI5+AK5 -> 0 | AN5: =AJ5+AL5 -> 0 | AO5: =AG5+AM5 -> 0 | AP5: =AH5+AN5 -> 0
D6: 5 | E6: BK5 | F6: 0 | G6: 417.257 | H6: 620.69 | I6: 0 | J6: =F6+G6+H6+I6 -> 1037.947 | K6: 2717.39 | L6: =J6+K6 -> 3755.337 | M6: 3122.9 | N6: 0 | O6: =M6+N6 -> 3122.9 | P6: 480.71 | Q6: =P6+O6 -> 3603.61 | R6: =MAX(L6-Q6,0) -> 151.727 | S6: 0 | T6: 0 | U6: 0 | V6: 0 | W6: 0 | X6: 0 | Y6: 0 | Z6: 0 | AA6: =AC6+AH6 -> 0 | AB6: =AE6+AN6 -> 0 | AC6: 0 | AD6: 0 | AE6: 0 | AF6: 0 | AG6: 0 | AH6: 0 | AI6: 0 | AJ6: 0 | AK6: 0 | AL6: 0 | AM6: =AI6+AK6 -> 0 | AN6: =AJ6+AL6 -> 0 | AO6: =AG6+AM6 -> 0 | AP6: =AH6+AN6 -> 0
F7: =SUM(F2:F6) -> 0 | G7: =SUM(G2:G6) -> 2709.584 | H7: =SUM(H2:H6) -> 14286.85 | I7: =SUM(I2:I6) -> 0 | J7: =SUM(J2:J6) -> 16996.434 | K7: =SUM(K2:K6) -> 7389.74 | L7: =SUM(L2:L6) -> 24386.174 | M7: =SUM(M2:M6) -> 16011.13 | ... AP7: =SUM(AP2:AP6) -> 0
B9: 1 | C9: 1 | D9: 1 | E9: BK1 | F9: 0 | G9: 477.125 | H9: 1631.73 | I9: 0 | J9: =F9+G9+H9+I9 -> 2108.855 | K9: 2185.24 | L9: =J9+K9 -> 4294.095 | M9: 3160.99 | N9: 0 | O9: =M9+N9 -> 3160.99 | P9: 959.6 | Q9: =P9+O9 -> 4120.59 | R9: =MAX(L9-Q9,0) -> 173.505 | S9: 0 | T9: 0 | U9: 0 | V9: 0 | W9: 0 | X9: 0 | Y9: 1631.73 | Z9: 0 | AA9: =AC9+AH9 -> 1631.73 | AB9: =AE9+AN9 -> 0 | AC9: 1631.73 | AD9: 0 | AE9: 0 | AF9: 0 | AG9: 0 | AH9: 0 | AI9: 0 | AJ9: 0 | AK9: 0 | AL9: 0 | AM9: =AI9+AK9 -> 0 | AN9: =AJ9+AL9 -> 0 | AO9: =AG9+AM9 -> 0 | AP9: =AH9+AN9 -> 0
D10: 2 | E10: BK2 | F10: 0 | G10: 587.693 | H10: 4303.24 | I10: 0 | J10: =F10+G10+H10+I10 -> 4890.933 | K10: 398.37 | L10: =J10+K10 -> 5289.303 | M10: 3231.37 | N10: 0 | O10: =M10+N10 -> 3231.37 | P10: 1844.24 | Q10: =P10+O10 -> 5075.61 | R10: =MAX(L10-Q10,0) -> 213.693 | S10: 0 | T10: 0 | U10: 0 | V10: 0 | W10: 0 | X10: 0 | Y10: 0 | Z10: 0 | AA10: =AC10+AH10 -> 0 | AB10: =AE10+AN10 -> 0 | AC10: 0 | AD10: 0 | AE10: 0 | AF10: 0 | AG10: 0 | AH10: 0 | AI10: 0 | AJ10: 0 | AK10: 0 | AL10: 0 | AM10: =AI10+AK10 -> 0 | AN10: =AJ10+AL10 -> 0 | AO10: =AG10+AM10 -> 0 | AP10: =AH10+AN10 -> 0
D11: 3 | E11: BK3 | F11: 0 | G11: 513.847 | H11: 3379.72 | I11: 0 | J11: =F11+G11+H11+I11 -> 3893.567 | K11: 730.99 | L11: =J11+K11 -> 4624.557 | M11: 3184.36 | N11: 0 | O11: =M11+N11 -> 3184.36 | P11: 1253.34 | Q11: =P11+O11 -> 4437.7 | R11: =MAX(L11-Q11,0) -> 186.857 | S11: 0 | T11: 0 | U11: 0 | V11: 0 | W11: 0 | X11: 0 | Y11: 0 | Z11: 0 | AA11: =AC11+AH11 -> 0 | AB11: =AE11+AN11 -> 0 | AC11: 0 | AD11: 0 | AE11: 0 | AF11: 0 | AG11: 0 | AH11: 0 | AI11: 0 | AJ11: 0 | AK11: 0 | AL11: 0 | AM11: =AI11+AK11 -> 0 | AN11: =AJ11+AL11 -> 0 | AO11: =AG11+AM11 -> 0 | AP11: =AH11+AN11 -> 0
D12: 4 | E12: BK4 | F12: 0 | G12: 713.662 | H12: 4351.47 | I12: 0 | J12: =F12+G12+H12+I12 -> 5065.132 | K12: 1357.75 | L12: =J12+K12 -> 6422.882 | M12: 3311.51 | N12: 0 | O12: =M12+N12 -> 3311.51 | P12: 2851.85 | Q12: =P12+O12 -> 6163.36 | R12: =MAX(L12-Q12,0) -> 259.522 | S12: 0 | T12: 0 | U12: 0 | V12: 0 | W12: 0 | X12: 0 | Y12: 0 | Z12: 0 | AA12: =AC12+AH12 -> 0 | AB12: =AE12+AN12 -> 0 | AC12: 0 | AD12: 0 | AE12: 0 | AF12: 0 | AG12: 0 | AH12: 0 | AI12: 0 | AJ12: 0 | AK12: 0 | AL12: 0 | AM12: =AI12+AK12 -> 0 | AN12: =AJ12+AL12 -> 0 | AO12: =AG12+AM12 -> 0 | AP12: =AH12+AN12 -> 0
D13: 5 | E13: BK5 | F13: 0 | G13: 417.257 | H13: 620.69 | I13: 0 | J13: =F13+G13+H13+I13 -> 1037.947 | K13: 2717.39 | L13: =J13+K13 -> 3755.337 | M13: 3122.9 | N13: 0 | O13: =M13+N13 -> 3122.9 | P13: 480.71 | Q13: =P13+O13 -> 3603.61 | R13: =MAX(L13-Q13,0) -> 151.727 | S13: 0 | T13: 0 | U13: 0 | V13: 0 | W13: 0 | X13: 0 | Y13: 0 | Z13: 0 | AA13: =AC13+AH13 -> 0 | AB13: =AE13+AN13 -> 0 | AC13: 0 | AD13: 0 | AE13: 0 | AF13: 0 | AG13: 0 | AH13: 0 | AI13: 0 | AJ13: 0 | AK13: 0 | AL13: 0 | AM13: =AI13+AK13 -> 0 | AN13: =AJ13+AL13 -> 0 | AO13: =AG13+AM13 -> 0 | AP13: =AH13+AN13 -> 0
F14: =SUM(F9:F13) -> 0 | G14: =SUM(G9:G13) -> 2709.584 | H14: =SUM(H9:H13) -> 14286.85 | I14: =SUM(I9:I13) -> 0 | J14: =SUM(J9:J13) -> 16996.434 | K14: =SUM(K9:K13) -> 7389.74 | L14: =SUM(L9:L13) -> 24386.174 | M14: =SUM(M9:M13) -> 16011.13 | ... AP14: =SUM(AP9:AP13) -> 0
B16: 1 | C16: 2 | D16: 1 | E16: BK1 | F16: 0 | G16: 477.125 | H16: 0 | I16: 0 | J16: =F16+G16+H16+I16 -> 477.125 | K16: 2185.24 | L16: =J16+K16 -> 2662.365 | M16: 2042.355 | N16: 0 | O16: =M16+N16 -> 2042.355 | P16: 620.009 | Q16: =P16+O16 -> 2662.364 | R16: 0 | S16: 0 | T16: 0 | U16: 0 | V16: 0 | W16: 0 | X16: 0 | Y16: 1631.73 | Z16: 0 | AA16: =AC16+AH16 -> 0 | AB16: =AE16+AN16 -> 0 | AC16: 0 | AD16: 1118.6423 | AE16: 0 | AF16: 0 | AG16: 339.6 | AH16: 0 | AI16: 0 | AJ16: 0 | AK16: 0 | AL16: 0 | AM16: =AI16+AK16 -> 0 | AN16: =AJ16+AL16 -> 0 | AO16: =AG16+AM16 -> 339.6 | AP16: =AH16+AN16 -> 0
D17: 2 | E17: BK2 | F17: 0 | G17: 587.693 | H17: 4303.24 | I17: 0 | J17: =F17+G17+H17+I17 -> 4890.933 | K17: 398.37 | L17: =J17+K17 -> 5289.303 | M17: 3231.37 | N17: 0 | O17: =M17+N17 -> 3231.37 | P17: 1844.24 | Q17: =P17+O17 -> 5075.61 | R17: 213.693 | S17: 0 | T17: 0 | U17: 0 | V17: 0 | W17: 0 | X17: 0 | Y17: 0 | Z17: 0 | AA17: =AC17+AH17 -> 0 | AB17: =AE17+AN17 -> 0 | AC17: 0 | AD17: 0 | AE17: 0 | AF17: 0 | AG17: 0 | AH17: 0 | AI17: 0 | AJ17: 0 | AK17: 0 | AL17: 0 | AM17: =AI17+AK17 -> 0 | AN17: =AJ17+AL17 -> 0 | AO17: =AG17+AM17 -> 0 | AP17: =AH17+AN17 -> 0
D18: 3 | E18: BK3 | F18: 0 | G18: 513.847 | H18: 3379.72 | I18: 0 | J18: =F18+G18+H18+I18 -> 3893.567 | K18: 730.99 | L18: =J18+K18 -> 4624.557 | M18: 3184.36 | N18: 0 | O18: =M18+N18 -> 3184.36 | P18: 1253.34 | Q18: =P18+O18 -> 4437.7 | R18: 186.857 | S18: 0 | T18: 0 | U18: 0 | V18: 0 | W18: 0 | X18: 0 | Y18: 0 | Z18: 0 | AA18: =AC18+AH18 -> 0 | AB18: =AE18+AN18 -> 0 | AC18: 0 | AD18: 0 | AE18: 0 | AF18: 0 | AG18: 0 | AH18: 0 | AI18: 0 | AJ18: 0 | AK18: 0 | AL18: 0 | AM18: =AI18+AK18 -> 0 | AN18: =AJ18+AL18 -> 0 | AO18: =AG18+AM18 -> 0 | AP18: =AH18+AN18 -> 0
D19: 4 | E19: BK4 | F19: 0 | G19: 713.662 | H19: 4351.47 | I19: 0 | J19: =F19+G19+H19+I19 -> 5065.132 | K19: 1357.75 | L19: =J19+K19 -> 6422.882 | M19: 3311.51 | N19: 0 | O19: =M19+N19 -> 3311.51 | P19: 2851.85 | Q19: =P19+O19 -> 6163.36 | R19: 259.522 | S19: 0 | T19: 0 | U19: 0 | V19: 0 | W19: 0 | X19: 0 | Y19: 0 | Z19: 0 | AA19: =AC19+AH19 -> 0 | AB19: =AE19+AN19 -> 0 | AC19: 0 | AD19: 0 | AE19: 0 | AF19: 0 | AG19: 0 | AH19: 0 | AI19: 0 | AJ19: 0 | AK19: 0 | AL19: 0 | AM19: =AI19+AK19 -> 0 | AN19: =AJ19+AL19 -> 0 | AO19: =AG19+AM19 -> 0 | AP19: =AH19+AN19 -> 0
D20: 5 | E20: BK5 | F20: 0 | G20: 417.257 | H20: 620.69 | I20: 0 | J20: =F20+G20+H20+I20 -> 1037.947 | K20: 2717.39 | L20: =J20+K20 -> 3755.337 | M20: 3122.9 | N20: 0 | O20: =M20+N20 -> 3122.9 | P20: 480.71 | Q20: =P20+O20 -> 3603.61 | R20: 151.727 | S20: 0 | T20: 0 | U20: 0 | V20: 0 | W20: 0 | X20: 0 | Y20: 0 | Z20: 0 | AA20: =AC20+AH20 -> 0 | AB20: =AE20+AN20 -> 0 | AC20: 0 | AD20: 0 | AE20: 0 | AF20: 0 | AG20: 0 | AH20: 0 | AI20: 0 | AJ20: 0 | AK20: 0 | AL20: 0 | AM20: =AI20+AK20 -> 0 | AN20: =AJ20+AL20 -> 0 | AO20: =AG20+AM20 -> 0 | AP20: =AH20+AN20 -> 0
F21: =SUM(F16:F20) -> 0 | G21: =SUM(G16:G20) -> 2709.584 | H21: =SUM(H16:H20) -> 12655.12 | I21: =SUM(I16:I20) -> 0 | J21: =SUM(J16:J20) -> 15364.704 | K21: =SUM(K16:K20) -> 7389.74 | L21: =SUM(L16:L20) -> 22754.444 | M21: =SUM(M16:M20) -> 14892.495 | ... AP21: =SUM(AP16:AP20) -> 0
B23: 2 | C23: 1 | D23: 1 | E23: BK1 | F23: 0 | G23: 477.125 | H23: 0 | I23: 0 | J23: =F23+G23+H23+I23 -> 477.125 | K23: 2185.24 | L23: =J23+K23 -> 2662.365 | M23: 2042.355 | N23: 0 | O23: =M23+N23 -> 2042.355 | P23: 620.009 | Q23: =P23+O23 -> 2662.364 | R23: 0 | S23: 0 | T23: 0 | U23: 0 | V23: 0 | W23: 0 | X23: 0 | Y23: 0 | Z23: 0 | AA23: =AC23+AH23 -> 0 | AB23: =AE23+AN23 -> 0 | AC23: 0 | AD23: 1118.6423 | AE23: 0 | AF23: 0 | AG23: 339.6 | AH23: 0 | AI23: 0 | AJ23: 0 | AK23: 0 | AL23: 0 | AM23: =AI23+AK23 -> 0 | AN23: =AJ23+AL23 -> 0 | AO23: =AG23+AM23 -> 339.6 | AP23: =AH23+AN23 -> 0
D24: 2 | E24: BK2 | F24: 0 | G24: 587.693 | H24: 4303.24 | I24: 0 | J24: =F24+G24+H24+I24 -> 4890.933 | K24: 398.37 | L24: =J24+K24 -> 5289.303 | M24: 3231.37 | N24: 0 | O24: =M24+N24 -> 3231.37 | P24: 1844.24 | Q24: =P24+O24 -> 5075.61 | R24: 213.693 | S24: 0 | T24: 0 | U24: 0 | V24: 0 | W24: 0 | X24: 0 | Y24: 38.698 | Z24: 0 | AA24: =AC24+AH24 -> 38.698 | AB24: =AE24+AN24 -> 0 | AC24: 0 | AD24: 0 | AE24: 0 | AF24: 0 | AG24: 0 | AH24: 38.698 | AI24: 0 | AJ24: 0 | AK24: 0 | AL24: 0 | AM24: =AI24+AK24 -> 0 | AN24: =AJ24+AL24 -> 0 | AO24: =AG24+AM24 -> 0 | AP24: =AH24+AN24 -> 38.698
D25: 3 | E25: BK3 | F25: 0 | G25: 513.847 | H25: 3379.72 | I25: 0 | J25: =F25+G25+H25+I25 -> 3893.567 | K25: 730.99 | L25: =J25+K25 -> 4624.557 | M25: 3184.36 | N25: 0 | O25: =M25+N25 -> 3184.36 | P25: 1253.34 | Q25: =P25+O25 -> 4437.7 | R25: 186.857 | S25: 0 | T25: 0 | U25: 0 | V25: 0 | W25: 0 | X25: 0 | Y25: 258.688 | Z25: 0 | AA25: =AC25+AH25 -> 258.688 | AB25: =AE25+AN25 -> 0 | AC25: 0 | AD25: 0 | AE25: 0 | AF25: 0 | AG25: 0 | AH25: 258.688 | AI25: 0 | AJ25: 0 | AK25: 0 | AL25: 0 | AM25: =AI25+AK25 -> 0 | AN25: =AJ25+AL25 -> 0 | AO25: =AG25+AM25 -> 0 | AP25: =AH25+AN25 -> 258.688
D26: 4 | E26: BK4 | F26: 0 | G26: 713.662 | H26: 4351.47 | I26: 0 | J26: =F26+G26+H26+I26 -> 5065.132 | K26: 1357.75 | L26: =J26+K26 -> 6422.882 | M26: 3311.51 | N26: 0 | O26: =M26+N26 -> 3311.51 | P26: 2851.85 | Q26: =P26+O26 -> 6163.36 | R26: 259.522 | S26: 0 | T26: 0 | U26: 0 | V26: 0 | W26: 0 | X26: 0 | Y26: 42.205 | Z26: 0 | AA26: =AC26+AH26 -> 42.205 | AB26: =AE26+AN26 -> 0 | AC26: 0 | AD26: 0 | AE26: 0 | AF26: 0 | AG26: 0 | AH26: 42.205 | AI26: 0 | AJ26: 0 | AK26: 0 | AL26: 0 | AM26: =AI26+AK26 -> 0 | AN26: =AJ26+AL26 -> 0 | AO26: =AG26+AM26 -> 0 | AP26: =AH26+AN26 -> 42.205
D27: 5 | E27: BK5 | F27: 0 | G27: 417.257 | H27: 620.69 | I27: 0 | J27: =F27+G27+H27+I27 -> 1037.947 | K27: 2717.39 | L27: =J27+K27 -> 3755.337 | M27: 3122.9 | N27: 0 | O27: =M27+N27 -> 3122.9 | P27: 480.71 | Q27: =P27+O27 -> 3603.61 | R27: 151.727 | S27: 0 | T27: 0 | U27: 0 | V27: 0 | W27: 0 | X27: 0 | Y27: 0 | Z27: 0 | AA27: =AC27+AH27 -> 0 | AB27: =AE27+AN27 -> 0 | AC27: 0 | AD27: 0 | AE27: 0 | AF27: 0 | AG27: 0 | AH27: 0 | AI27: 0 | AJ27: 0 | AK27: 0 | AL27: 0 | AM27: =AI27+AK27 -> 0 | AN27: =AJ27+AL27 -> 0 | AO27: =AG27+AM27 -> 0 | AP27: =AH27+AN27 -> 0
F28: =SUM(F23:F27) -> 0 | G28: =SUM(G23:G27) -> 2709.584 | H28: =SUM(H23:H27) -> 12655.12 | I28: =SUM(I23:I27) -> 0 | J28: =SUM(J23:J27) -> 15364.704 | K28: =SUM(K23:K27) -> 7389.74 | L28: =SUM(L23:L27) -> 22754.444 | M28: =SUM(M23:M27) -> 14892.495 | ... AP28: =SUM(AP23:AP27) -> 339.591
B30: 2 | C30: 2 | D30: 1 | E30: BK1 | F30: 0 | G30: 477.125 | H30: 0 | I30: 0 | J30: =F30+G30+H30+I30 -> 477.125 | K30: 2185.24 | L30: =J30+K30 -> 2662.365 | M30: 2042.355 | N30: 0 | O30: =M30+N30 -> 2042.355 | P30: 620.009 | Q30: =P30+O30 -> 2662.364 | R30: 0 | S30: 0 | T30: 0 | U30: 0 | V30: 0 | W30: 0 | X30: 0 | Y30: 0 | Z30: 0 | AA30: =AC30+AH30 -> 0 | AB30: =AE30+AN30 -> 0 | AC30: 0 | AD30: 0 | AE30: 0 | AF30: 0 | AG30: 0 | AH30: 0 | AI30: 0 | AJ30: 0 | AK30: 0 | AL30: 0 | AM30: =AI30+AK30 -> 0 | AN30: =AJ30+AL30 -> 0 | AO30: =AG30+AM30 -> 0 | AP30: =AH30+AN30 -> 0
D31: 2 | E31: BK2 | F31: 0 | G31: 587.693 | H31: 4303.24 | I31: 0 | J31: =F31+G31+H31+I31 -> 4890.933 | K31: 359.67215 | L31: =J31+K31 -> 5250.6052 | M31: 3231.37 | N31: 0 | O31: =M31+N31 -> 3231.37 | P31: 1844.24 | Q31: =P31+O31 -> 5075.61 | R31: 174.98502 | S31: 0 | T31: 0 | U31: 0 | V31: 0 | W31: 0 | X31: 0 | Y31: 38.698 | Z31: 0 | AA31: =AC31+AH31 -> 38.698 | AB31: =AE31+AN31 -> 0 | AC31: 0 | AD31: 0 | AE31: 0 | AF31: 0 | AG31: 0 | AH31: 38.698 | AI31: 0 | AJ31: 0 | AK31: 0 | AL31: 0 | AM31: =AI31+AK31 -> 0 | AN31: =AJ31+AL31 -> 0 | AO31: =AG31+AM31 -> 0 | AP31: =AH31+AN31 -> 38.698
D32: 3 | E32: BK3 | F32: 0 | G32: 513.847 | H32: 3379.72 | I32: 0 | J32: =F32+G32+H32+I32 -> 3893.567 | K32: 472.30005 | L32: =J32+K32 -> 4365.867 | M32: 3132.8074 | N32: 0 | O32: =M32+N32 -> 3132.8074 | P32: 1233.0492 | Q32: =P32+O32 -> 4365.8566 | R32: 0 | S32: 0 | T32: 0 | U32: 0 | V32: 0 | W32: 0 | X32: 0 | Y32: 258.688 | Z32: 0 | AA32: =AC32+AH32 -> 258.688 | AB32: =AE32+AN32 -> 0 | AC32: 0 | AD32: 51.552734 | AE32: 0 | AF32: 0 | AG32: 20.290771 | AH32: 258.688 | AI32: 0 | AJ32: 0 | AK32: 0 | AL32: 0 | AM32: =AI32+AK32 -> 0 | AN32: =AJ32+AL32 -> 0 | AO32: =AG32+AM32 -> 20.290771 | AP32: =AH32+AN32 -> 258.688
D33: 4 | E33: BK4 | F33: 0 | G33: 713.662 | H33: 4351.47 | I33: 0 | J33: =F33+G33+H33+I33 -> 5065.132 | K33: 1315.545 | L33: =J33+K33 -> 6380.677 | M33: 3311.51 | N33: 0 | O33: =M33+N33 -> 3311.51 | P33: 2851.85 | Q33: =P33+O33 -> 6163.36 | R33: 217.30754 | S33: 0 | T33: 0 | U33: 0 | V33: 0 | W33: 0 | X33: 0 | Y33: 42.205 | Z33: 0 | AA33: =AC33+AH33 -> 42.205 | AB33: =AE33+AN33 -> 0 | AC33: 0 | AD33: 0 | AE33: 0 | AF33: 0 | AG33: 0 | AH33: 42.205 | AI33: 0 | AJ33: 0 | AK33: 0 | AL33: 0 | AM33: =AI33+AK33 -> 0 | AN33: =AJ33+AL33 -> 0 | AO33: =AG33+AM33 -> 0 | AP33: =AH33+AN33 -> 42.205
D34: 5 | E34: BK5 | F34: 0 | G34: 417.257 | H34: 620.69 | I34: 0 | J34: =F34+G34+H34+I34 -> 1037.947 | K34: 2717.39 | L34: =J34+K34 -> 3755.337 | M34: 3122.9 | N34: 0 | O34: =M34+N34 -> 3122.9 | P34: 480.71 | Q34: =P34+O34 -> 3603.61 | R34: 151.727 | S34: 0 | T34: 0 | U34: 0 | V34: 0 | W34: 0 | X34: 0 | Y34: 0 | Z34: 0 | AA34: =AC34+AH34 -> 0 | AB34: =AE34+AN34 -> 0 | AC34: 0 | AD34: 0 | AE34: 0 | AF34: 0 | AG34: 0 | AH34: 0 | AI34: 0 | AJ34: 0 | AK34: 0 | AL34: 0 | AM34: =AI34+AK34 -> 0 | AN34: =AJ34+AL34 -> 0 | AO34: =AG34+AM34 -> 0 | AP34: =AH34+AN34 -> 0
F35: =SUM(F30:F34) -> 0 | G35: =SUM(G30:G34) -> 2709.584 | H35: =SUM(H30:H34) -> 12655.12 | I35: =SUM(I30:I34) -> 0 | J35: =SUM(J30:J34) -> 15364.704 | K35: =SUM(K30:K34) -> 7050.1472 | L35: =SUM(L30:L34) -> 22414.851 | M35: =SUM(M30:M34) -> 14840.942 | ... AP35: =SUM(AP30:AP34) -> 339.591
B37: 3 | C37: 1 | D37: 1 | E37: BK1 | F37: 0 | G37: 477.125 | H37: 0 | I37: 0 | J37: =F37+G37+H37+I37 -> 477.125 | K37: 2185.24 | L37: =J37+K37 -> 2662.365 | M37: 2042.355 | N37: 0 | O37: =M37+N37 -> 2042.355 | P37: 620.009 | Q37: =P37+O37 -> 2662.364 | R37: 0 | S37: 0 | T37: 0 | U37: 0 | V37: 0 | W37: 0 | X37: 0 | Y37: 0 | Z37: 0 | AA37: =AC37+AH37 -> 0 | AB37: =AE37+AN37 -> 0 | AC37: 0 | AD37: 0 | AE37: 0 | AF37: 0 | AG37: 0 | AH37: 0 | AI37: 0 | AJ37: 0 | AK37: 0 | AL37: 0 | AM37: =AI37+AK37 -> 0 | AN37: =AJ37+AL37 -> 0 | AO37: =AG37+AM37 -> 0 | AP37: =AH37+AN37 -> 0
D38: 2 | E38: BK2 | F38: 0 | G38: 587.693 | H38: 4303.24 | I38: 0 | J38: =F38+G38+H38+I38 -> 4890.933 | K38: 359.67215 | L38: =J38+K38 -> 5250.6052 | M38: 3231.37 | N38: 0 | O38: =M38+N38 -> 3231.37 | P38: 1844.24 | Q38: =P38+O38 -> 5075.61 | R38: 174.98502 | S38: 0 | T38: 0 | U38: 0 | V38: 0 | W38: 0 | X38: 0 | Y38: 4.67905 | Z38: 0 | AA38: =AC38+AH38 -> 4.67905 | AB38: =AE38+AN38 -> 0 | AC38: 0 | AD38: 0 | AE38: 0 | AF38: 0 | AG38: 0 | AH38: 4.67905 | AI38: 0 | AJ38: 0 | AK38: 0 | AL38: 0 | AM38: =AI38+AK38 -> 0 | AN38: =AJ38+AL38 -> 0 | AO38: =AG38+AM38 -> 0 | AP38: =AH38+AN38 -> 4.67905
D39: 3 | E39: BK3 | F39: 0 | G39: 513.847 | H39: 3379.72 | I39: 0 | J39: =F39+G39+H39+I39 -> 3893.567 | K39: 472.30005 | L39: =J39+K39 -> 4365.867 | M39: 3132.8074 | N39: 0 | O39: =M39+N39 -> 3132.8074 | P39: 1233.0492 | Q39: =P39+O39 -> 4365.8566 | R39: 0 | S39: 0 | T39: 0 | U39: 0 | V39: 0 | W39: 0 | X39: 0 | Y39: 0 | Z39: 0 | AA39: =AC39+AH39 -> 0 | AB39: =AE39+AN39 -> 0 | AC39: 0 | AD39: 51.552734 | AE39: 0 | AF39: 0 | AG39: 20.290771 | AH39: 0 | AI39: 0 | AJ39: 0 | AK39: 0 | AL39: 0 | AM39: =AI39+AK39 -> 0 | AN39: =AJ39+AL39 -> 0 | AO39: =AG39+AM39 -> 20.290771 | AP39: =AH39+AN39 -> 0
D40: 4 | E40: BK4 | F40: 0 | G40: 713.662 | H40: 4351.47 | I40: 0 | J40: =F40+G40+H40+I40 -> 5065.132 | K40: 1315.545 | L40: =J40+K40 -> 6380.677 | M40: 3311.51 | N40: 0 | O40: =M40+N40 -> 3311.51 | P40: 2851.85 | Q40: =P40+O40 -> 6163.36 | R40: 217.30754 | S40: 0 | T40: 0 | U40: 0 | V40: 0 | W40: 0 | X40: 0 | Y40: 15.6117 | Z40: 0 | AA40: =AC40+AH40 -> 15.6117 | AB40: =AE40+AN40 -> 0 | AC40: 0 | AD40: 0 | AE40: 0 | AF40: 0 | AG40: 0 | AH40: 15.6117 | AI40: 0 | AJ40: 0 | AK40: 0 | AL40: 0 | AM40: =AI40+AK40 -> 0 | AN40: =AJ40+AL40 -> 0 | AO40: =AG40+AM40 -> 0 | AP40: =AH40+AN40 -> 15.6117
D41: 5 | E41: BK5 | F41: 0 | G41: 417.257 | H41: 620.69 | I41: 0 | J41: =F41+G41+H41+I41 -> 1037.947 | K41: 2717.39 | L41: =J41+K41 -> 3755.337 | M41: 3122.9 | N41: 0 | O41: =M41+N41 -> 3122.9 | P41: 480.71 | Q41: =P41+O41 -> 3603.61 | R41: 151.727 | S41: 0 | T41: 0 | U41: 0 | V41: 0 | W41: 0 | X41: 0 | Y41: 0 | Z41: 0 | AA41: =AC41+AH41 -> 0 | AB41: =AE41+AN41 -> 0 | AC41: 0 | AD41: 0 | AE41: 0 | AF41: 0 | AG41: 0 | AH41: 0 | AI41: 0 | AJ41: 0 | AK41: 0 | AL41: 0 | AM41: =AI41+AK41 -> 0 | AN41: =AJ41+AL41 -> 0 | AO41: =AG41+AM41 -> 0 | AP41: =AH41+AN41 -> 0
F42: =SUM(F37:F41) -> 0 | G42: =SUM(G37:G41) -> 2709.584 | H42: =SUM(H37:H41) -> 12655.12 | I42: =SUM(I37:I41) -> 0 | J42: =SUM(J37:J41) -> 15364.704 | K42: =SUM(K37:K41) -> 7050.1472 | L42: =SUM(L37:L41) -> 22414.851 | M42: =SUM(M37:M41) -> 14840.942 | ... AP42: =SUM(AP37:AP41) -> 20.29075
B44: 3 | C44: 2 | D44: 1 | E44: BK1 | F44: 0 | G44: 477.125 | H44: 0 | I44: 0 | J44: =F44+G44+H44+I44 -> 477.125 | K44: 2185.24 | L44: =J44+K44 -> 2662.365 | M44: 2042.355 | N44: 0 | O44: =M44+N44 -> 2042.355 | P44: 620.009 | Q44: =P44+O44 -> 2662.364 | R44: 0 | S44: 0 | T44: 0 | U44: 0 | V44: 0 | W44: 0 | X44: 0 | Y44: 0 | Z44: 0 | AA44: =AC44+AH44 -> 0 | AB44: =AE44+AN44 -> 0 | AC44: 0 | AD44: 0 | AE44: 0 | AF44: 0 | AG44: 0 | AH44: 0 | AI44: 0 | AJ44: 0 | AK44: 0 | AL44: 0 | AM44: =AI44+AK44 -> 0 | AN44: =AJ44+AL44 -> 0 | AO44: =AG44+AM44 -> 0 | AP44: =AH44+AN44 -> 0
D45: 2 | E45: BK2 | F45: 0 | G45: 587.693 | H45: 4303.24 | I45: 0 | J45: =F45+G45+H45+I45 -> 4890.933 | K45: 354.9931 | L45: =J45+K45 -> 5245.9261 | M45: 3231.37 | N45: 0 | O45: =M45+N45 -> 3231.37 | P45: 1844.24 | Q45: =P45+O45 -> 5075.61 | R45: 170.30597 | S45: 0 | T45: 0 | U45: 0 | V45: 0 | W45: 0 | X45: 0 | Y45: 4.67905 | Z45: 0 | AA45: =AC45+AH45 -> 0 | AB45: =AE45+AN45 -> 0 | AC45: 0 | AD45: 0 | AE45: 0 | AF45: 0 | AG45: 0 | AH45: 0 | AI45: 0 | AJ45: 0 | AK45: 0 | AL45: 0 | AM45: =AI45+AK45 -> 0 | AN45: =AJ45+AL45 -> 0 | AO45: =AG45+AM45 -> 0 | AP45: =AH45+AN45 -> 0
D46: 3 | E46: BK3 | F46: 0 | G46: 513.847 | H46: 3379.72 | I46: 0 | J46: =F46+G46+H46+I46 -> 3893.567 | K46: 472.30005 | L46: =J46+K46 -> 4365.867 | M46: 3132.8074 | N46: 0 | O46: =M46+N46 -> 3132.8074 | P46: 1233.0492 | Q46: =P46+O46 -> 4365.8566 | R46: 0 | S46: 0 | T46: 0 | U46: 0 | V46: 0 | W46: 0 | X46: 0 | Y46: 0 | Z46: 0 | AA46: =AC46+AH46 -> 0 | AB46: =AE46+AN46 -> 0 | AC46: 0 | AD46: 0 | AE46: 0 | AF46: 0 | AG46: 0 | AH46: 0 | AI46: 0 | AJ46: 0 | AK46: 0 | AL46: 0 | AM46: =AI46+AK46 -> 0 | AN46: =AJ46+AL46 -> 0 | AO46: =AG46+AM46 -> 0 | AP46: =AH46+AN46 -> 0
D47: 4 | E47: BK4 | F47: 0 | G47: 713.662 | H47: 4351.47 | I47: 0 | J47: =F47+G47+H47+I47 -> 5065.132 | K47: 1299.9333 | L47: =J47+K47 -> 6365.0653 | M47: 3311.51 | N47: 0 | O47: =M47+N47 -> 3311.51 | P47: 2851.85 | Q47: =P47+O47 -> 6163.36 | R47: 201.69582 | S47: 0 | T47: 0 | U47: 0 | V47: 0 | W47: 0 | X47: 0 | Y47: 15.6117 | Z47: 0 | AA47: =AC47+AH47 -> 0 | AB47: =AE47+AN47 -> 0 | AC47: 0 | AD47: 0 | AE47: 0 | AF47: 0 | AG47: 0 | AH47: 0 | AI47: 0 | AJ47: 0 | AK47: 0 | AL47: 0 | AM47: =AI47+AK47 -> 0 | AN47: =AJ47+AL47 -> 0 | AO47: =AG47+AM47 -> 0 | AP47: =AH47+AN47 -> 0
D48: 5 | E48: BK5 | F48: 0 | G48: 417.257 | H48: 620.69 | I48: 0 | J48: =F48+G48+H48+I48 -> 1037.947 | K48: 2717.39 | L48: =J48+K48 -> 3755.337 | M48: 3122.9 | N48: 0 | O48: =M48+N48 -> 3122.9 | P48: 480.71 | Q48: =P48+O48 -> 3603.61 | R48: 151.727 | S48: 0 | T48: 0 | U48: 0 | V48: 0 | W48: 0 | X48: 0 | Y48: 0 | Z48: 0 | AA48: =AC48+AH48 -> 0 | AB48: =AE48+AN48 -> 0 | AC48: 0 | AD48: 0 | AE48: 0 | AF48: 0 | AG48: 0 | AH48: 0 | AI48: 0 | AJ48: 0 | AK48: 0 | AL48: 0 | AM48: =AI48+AK48 -> 0 | AN48: =AJ48+AL48 -> 0 | AO48: =AG48+AM48 -> 0 | AP48: =AH48+AN48 -> 0
F49: =SUM(F44:F48) -> 0 | G49: =SUM(G44:G48) -> 2709.584 | H49: =SUM(H44:H48) -> 12655.12 | I49: =SUM(I44:I48) -> 0 | J49: =SUM(J44:J48) -> 15364.704 | K49: =SUM(K44:K48) -> 7029.8564 | L49: =SUM(L44:L48) -> 22394.56 | M49: =SUM(M44:M48) -> 14840.942 | ... AP49: =SUM(AP44:AP48) -> 0
A51: 3 | B51: 1 | C51: 1 | D51: 1 | E51: BK1 | F51: 0 | G51: 477.125 | H51: 0 | I51: 0 | J51: =F51+G51+H51+I51 -> 477.125 | K51: 0 | L51: =J51+K51 -> 477.125 | M51: 2042.355 | N51: 0 | O51: =M51+N51 -> 2042.355 | P51: 620.009 | Q51: =P51+O51 -> 2662.364 | R51: 0 | S51: 0 | T51: 0 | U51: 0 | V51: 0 | W51: 0 | X51: 0 | Y51: 0 | Z51: 0 | AA51: =AC51+AH51 -> 0 | AB51: =AE51+AN51 -> 0 | AD51: 0 | AF51: 0 | AG51: 0 | AH51: 0 | AI51: 0 | AJ51: 0 | AK51: 2185.24 | AL51: 0 | AM51: =AI51+AK51 -> 2185.24 | AN51: =AJ51+AL51 -> 0 | AO51: =AG51+AM51 -> 2185.24 | AP51: =AH51+AN51 -> 0
D52: 2 | E52: BK2 | F52: 0 | G52: 587.693 | H52: 4303.24 | I52: 0 | J52: =F52+G52+H52+I52 -> 4890.933 | K52: 354.9931 | L52: =J52+K52 -> 5245.9261 | M52: 3231.37 | N52: 0 | O52: =M52+N52 -> 3231.37 | P52: 1844.24 | Q52: =P52+O52 -> 5075.61 | R52: 170.30597 | S52: 0 | T52: 0 | U52: 0 | V52: 0 | W52: 0 | X52: 0 | Y52: 4.67905 | Z52: 0 | AA52: =AC52+AH52 -> 0 | AB52: =AE52+AN52 -> 0 | AD52: 0 | AF52: 0 | AG52: 0 | AH52: 0 | AI52: 0 | AJ52: 0 | AK52: 0 | AL52: 0 | AM52: =AI52+AK52 -> 0 | AN52: =AJ52+AL52 -> 0 | AO52: =AG52+AM52 -> 0 | AP52: =AH52+AN52 -> 0
D53: 3 | E53: BK3 | F53: 0 | G53: 513.847 | H53: 0 | I53: 0 | J53: =F53+G53+H53+I53 -> 513.847 | K53: 0 | L53: =J53+K53 -> 513.847 | M53: 3132.8074 | N53: 0 | O53: =M53+N53 -> 3132.8074 | P53: 1233.0492 | Q53: =P53+O53 -> 4365.8566 | R53: 0 | S53: 0 | T53: 0 | U53: 0 | V53: 0 | W53: 0 | X53: 0 | Y53: 0 | Z53: 0 | AA53: =AC53+AH53 -> 0 | AB53: =AE53+AN53 -> 0 | AD53: 0 | AF53: 3379.72 | AG53: 0 | AH53: 0 | AI53: 0 | AJ53: 0 | AK53: 472.30005 | AL53: 0 | AM53: =AI53+AK53 -> 472.30005 | AN53: =AJ53+AL53 -> 0 | AO53: =AG53+AM53 -> 472.30005 | AP53: =AH53+AN53 -> 0
D54: 4 | E54: BK4 | F54: 0 | G54: 713.662 | H54: 4351.47 | I54: 0 | J54: =F54+G54+H54+I54 -> 5065.132 | K54: 1299.9333 | L54: =J54+K54 -> 6365.0653 | M54: 3311.51 | N54: 0 | O54: =M54+N54 -> 3311.51 | P54: 2851.85 | Q54: =P54+O54 -> 6163.36 | R54: 201.69582 | S54: 0 | T54: 0 | U54: 0 | V54: 0 | W54: 0 | X54: 0 | Y54: 15.6117 | Z54: 0 | AA54: =AC54+AH54 -> 0 | AB54: =AE54+AN54 -> 0 | AD54: 0 | AF54: 0 | AG54: 0 | AH54: 0 | AI54: 0 | AJ54: 0 | AK54: 0 | AL54: 0 | AM54: =AI54+AK54 -> 0 | AN54: =AJ54+AL54 -> 0 | AO54: =AG54+AM54 -> 0 | AP54: =AH54+AN54 -> 0
D55: 5 | E55: BK5 | F55: 0 | G55: 417.257 | H55: 620.69 | I55: 0 | J55: =F55+G55+H55+I55 -> 1037.947 | K55: 2717.39 | L55: =J55+K55 -> 3755.337 | M55: 3122.9 | N55: 0 | O55: =M55+N55 -> 3122.9 | P55: 480.71 | Q55: =P55+O55 -> 3603.61 | R55: 151.727 | S55: 0 | T55: 0 | U55: 0 | V55: 0 | W55: 0 | X55: 0 | Y55: 0 | Z55: 0 | AA55: =AC55+AH55 -> 0 | AB55: =AE55+AN55 -> 0 | AD55: 0 | AF55: 0 | AG55: 0 | AH55: 0 | AI55: 0 | AJ55: 0 | AK55: 0 | AL55: 0 | AM55: =AI55+AK55 -> 0 | AN55: =AJ55+AL55 -> 0 | AO55: =AG55+AM55 -> 0 | AP55: =AH55+AN55 -> 0
F56: =SUM(F51:F55) -> 0 | G56: =SUM(G51:G55) -> 2709.584 | H56: =SUM(H51:H55) -> 9275.4 | I56: =SUM(I51:I55) -> 0 | J56: =SUM(J51:J55) -> 11984.984 | K56: =SUM(K51:K55) -> 4372.3164 | L56: =SUM(L51:L55) -> 16357.3 | M56: =SUM(M51:M55) -> 14840.942 | ... AB56: =SUM(AB51:AB55) -> 0 | AD56: =SUM(AD51:AD55) -> 0 | AF56: =SUM(AF51:AF55) -> 3379.72 | AG56: =SUM(AG51:AG55) -> 0 | AH56: =SUM(AH51:AH55) -> 0 | AI56: =SUM(AI51:AI55) -> 0 | AJ56: =SUM(AJ51:AJ55) -> 0 | AK56: =SUM(AK51:AK55) -> 2657.54 | AL56: =SUM(AL51:AL55) -> 0 | AM56: =SUM(AM51:AM55) -> 2657.54 | ... AP56: =SUM(AP51:AP55) -> 0
B58: 2 | C58: 2 | D58: 1 | E58: BK1 | F58: 0 | G58: 477.125 | H58: 0 | I58: 0 | J58: =F58+G58+H58+I58 -> 477.125 | K58: 0 | L58: =J58+K58 -> 477.125 | M58: 2042.355 | N58: 0 | O58: =M58+N58 -> 2042.355 | P58: 620.009 | Q58: =P58+O58 -> 2662.364 | R58: 0 | S58: 0 | T58: 0 | U58: 0 | V58: 0 | W58: 0 | X58: 0 | Y58: 0 | Z58: 472.302 | AA58: =AC58+AH58 -> 0 | AB58: =AE58+AN58 -> 472.302 | AD58: 0 | AF58: 0 | AG58: 0 | AH58: 0 | AI58: 0 | AJ58: 0 | AK58: 0 | AL58: 472.302 | AM58: =AI58+AK58 -> 0 | AN58: =AJ58+AL58 -> 472.302 | AO58: =AG58+AM58 -> 0 | AP58: =AH58+AN58 -> 472.302
D59: 2 | E59: BK2 | F59: 0 | G59: 587.693 | H59: 4303.24 | I59: 0 | J59: =F59+G59+H59+I59 -> 4890.933 | K59: 354.9931 | L59: =J59+K59 -> 5245.9261 | M59: 3231.37 | N59: 0 | O59: =M59+N59 -> 3231.37 | P59: 1844.24 | Q59: =P59+O59 -> 5075.61 | R59: 170.30597 | S59: 0 | T59: 0 | U59: 0 | V59: 0 | W59: 0 | X59: 0 | Y59: 0 | Z59: 1728.55 | AA59: =AC59+AH59 -> 0 | AB59: =AE59+AN59 -> 1728.55 | AD59: 0 | AF59: 0 | AG59: 0 | AH59: 0 | AI59: 0 | AJ59: 0 | AK59: 0 | AL59: 1728.55 | AM59: =AI59+AK59 -> 0 | AN59: =AJ59+AL59 -> 1728.55 | AO59: =AG59+AM59 -> 0 | AP59: =AH59+AN59 -> 1728.55
D60: 3 | E60: BK3 | F60: 0 | G60: 513.847 | H60: 0 | I60: 0 | J60: =F60+G60+H60+I60 -> 513.847 | K60: 0 | L60: =J60+K60 -> 513.847 | M60: 3132.8074 | N60: 0 | O60: =M60+N60 -> 3132.8074 | P60: 1233.0492 | Q60: =P60+O60 -> 4365.8566 | R60: 0 | S60: 0 | T60: 0 | U60: 0 | V60: 0 | W60: 0 | X60: 0 | Y60: 0 | Z60: 0 | AA60: =AC60+AH60 -> 0 | AB60: =AE60+AN60 -> 0 | AD60: 0 | AF60: 0 | AG60: 0 | AH60: 0 | AI60: 0 | AJ60: 0 | AK60: 0 | AL60: 0 | AM60: =AI60+AK60 -> 0 | AN60: =AJ60+AL60 -> 0 | AO60: =AG60+AM60 -> 0 | AP60: =AH60+AN60 -> 0
D61: 4 | E61: BK4 | F61: 0 | G61: 713.662 | H61: 4351.47 | I61: 0 | J61: =F61+G61+H61+I61 -> 5065.132 | K61: 1299.9333 | L61: =J61+K61 -> 6365.0653 | M61: 3311.51 | N61: 0 | O61: =M61+N61 -> 3311.51 | P61: 2851.85 | Q61: =P61+O61 -> 6163.36 | R61: 201.69582 | S61: 0 | T61: 0 | U61: 0 | V61: 0 | W61: 0 | X61: 0 | Y61: 0 | Z61: 134.46 | AA61: =AC61+AH61 -> 0 | AB61: =AE61+AN61 -> 134.46 | AD61: 0 | AF61: 0 | AG61: 0 | AH61: 0 | AI61: 0 | AJ61: 0 | AK61: 0 | AL61: 134.46 | AM61: =AI61+AK61 -> 0 | AN61: =AJ61+AL61 -> 134.46 | AO61: =AG61+AM61 -> 0 | AP61: =AH61+AN61 -> 134.46
D62: 5 | E62: BK5 | F62: 0 | G62: 417.257 | H62: 620.69 | I62: 0 | J62: =F62+G62+H62+I62 -> 1037.947 | K62: 2717.39 | L62: =J62+K62 -> 3755.337 | M62: 3122.9 | N62: 0 | O62: =M62+N62 -> 3122.9 | P62: 480.71 | Q62: =P62+O62 -> 3603.61 | R62: 151.727 | S62: 0 | T62: 0 | U62: 0 | V62: 0 | W62: 0 | X62: 0 | Y62: 0 | Z62: 322.23 | AA62: =AC62+AH62 -> 0 | AB62: =AE62+AN62 -> 322.23 | AD62: 0 | AF62: 0 | AG62: 0 | AH62: 0 | AI62: 0 | AJ62: 0 | AK62: 0 | AL62: 322.23 | AM62: =AI62+AK62 -> 0 | AN62: =AJ62+AL62 -> 322.23 | AO62: =AG62+AM62 -> 0 | AP62: =AH62+AN62 -> 322.23
F63: =SUM(F58:F62) -> 0 | G63: =SUM(G58:G62) -> 2709.584 | H63: =SUM(H58:H62) -> 9275.4 | I63: =SUM(I58:I62) -> 0 | J63: =SUM(J58:J62) -> 11984.984 | K63: =SUM(K58:K62) -> 4372.3164 | L63: =SUM(L58:L62) -> 16357.3 | M63: =SUM(M58:M62) -> 14840.942 | ... AB63: =SUM(AB58:AB62) -> 2657.542 | AD63: =SUM(AD58:AD62) -> 0 | AF63: =SUM(AF58:AF62) -> 0 | AG63: =SUM(AG58:AG62) -> 0 | AH63: =SUM(AH58:AH62) -> 0 | AI63: =SUM(AI58:AI62) -> 0 | AJ63: =SUM(AJ58:AJ62) -> 0 | AK63: =SUM(AK58:AK62) -> 0 | AL63: =SUM(AL58:AL62) -> 2657.542 | AM63: =SUM(AM58:AM62) -> 0 | ... AP63: =SUM(AP58:AP62) -> 2657.542
B65: 2 | C65: 1 | D65: 1 | E65: BK1 | F65: 0 | G65: 4.8249817 | H65: 0 | I65: 0 | J65: =F65+G65+H65+I65 -> 4.8249817 | K65: 0 | L65: =J65+K65 -> 4.8249817 | M65: 2042.355 | N65: 0 | O65: =M65+N65 -> 2042.355 | P65: 620.009 | Q65: =P65+O65 -> 2662.364 | R65: 0 | S65: 0 | T65: 0 | U65: 0 | V65: 0 | W65: 0 | X65: 0 | Y65: 0 | Z65: 472.302 | AA65: =AC65+AH65 -> 0 | AB65: =AE65+AN65 -> 0 | AD65: 0 | AF65: 0 | AG65: 0 | AH65: 0 | AI65: 0 | AJ65: 0 | AK65: 0 | AL65: 0 | AM65: =AI65+AK65 -> 0 | AN65: =AJ65+AL65 -> 0 | AO65: =AG65+AM65 -> 0 | AP65: =AH65+AN65 -> 0
D66: 2 | E66: BK2 | F66: 0 | G66: 587.693 | H66: 4303.24 | I66: 0 | J66: =F66+G66+H66+I66 -> 4890.933 | K66: 354.9931 | L66: =J66+K66 -> 5245.9261 | M66: 3231.37 | N66: 0 | O66: =M66+N66 -> 3231.37 | P66: 1844.24 | Q66: =P66+O66 -> 5075.61 | R66: 170.30597 | S66: 0 | T66: 0 | U66: 0 | V66: 0 | W66: 0 | X66: 0 | Y66: 0 | Z66: 1728.55 | AA66: =AC66+AH66 -> 0 | AB66: =AE66+AN66 -> 0 | AD66: 0 | AF66: 0 | AG66: 0 | AH66: 0 | AI66: 0 | AJ66: 0 | AK66: 0 | AL66: 0 | AM66: =AI66+AK66 -> 0 | AN66: =AJ66+AL66 -> 0 | AO66: =AG66+AM66 -> 0 | AP66: =AH66+AN66 -> 0
D67: 3 | E67: BK3 | F67: 0 | G67: 513.847 | H67: 0 | I67: 0 | J67: =F67+G67+H67+I67 -> 513.847 | K67: 0 | L67: =J67+K67 -> 513.847 | M67: 3132.8074 | N67: 0 | O67: =M67+N67 -> 3132.8074 | P67: 1233.0492 | Q67: =P67+O67 -> 4365.8566 | R67: 0 | S67: 0 | T67: 0 | U67: 0 | V67: 0 | W67: 0 | X67: 0 | Y67: 0 | Z67: 0 | AA67: =AC67+AH67 -> 0 | AB67: =AE67+AN67 -> 0 | AD67: 0 | AF67: 0 | AG67: 0 | AH67: 0 | AI67: 0 | AJ67: 0 | AK67: 0 | AL67: 0 | AM67: =AI67+AK67 -> 0 | AN67: =AJ67+AL67 -> 0 | AO67: =AG67+AM67 -> 0 | AP67: =AH67+AN67 -> 0
D68: 4 | E68: BK4 | F68: 0 | G68: 713.662 | H68: 4351.47 | I68: 0 | J68: =F68+G68+H68+I68 -> 5065.132 | K68: 1299.9333 | L68: =J68+K68 -> 6365.0653 | M68: 3311.51 | N68: 0 | O68: =M68+N68 -> 3311.51 | P68: 2851.85 | Q68: =P68+O68 -> 6163.36 | R68: 201.69582 | S68: 0 | T68: 0 | U68: 0 | V68: 0 | W68: 0 | X68: 0 | Y68: 0 | Z68: 134.46 | AA68: =AC68+AH68 -> 0 | AB68: =AE68+AN68 -> 0 | AD68: 0 | AF68: 0 | AG68: 0 | AH68: 0 | AI68: 0 | AJ68: 0 | AK68: 0 | AL68: 0 | AM68: =AI68+AK68 -> 0 | AN68: =AJ68+AL68 -> 0 | AO68: =AG68+AM68 -> 0 | AP68: =AH68+AN68 -> 0
D69: 5 | E69: BK5 | F69: 0 | G69: 417.257 | H69: 620.69 | I69: 0 | J69: =F69+G69+H69+I69 -> 1037.947 | K69: 2717.39 | L69: =J69+K69 -> 3755.337 | M69: 3122.9 | N69: 0 | O69: =M69+N69 -> 3122.9 | P69: 480.71 | Q69: =P69+O69 -> 3603.61 | R69: 151.727 | S69: 0 | T69: 0 | U69: 0 | V69: 0 | W69: 0 | X69: 0 | Y69: 0 | Z69: 322.23 | AA69: =AC69+AH69 -> 0 | AB69: =AE69+AN69 -> 0 | AD69: 0 | AF69: 0 | AG69: 0 | AH69: 0 | AI69: 0 | AJ69: 0 | AK69: 0 | AL69: 0 | AM69: =AI69+AK69 -> 0 | AN69: =AJ69+AL69 -> 0 | AO69: =AG69+AM69 -> 0 | AP69: =AH69+AN69 -> 0
F70: =SUM(F65:F69) -> 0 | G70: =SUM(G65:G69) -> 2237.284 | H70: =SUM(H65:H69) -> 9275.4 | I70: =SUM(I65:I69) -> 0 | J70: =SUM(J65:J69) -> 11512.684 | K70: =SUM(K65:K69) -> 4372.3164 | L70: =SUM(L65:L69) -> 15885 | M70: =SUM(M65:M69) -> 14840.942 | ... AB70: =SUM(AB65:AB69) -> 0 | AD70: =SUM(AD65:AD69) -> 0 | AF70: =SUM(AF65:AF69) -> 0 | AG70: =SUM(AG65:AG69) -> 0 | AH70: =SUM(AH65:AH69) -> 0 | AI70: =SUM(AI65:AI69) -> 0 | AJ70: =SUM(AJ65:AJ69) -> 0 | AK70: =SUM(AK65:AK69) -> 0 | AL70: =SUM(AL65:AL69) -> 0 | AM70: =SUM(AM65:AM69) -> 0 | ... AP70: =SUM(AP65:AP69) -> 0
B72: 2 | C72: 2 | D72: 1 | E72: BK1 | F72: 0 | G72: 4.8249817 | H72: 0 | I72: 0 | J72: =F72+G72+H72+I72 -> 4.8249817 | K72: 0 | L72: =J72+K72 -> 4.8249817 | M72: 2042.355 | N72: 0 | O72: =M72+N72 -> 2042.355 | P72: 620.009 | Q72: =P72+O72 -> 2662.364 | R72: 0 | S72: 0 | T72: 0 | U72: 0 | V72: 0 | W72: 0 | X72: 0 | Y72: 0 | Z72: 472.302 | AA72: =AC72+AH72 -> 0 | AB72: =AE72+AN72 -> 0 | AD72: 0 | AF72: 0 | AG72: 0 | AH72: 0 | AI72: 0 | AJ72: 0 | AK72: 0 | AL72: 0 | AM72: =AI72+AK72 -> 0 | AN72: =AJ72+AL72 -> 0 | AO72: =AG72+AM72 -> 0 | AP72: =AH72+AN72 -> 0
D73: 2 | E73: BK2 | F73: 0 | G73: 0 | H73: 4303.24 | I73: 0 | J73: =F73+G73+H73+I73 -> 4303.24 | K73: 354.9931 | L73: =J73+K73 -> 4658.2331 | M73: 3231.37 | N73: 0 | O73: =M73+N73 -> 3231.37 | P73: 1844.24 | Q73: =P73+O73 -> 5075.61 | R73: 170.30597 | S73: 0 | T73: 0 | U73: 0 | V73: 0 | W73: 0 | X73: 0 | Y73: 0 | Z73: 1728.55 | AA73: =AC73+AH73 -> 0 | AB73: =AE73+AN73 -> 0 | AD73: 0 | AF73: 0 | AG73: 0 | AH73: 0 | AI73: 0 | AJ73: 0 | AK73: 0 | AL73: 0 | AM73: =AI73+AK73 -> 0 | AN73: =AJ73+AL73 -> 0 | AO73: =AG73+AM73 -> 0 | AP73: =AH73+AN73 -> 0
D74: 3 | E74: BK3 | F74: 0 | G74: 513.847 | H74: 0 | I74: 0 | J74: =F74+G74+H74+I74 -> 513.847 | K74: 0 | L74: =J74+K74 -> 513.847 | M74: 3132.8074 | N74: 0 | O74: =M74+N74 -> 3132.8074 | P74: 1233.0492 | Q74: =P74+O74 -> 4365.8566 | R74: 0 | S74: 0 | T74: 0 | U74: 0 | V74: 0 | W74: 0 | X74: 0 | Y74: 0 | Z74: 0 | AA74: =AC74+AH74 -> 0 | AB74: =AE74+AN74 -> 0 | AD74: 0 | AF74: 0 | AG74: 0 | AH74: 0 | AI74: 0 | AJ74: 0 | AK74: 0 | AL74: 0 | AM74: =AI74+AK74 -> 0 | AN74: =AJ74+AL74 -> 0 | AO74: =AG74+AM74 -> 0 | AP74: =AH74+AN74 -> 0
D75: 4 | E75: BK4 | F75: 0 | G75: 579.20197 | H75: 4351.47 | I75: 0 | J75: =F75+G75+H75+I75 -> 4930.672 | K75: 1299.9333 | L75: =J75+K75 -> 6230.6053 | M75: 3311.51 | N75: 0 | O75: =M75+N75 -> 3311.51 | P75: 2851.85 | Q75: =P75+O75 -> 6163.36 | R75: 201.69582 | S75: 0 | T75: 0 | U75: 0 | V75: 0 | W75: 0 | X75: 0 | Y75: 0 | Z75: 134.46 | AA75: =AC75+AH75 -> 0 | AB75: =AE75+AN75 -> 0 | AD75: 0 | AF75: 0 | AG75: 0 | AH75: 0 | AI75: 0 | AJ75: 0 | AK75: 0 | AL75: 0 | AM75: =AI75+AK75 -> 0 | AN75: =AJ75+AL75 -> 0 | AO75: =AG75+AM75 -> 0 | AP75: =AH75+AN75 -> 0
D76: 5 | E76: BK5 | F76: 0 | G76: 95.02698 | H76: 620.69 | I76: 0 | J76: =F76+G76+H76+I76 -> 715.71698 | K76: 2717.39 | L76: =J76+K76 -> 3433.107 | M76: 3122.9 | N76: 0 | O76: =M76+N76 -> 3122.9 | P76: 480.71 | Q76: =P76+O76 -> 3603.61 | R76: 151.727 | S76: 0 | T76: 0 | U76: 0 | V76: 0 | W76: 0 | X76: 0 | Y76: 0 | Z76: 322.23 | AA76: =AC76+AH76 -> 0 | AB76: =AE76+AN76 -> 0 | AD76: 0 | AF76: 0 | AG76: 0 | AH76: 0 | AI76: 0 | AJ76: 0 | AK76: 0 | AL76: 0 | AM76: =AI76+AK76 -> 0 | AN76: =AJ76+AL76 -> 0 | AO76: =AG76+AM76 -> 0 | AP76: =AH76+AN76 -> 0
F77: =SUM(F72:F76) -> 0 | G77: =SUM(G72:G76) -> 1192.9009 | H77: =SUM(H72:H76) -> 9275.4 | I77: =SUM(I72:I76) -> 0 | J77: =SUM(J72:J76) -> 10468.301 | K77: =SUM(K72:K76) -> 4372.3164 | L77: =SUM(L72:L76) -> 14840.617 | M77: =SUM(M72:M76) -> 14840.942 | ... AB77: =SUM(AB72:AB76) -> 0 | AD77: =SUM(AD72:AD76) -> 0 | AF77: =SUM(AF72:AF76) -> 0 | AG77: =SUM(AG72:AG76) -> 0 | AH77: =SUM(AH72:AH76) -> 0 | AI77: =SUM(AI72:AI76) -> 0 | AJ77: =SUM(AJ72:AJ76) -> 0 | AK77: =SUM(AK72:AK76) -> 0 | AL77: =SUM(AL72:AL76) -> 0 | AM77: =SUM(AM72:AM76) -> 0 | ... AP77: =SUM(AP72:AP76) -> 0

Sheet BI之过程-theta_Shock_exBI_t=1
A1: 子过程 | B1: id | C1: tau | D1: t | F1: A_BI | M1: Z_BI | T1: Shock_BI_def | AA1: Shock_BI_run_ilq | AH1: Shock_BI_run_br | AO1: Shock_BI_run
A2: 1 | C2: 1 | D2: 0 | F2: 0 | G2: 1728.55 | H2: 0 | I2: 134.46 | J2: 322.23 | K2: =SUM(F2:J2) -> 2185.24 | M2: 0 | N2: 109.35 | O2: 730.99 | P2: 119.26 | Q2: 0 | R2: =SUM(M2:Q2) -> 959.6 | T2: 0 | U2: 0 | V2: 0 | W2: 0 | X2: 0 | Y2: =SUM(T2:X2) -> 0 | AA2: 0 | AB2: 0 | AC2: 0 | AD2: 0 | AE2: 0 | AF2: =SUM(AA2:AE2) -> 0 | AH2: 0 | AI2: 0 | AJ2: 0 | AK2: 0 | AL2: 0 | AM2: =SUM(AH2:AL2) -> 0 | AO2: =AH2+AA2 -> 0 | AP2: =AI2+AB2 -> 0 | AQ2: =AJ2+AC2 -> 0 | AR2: =AK2+AD2 -> 0 | AS2: =AL2+AE2 -> 0 | AT2: =SUM(AO2:AS2) -> 0
F3: 109.35 | G3: 0 | H3: 289.02 | I3: 0 | J3: 0 | K3: =SUM(F3:J3) -> 398.37 | M3: 1728.55 | N3: 0 | O3: 0 | P3: 115.69 | Q3: 0 | R3: =SUM(M3:Q3) -> 1844.24 | T3: 0 | U3: 0 | V3: 0 | W3: 0 | X3: 0 | Y3: =SUM(T3:X3) -> 0 | AA3: 0 | AB3: 0 | AC3: 0 | AD3: 0 | AE3: 0 | AF3: =SUM(AA3:AE3) -> 0 | AH3: 0 | AI3: 0 | AJ3: 0 | AK3: 0 | AL3: 0 | AM3: =SUM(AH3:AL3) -> 0 | AO3: =AH3+AA3 -> 0 | AP3: =AI3+AB3 -> 0 | AQ3: =AJ3+AC3 -> 0 | AR3: =AK3+AD3 -> 0 | AS3: =AL3+AE3 -> 0 | AT3: =SUM(AO3:AS3) -> 0
F4: 730.99 | G4: 0 | H4: 0 | I4: 0 | J4: 0 | K4: =SUM(F4:J4) -> 730.99 | M4: 0 | N4: 289.02 | O4: 0 | P4: 964.32 | Q4: 0 | R4: =SUM(M4:Q4) -> 1253.34 | T4: 0 | U4: 0 | V4: 0 | W4: 0 | X4: 0 | Y4: =SUM(T4:X4) -> 0 | AA4: 0 | AB4: 0 | AC4: 0 | AD4: 0 | AE4: 0 | AF4: =SUM(AA4:AE4) -> 0 | AH4: 0 | AI4: 0 | AJ4: 0 | AK4: 0 | AL4: 0 | AM4: =SUM(AH4:AL4) -> 0 | AO4: =AH4+AA4 -> 0 | AP4: =AI4+AB4 -> 0 | AQ4: =AJ4+AC4 -> 0 | AR4: =AK4+AD4 -> 0 | AS4: =AL4+AE4 -> 0 | AT4: =SUM(AO4:AS4) -> 0
F5: 119.26 | G5: 115.69 | H5: 964.32 | I5: 0 | J5: 158.48 | K5: =SUM(F5:J5) -> 1357.75 | M5: 134.46 | N5: 0 | O5: 0 | P5: 0 | Q5: 2717.39 | R5: =SUM(M5:Q5) -> 2851.85 | T5: 0 | U5: 0 | V5: 0 | W5: 0 | X5: 0 | Y5: =SUM(T5:X5) -> 0 | AA5: 0 | AB5: 0 | AC5: 0 | AD5: 0 | AE5: 0 | AF5: =SUM(AA5:AE5) -> 0 | AH5: 0 | AI5: 0 | AJ5: 0 | AK5: 0 | AL5: 0 | AM5: =SUM(AH5:AL5) -> 0 | AO5: =AH5+AA5 -> 0 | AP5: =AI5+AB5 -> 0 | AQ5: =AJ5+AC5 -> 0 | AR5: =AK5+AD5 -> 0 | AS5: =AL5+AE5 -> 0 | AT5: =SUM(AO5:AS5) -> 0
F6: 0 | G6: 0 | H6: 0 | I6: 2717.39 | J6: 0 | K6: =SUM(F6:J6) -> 2717.39 | M6: 322.23 | N6: 0 | O6: 0 | P6: 158.48 | Q6: 0 | R6: =SUM(M6:Q6) -> 480.71 | T6: 0 | U6: 0 | V6: 0 | W6: 0 | X6: 0 | Y6: =SUM(T6:X6) -> 0 | AA6: 0 | AB6: 0 | AC6: 0 | AD6: 0 | AE6: 0 | AF6: =SUM(AA6:AE6) -> 0 | AH6: 0 | AI6: 0 | AJ6: 0 | AK6: 0 | AL6: 0 | AM6: =SUM(AH6:AL6) -> 0 | AO6: =AH6+AA6 -> 0 | AP6: =AI6+AB6 -> 0 | AQ6: =AJ6+AC6 -> 0 | AR6: =AK6+AD6 -> 0 | AS6: =AL6+AE6 -> 0 | AT6: =SUM(AO6:AS6) -> 0
F7: =SUM(F2:F6) -> 959.6 | G7: =SUM(G2:G6) -> 1844.24 | H7: =SUM(H2:H6) -> 1253.34 | I7: =SUM(I2:I6) -> 2851.85 | J7: =SUM(J2:J6) -> 480.71 | K7: =SUM(K2:K6) -> 7389.74 | M7: =SUM(M2:M6) -> 2185.24 | N7: =SUM(N2:N6) -> 398.37 | O7: =SUM(O2:O6) -> 730.99 | P7: =SUM(P2:P6) -> 1357.75 | Q7: =SUM(Q2:Q6) -> 2717.39 | R7: =SUM(R2:R6) -> 7389.74 | T7: =SUM(T2:T6) -> 0 | U7: =SUM(U2:U6) -> 0 | V7: =SUM(V2:V6) -> 0 | W7: =SUM(W2:W6) -> 0 | X7: =SUM(X2:X6) -> 0 | Y7: =SUM(Y2:Y6) -> 0 | AA7: =SUM(AA2:AA6) -> 0 | AB7: =SUM(AB2:AB6) -> 0 | AC7: =SUM(AC2:AC6) -> 0 | AD7: =SUM(AD2:AD6) -> 0 | AE7: =SUM(AE2:AE6) -> 0 | AF7: =SUM(AF2:AF6) -> 0 | AH7: =SUM(AH2:AH6) -> 0 | AI7: =SUM(AI2:AI6) -> 0 | AJ7: =SUM(AJ2:AJ6) -> 0 | AK7: =SUM(AK2:AK6) -> 0 | AL7: =SUM(AL2:AL6) -> 0 | AM7: =SUM(AM2:AM6) -> 0 | AO7: =SUM(AO2:AO6) -> 0 | AP7: =SUM(AP2:AP6) -> 0 | AQ7: =SUM(AQ2:AQ6) -> 0 | AR7: =SUM(AR2:AR6) -> 0 | AS7: =SUM(AS2:AS6) -> 0 | AT7: =SUM(AT2:AT6) -> 0
C9: 2 | D9: 1-1 | F9: 0 | G9: 1728.55 | H9: 0 | I9: 134.46 | J9: 322.23 | K9: =SUM(F9:J9) -> 2185.24 | M9: 0 | N9: 70.652 | O9: 472.302 | P9: 77.055 | Q9: 0 | R9: =SUM(M9:Q9) -> 620.009 | T9: 0 | U9: 0 | V9: 0 | W9: 0 | X9: 0 | Y9: =SUM(T9:X9) -> 0 | AA9: 0 | AB9: 0 | AC9: 0 | AD9: 0 | AE9: 0 | AF9: =SUM(AA9:AE9) -> 0 | AH9: 0 | AI9: 0 | AJ9: 0 | AK9: 0 | AL9: 0 | AM9: =SUM(AH9:AL9) -> 0 | AO9: =AH9+AA9 -> 0 | AP9: =AI9+AB9 -> 0 | AQ9: =AJ9+AC9 -> 0 | AR9: =AK9+AD9 -> 0 | AS9: =AL9+AE9 -> 0 | AT9: =SUM(AO9:AS9) -> 0
F10: 70.652 | G10: 0 | H10: 289.02 | I10: 0 | J10: 0 | K10: =SUM(F10:J10) -> 359.672 | M10: 1728.55 | N10: 0 | O10: 0 | P10: 115.69 | Q10: 0 | R10: =SUM(M10:Q10) -> 1844.24 | T10: 38.698 | U10: 0 | V10: 0 | W10: 0 | X10: 0 | Y10: =SUM(T10:X10) -> 38.698 | AA10: 0 | AB10: 0 | AC10: 0 | AD10: 0 | AE10: 0 | AF10: =SUM(AA10:AE10) -> 0 | AH10: 0 | AI10: 0 | AJ10: 0 | AK10: 0 | AL10: 0 | AM10: =SUM(AH10:AL10) -> 0 | AO10: =AH10+AA10 -> 0 | AP10: =AI10+AB10 -> 0 | AQ10: =AJ10+AC10 -> 0 | AR10: =AK10+AD10 -> 0 | AS10: =AL10+AE10 -> 0 | AT10: =SUM(AO10:AS10) -> 0
F11: 472.302 | G11: 0 | H11: 0 | I11: 0 | J11: 0 | K11: =SUM(F11:J11) -> 472.302 | M11: 0 | N11: 289.02 | O11: 0 | P11: 964.32 | Q11: 0 | R11: =SUM(M11:Q11) -> 1253.34 | T11: 258.688 | U11: 0 | V11: 0 | W11: 0 | X11: 0 | Y11: =SUM(T11:X11) -> 258.688 | AA11: 0 | AB11: 0 | AC11: 0 | AD11: 0 | AE11: 0 | AF11: =SUM(AA11:AE11) -> 0 | AH11: 0 | AI11: 0 | AJ11: 0 | AK11: 0 | AL11: 0 | AM11: =SUM(AH11:AL11) -> 0 | AO11: =AH11+AA11 -> 0 | AP11: =AI11+AB11 -> 0 | AQ11: =AJ11+AC11 -> 0 | AR11: =AK11+AD11 -> 0 | AS11: =AL11+AE11 -> 0 | AT11: =SUM(AO11:AS11) -> 0
F12: 77.055 | G12: 115.69 | H12: 964.32 | I12: 0 | J12: 158.48 | K12: =SUM(F12:J12) -> 1315.545 | M12: 134.46 | N12: 0 | O12: 0 | P12: 0 | Q12: 2717.39 | R12: =SUM(M12:Q12) -> 2851.85 | T12: 42.205 | U12: 0 | V12: 0 | W12: 0 | X12: 0 | Y12: =SUM(T12:X12) -> 42.205 | AA12: 0 | AB12: 0 | AC12: 0 | AD12: 0 | AE12: 0 | AF12: =SUM(AA12:AE12) -> 0 | AH12: 0 | AI12: 0 | AJ12: 0 | AK12: 0 | AL12: 0 | AM12: =SUM(AH12:AL12) -> 0 | AO12: =AH12+AA12 -> 0 | AP12: =AI12+AB12 -> 0 | AQ12: =AJ12+AC12 -> 0 | AR12: =AK12+AD12 -> 0 | AS12: =AL12+AE12 -> 0 | AT12: =SUM(AO12:AS12) -> 0
F13: 0 | G13: 0 | H13: 0 | I13: 2717.39 | J13: 0 | K13: =SUM(F13:J13) -> 2717.39 | M13: 322.23 | N13: 0 | O13: 0 | P13: 158.48 | Q13: 0 | R13: =SUM(M13:Q13) -> 480.71 | T13: 0 | U13: 0 | V13: 0 | W13: 0 | X13: 0 | Y13: =SUM(T13:X13) -> 0 | AA13: 0 | AB13: 0 | AC13: 0 | AD13: 0 | AE13: 0 | AF13: =SUM(AA13:AE13) -> 0 | AH13: 0 | AI13: 0 | AJ13: 0 | AK13: 0 | AL13: 0 | AM13: =SUM(AH13:AL13) -> 0 | AO13: =AH13+AA13 -> 0 | AP13: =AI13+AB13 -> 0 | AQ13: =AJ13+AC13 -> 0 | AR13: =AK13+AD13 -> 0 | AS13: =AL13+AE13 -> 0 | AT13: =SUM(AO13:AS13) -> 0
F14: =SUM(F9:F13) -> 620.009 | G14: =SUM(G9:G13) -> 1844.24 | H14: =SUM(H9:H13) -> 1253.34 | I14: =SUM(I9:I13) -> 2851.85 | J14: =SUM(J9:J13) -> 480.71 | K14: =SUM(K9:K13) -> 7050.149 | M14: =SUM(M9:M13) -> 2185.24 | N14: =SUM(N9:N13) -> 359.672 | O14: =SUM(O9:O13) -> 472.302 | P14: =SUM(P9:P13) -> 1315.545 | Q14: =SUM(Q9:Q13) -> 2717.39 | R14: =SUM(R9:R13) -> 7050.149 | T14: =SUM(T9:T13) -> 339.591 | U14: =SUM(U9:U13) -> 0 | V14: =SUM(V9:V13) -> 0 | W14: =SUM(W9:W13) -> 0 | X14: =SUM(X9:X13) -> 0 | Y14: =SUM(Y9:Y13) -> 339.591 | AA14: =SUM(AA9:AA13) -> 0 | AB14: =SUM(AB9:AB13) -> 0 | AC14: =SUM(AC9:AC13) -> 0 | AD14: =SUM(AD9:AD13) -> 0 | AE14: =SUM(AE9:AE13) -> 0 | AF14: =SUM(AF9:AF13) -> 0 | AH14: =SUM(AH9:AH13) -> 0 | AI14: =SUM(AI9:AI13) -> 0 | AJ14: =SUM(AJ9:AJ13) -> 0 | AK14: =SUM(AK9:AK13) -> 0 | AL14: =SUM(AL9:AL13) -> 0 | AM14: =SUM(AM9:AM13) -> 0 | AO14: =SUM(AO9:AO13) -> 0 | AP14: =SUM(AP9:AP13) -> 0 | AQ14: =SUM(AQ9:AQ13) -> 0 | AR14: =SUM(AR9:AR13) -> 0 | AS14: =SUM(AS9:AS13) -> 0 | AT14: =SUM(AT9:AT13) -> 0
C16: 3 | D16: 1-1 | F16: 0 | G16: 1728.55 | H16: 0 | I16: 134.46 | J16: 322.23 | K16: =SUM(F16:J16) -> 2185.24 | M16: 0 | N16: 70.652 | O16: 472.302 | P16: 77.055 | Q16: 0 | R16: =SUM(M16:Q16) -> 620.009 | T16: 0 | U16: 0 | V16: 0 | W16: 0 | X16: 0 | Y16: =SUM(T16:X16) -> 0 | AA16: 0 | AB16: 0 | AC16: 0 | AD16: 0 | AE16: 0 | AF16: =SUM(AA16:AE16) -> 0 | AH16: 0 | AI16: 0 | AJ16: 0 | AK16: 0 | AL16: 0 | AM16: =SUM(AH16:AL16) -> 0 | AO16: =AH16+AA16 -> 0 | AP16: =AI16+AB16 -> 0 | AQ16: =AJ16+AC16 -> 0 | AR16: =AK16+AD16 -> 0 | AS16: =AL16+AE16 -> 0 | AT16: =SUM(AO16:AS16) -> 0
F17: 70.652 | G17: 0 | H17: 284.34095 | I17: 0 | J17: 0 | K17: =SUM(F17:J17) -> 354.99295 | M17: 1728.55 | N17: 0 | O17: 0 | P17: 115.69 | Q17: 0 | R17: =SUM(M17:Q17) -> 1844.24 | T17: 0 | U17: 0 | V17: 4.67905 | W17: 0 | X17: 0 | Y17: =SUM(T17:X17) -> 4.67905 | AA17: 0 | AB17: 0 | AC17: 0 | AD17: 0 | AE17: 0 | AF17: =SUM(AA17:AE17) -> 0 | AH17: 0 | AI17: 0 | AJ17: 0 | AK17: 0 | AL17: 0 | AM17: =SUM(AH17:AL17) -> 0 | AO17: =AH17+AA17 -> 0 | AP17: =AI17+AB17 -> 0 | AQ17: =AJ17+AC17 -> 0 | AR17: =AK17+AD17 -> 0 | AS17: =AL17+AE17 -> 0 | AT17: =SUM(AO17:AS17) -> 0
F18: 472.302 | G18: 0 | H18: 0 | I18: 0 | J18: 0 | K18: =SUM(F18:J18) -> 472.302 | M18: 0 | N18: 284.34095 | O18: 0 | P18: 948.7083 | Q18: 0 | R18: =SUM(M18:Q18) -> 1233.0493 | T18: 0 | U18: 0 | V18: 0 | W18: 0 | X18: 0 | Y18: =SUM(T18:X18) -> 0 | AA18: 0 | AB18: 0 | AC18: 0 | AD18: 0 | AE18: 0 | AF18: =SUM(AA18:AE18) -> 0 | AH18: 0 | AI18: 0 | AJ18: 0 | AK18: 0 | AL18: 0 | AM18: =SUM(AH18:AL18) -> 0 | AO18: =AH18+AA18 -> 0 | AP18: =AI18+AB18 -> 0 | AQ18: =AJ18+AC18 -> 0 | AR18: =AK18+AD18 -> 0 | AS18: =AL18+AE18 -> 0 | AT18: =SUM(AO18:AS18) -> 0
F19: 77.055 | G19: 115.69 | H19: 948.7083 | I19: 0 | J19: 158.48 | K19: =SUM(F19:J19) -> 1299.9333 | M19: 134.46 | N19: 0 | O19: 0 | P19: 0 | Q19: 2717.39 | R19: =SUM(M19:Q19) -> 2851.85 | T19: 0 | U19: 0 | V19: 15.6117 | W19: 0 | X19: 0 | Y19: =SUM(T19:X19) -> 15.6117 | AA19: 0 | AB19: 0 | AC19: 0 | AD19: 0 | AE19: 0 | AF19: =SUM(AA19:AE19) -> 0 | AH19: 0 | AI19: 0 | AJ19: 0 | AK19: 0 | AL19: 0 | AM19: =SUM(AH19:AL19) -> 0 | AO19: =AH19+AA19 -> 0 | AP19: =AI19+AB19 -> 0 | AQ19: =AJ19+AC19 -> 0 | AR19: =AK19+AD19 -> 0 | AS19: =AL19+AE19 -> 0 | AT19: =SUM(AO19:AS19) -> 0
F20: 0 | G20: 0 | H20: 0 | I20: 2717.39 | J20: 0 | K20: =SUM(F20:J20) -> 2717.39 | M20: 322.23 | N20: 0 | O20: 0 | P20: 158.48 | Q20: 0 | R20: =SUM(M20:Q20) -> 480.71 | T20: 0 | U20: 0 | V20: 0 | W20: 0 | X20: 0 | Y20: =SUM(T20:X20) -> 0 | AA20: 0 | AB20: 0 | AC20: 0 | AD20: 0 | AE20: 0 | AF20: =SUM(AA20:AE20) -> 0 | AH20: 0 | AI20: 0 | AJ20: 0 | AK20: 0 | AL20: 0 | AM20: =SUM(AH20:AL20) -> 0 | AO20: =AH20+AA20 -> 0 | AP20: =AI20+AB20 -> 0 | AQ20: =AJ20+AC20 -> 0 | AR20: =AK20+AD20 -> 0 | AS20: =AL20+AE20 -> 0 | AT20: =SUM(AO20:AS20) -> 0
F21: =SUM(F16:F20) -> 620.009 | G21: =SUM(G16:G20) -> 1844.24 | H21: =SUM(H16:H20) -> 1233.0493 | I21: =SUM(I16:I20) -> 2851.85 | J21: =SUM(J16:J20) -> 480.71 | K21: =SUM(K16:K20) -> 7029.8582 | M21: =SUM(M16:M20) -> 2185.24 | N21: =SUM(N16:N20) -> 354.99295 | O21: =SUM(O16:O20) -> 472.302 | P21: =SUM(P16:P20) -> 1299.9333 | Q21: =SUM(Q16:Q20) -> 2717.39 | R21: =SUM(R16:R20) -> 7029.8583 | T21: =SUM(T16:T20) -> 0 | U21: =SUM(U16:U20) -> 0 | V21: =SUM(V16:V20) -> 20.29075 | W21: =SUM(W16:W20) -> 0 | X21: =SUM(X16:X20) -> 0 | Y21: =SUM(Y16:Y20) -> 20.29075 | AA21: =SUM(AA16:AA20) -> 0 | AB21: =SUM(AB16:AB20) -> 0 | AC21: =SUM(AC16:AC20) -> 0 | AD21: =SUM(AD16:AD20) -> 0 | AE21: =SUM(AE16:AE20) -> 0 | AF21: =SUM(AF16:AF20) -> 0 | AH21: =SUM(AH16:AH20) -> 0 | AI21: =SUM(AI16:AI20) -> 0 | AJ21: =SUM(AJ16:AJ20) -> 0 | AK21: =SUM(AK16:AK20) -> 0 | AL21: =SUM(AL16:AL20) -> 0 | AM21: =SUM(AM16:AM20) -> 0 | AO21: =SUM(AO16:AO20) -> 0 | AP21: =SUM(AP16:AP20) -> 0 | AQ21: =SUM(AQ16:AQ20) -> 0 | AR21: =SUM(AR16:AR20) -> 0 | AS21: =SUM(AS16:AS20) -> 0 | AT21: =SUM(AT16:AT20) -> 0
A23: 3 | C23: 2 | D23: 1-3 | F23: 0 | G23: 1728.55 | H23: 0 | I23: 134.46 | J23: 322.23 | K23: =SUM(F23:J23) -> 2185.24 | M23: 0 | N23: 70.652 | O23: 0 | P23: 77.055 | Q23: 0 | R23: =SUM(M23:Q23) -> 147.707 | T23: 0 | U23: 0 | V23: 0 | W23: 0 | X23: 0 | Y23: =SUM(T23:X23) -> 0 | AA23: 0 | AB23: 0 | AC23: 0 | AD23: 0 | AE23: 0 | AF23: =SUM(AA23:AE23) -> 0 | AH23: 0 | AI23: 0 | AJ23: 472.302 | AK23: 0 | AL23: 0 | AM23: =SUM(AH23:AL23) -> 472.302 | AO23: =AH23+AA23 -> 0 | AP23: =AI23+AB23 -> 0 | AQ23: =AJ23+AC23 -> 472.302 | AR23: =AK23+AD23 -> 0 | AS23: =AL23+AE23 -> 0 | AT23: =SUM(AO23:AS23) -> 472.302
F24: 70.652 | G24: 0 | H24: 284.34095 | I24: 0 | J24: 0 | K24: =SUM(F24:J24) -> 354.99295 | M24: 0 | N24: 0 | O24: 0 | P24: 115.69 | Q24: 0 | R24: =SUM(M24:Q24) -> 115.69 | T24: 0 | U24: 0 | V24: 0 | W24: 0 | X24: 0 | Y24: =SUM(T24:X24) -> 0 | AA24: 0 | AB24: 0 | AC24: 0 | AD24: 0 | AE24: 0 | AF24: =SUM(AA24:AE24) -> 0 | AH24: 1728.55 | AI24: 0 | AJ24: 0 | AK24: 0 | AL24: 0 | AM24: =SUM(AH24:AL24) -> 1728.55 | AO24: =AH24+AA24 -> 1728.55 | AP24: =AI24+AB24 -> 0 | AQ24: =AJ24+AC24 -> 0 | AR24: =AK24+AD24 -> 0 | AS24: =AL24+AE24 -> 0 | AT24: =SUM(AO24:AS24) -> 1728.55
F25: 472.302 | G25: 0 | H25: 0 | I25: 0 | J25: 0 | K25: =SUM(F25:J25) -> 472.302 | M25: 0 | N25: 284.34095 | O25: 0 | P25: 948.7083 | Q25: 0 | R25: =SUM(M25:Q25) -> 1233.0493 | T25: 0 | U25: 0 | V25: 0 | W25: 0 | X25: 0 | Y25: =SUM(T25:X25) -> 0 | AA25: 0 | AB25: 0 | AC25: 0 | AD25: 0 | AE25: 0 | AF25: =SUM(AA25:AE25) -> 0 | AH25: 0 | AI25: 0 | AJ25: 0 | AK25: 0 | AL25: 0 | AM25: =SUM(AH25:AL25) -> 0 | AO25: =AH25+AA25 -> 0 | AP25: =AI25+AB25 -> 0 | AQ25: =AJ25+AC25 -> 0 | AR25: =AK25+AD25 -> 0 | AS25: =AL25+AE25 -> 0 | AT25: =SUM(AO25:AS25) -> 0
F26: 77.055 | G26: 115.69 | H26: 948.7083 | I26: 0 | J26: 158.48 | K26: =SUM(F26:J26) -> 1299.9333 | M26: 0 | N26: 0 | O26: 0 | P26: 0 | Q26: 2717.39 | R26: =SUM(M26:Q26) -> 2717.39 | T26: 0 | U26: 0 | V26: 0 | W26: 0 | X26: 0 | Y26: =SUM(T26:X26) -> 0 | AA26: 0 | AB26: 0 | AC26: 0 | AD26: 0 | AE26: 0 | AF26: =SUM(AA26:AE26) -> 0 | AH26: 134.46 | AI26: 0 | AJ26: 0 | AK26: 0 | AL26: 0 | AM26: =SUM(AH26:AL26) -> 134.46 | AO26: =AH26+AA26 -> 134.46 | AP26: =AI26+AB26 -> 0 | AQ26: =AJ26+AC26 -> 0 | AR26: =AK26+AD26 -> 0 | AS26: =AL26+AE26 -> 0 | AT26: =SUM(AO26:AS26) -> 134.46
F27: 0 | G27: 0 | H27: 0 | I27: 2717.39 | J27: 0 | K27: =SUM(F27:J27) -> 2717.39 | M27: 0 | N27: 0 | O27: 0 | P27: 158.48 | Q27: 0 | R27: =SUM(M27:Q27) -> 158.48 | T27: 0 | U27: 0 | V27: 0 | W27: 0 | X27: 0 | Y27: =SUM(T27:X27) -> 0 | AA27: 0 | AB27: 0 | AC27: 0 | AD27: 0 | AE27: 0 | AF27: =SUM(AA27:AE27) -> 0 | AH27: 322.23 | AI27: 0 | AJ27: 0 | AK27: 0 | AL27: 0 | AM27: =SUM(AH27:AL27) -> 322.23 | AO27: =AH27+AA27 -> 322.23 | AP27: =AI27+AB27 -> 0 | AQ27: =AJ27+AC27 -> 0 | AR27: =AK27+AD27 -> 0 | AS27: =AL27+AE27 -> 0 | AT27: =SUM(AO27:AS27) -> 322.23
F28: =SUM(F23:F27) -> 620.009 | G28: =SUM(G23:G27) -> 1844.24 | H28: =SUM(H23:H27) -> 1233.0493 | I28: =SUM(I23:I27) -> 2851.85 | J28: =SUM(J23:J27) -> 480.71 | K28: =SUM(K23:K27) -> 7029.8582 | M28: =SUM(M23:M27) -> 0 | N28: =SUM(N23:N27) -> 354.99295 | O28: =SUM(O23:O27) -> 0 | P28: =SUM(P23:P27) -> 1299.9333 | Q28: =SUM(Q23:Q27) -> 2717.39 | R28: =SUM(R23:R27) -> 4372.3162 | T28: =SUM(T23:T27) -> 0 | U28: =SUM(U23:U27) -> 0 | V28: =SUM(V23:V27) -> 0 | W28: =SUM(W23:W27) -> 0 | X28: =SUM(X23:X27) -> 0 | Y28: =SUM(Y23:Y27) -> 0 | AA28: =SUM(AA23:AA27) -> 0 | AB28: =SUM(AB23:AB27) -> 0 | AC28: =SUM(AC23:AC27) -> 0 | AD28: =SUM(AD23:AD27) -> 0 | AE28: =SUM(AE23:AE27) -> 0 | AF28: =SUM(AF23:AF27) -> 0 | AH28: =SUM(AH23:AH27) -> 2185.24 | AI28: =SUM(AI23:AI27) -> 0 | AJ28: =SUM(AJ23:AJ27) -> 472.302 | AK28: =SUM(AK23:AK27) -> 0 | AL28: =SUM(AL23:AL27) -> 0 | AM28: =SUM(AM23:AM27) -> 2657.542 | AO28: =SUM(AO23:AO27) -> 2185.24 | AP28: =SUM(AP23:AP27) -> 0 | AQ28: =SUM(AQ23:AQ27) -> 472.302 | AR28: =SUM(AR23:AR27) -> 0 | AS28: =SUM(AS23:AS27) -> 0 | AT28: =SUM(AT23:AT27) -> 2657.542

Sheet BB之过程-theta_Shock_exBI_t=0_0313
A1: 子过程 | B1: tau | C1: t | D1: id | E1: name | F1: A_R | G1: A_Q | H1: A_P | I1: A_other | J1: A_exBI | K1: A_BI_all | L1: A_all | M1: Z_D | N1: Z_other | O1: Z_exBI | P1: Z_BI_all | Q1: Z_all | R1: E_all | S1: Bo_D | T1: Li_P | U1: Lo_BI_all | V1: Li_BI_all | W1: Bi_BI_all | X1: Bo_BI_all | Y1: Shock_B_def_t | Z1: Shock_B_run_t | AA1: BB.Shock_P_def_t | AB1: BB.Shock_D_def_s | AC1: BB.Shock_D_run_t | AD1: BB.Shock_P_run_s | AE1: BB.Shock_BI_def_s | AF1: BB.Shock_BI_def_t | AG1: BB.Shock_BI_run_ilq_s | AH1: BB.Shock_BI_run_ilq_t | AI1: BB.Shock_BI_run_br_s | AJ1: BB.Shock_BI_run_br_t | AK1: BB.Shock_BI_run_s | AL1: BB.Shock_BI_run_t | AM1: BB.Shock_BI_s | AN1: BB.Shock_BI_t
A2: 2 | B2: 1 | C2: 0 | D2: 1 | E2: BK1 | F2: 0 | G2: 477.125 | H2: 1631.73 | I2: 0 | J2: =F2+G2+H2+I2 -> 2108.855 | K2: 2185.24 | L2: =J2+K2 -> 4294.095 | M2: 3160.99 | N2: 0 | O2: =M2+N2 -> 3160.99 | P2: 959.6 | Q2: =P2+O2 -> 4120.59 | R2: =MAX(L2-Q2,0) -> 173.505 | S2: 0 | T2: 0 | U2: 0 | V2: 0 | W2: 0 | X2: 0 | Y2: =AA2+AF2 -> 0 | Z2: =AC2+AL2 -> 0 | AA2: 0 | AB2: 0 | AC2: 0 | AD2: 0 | AE2: 0 | AF2: 0 | AG2: 0 | AH2: 0 | AI2: 0 | AJ2: 0 | AK2: =AG2+AI2 -> 0 | AL2: =AH2+AJ2 -> 0 | AM2: =AE2+AK2 -> 0 | AN2: =AF2+AL2 -> 0
D3: 2 | E3: BK2 | F3: 0 | G3: 587.693 | H3: 4303.24 | I3: 0 | J3: =F3+G3+H3+I3 -> 4890.933 | K3: 398.37 | L3: =J3+K3 -> 5289.303 | M3: 3231.37 | N3: 0 | O3: =M3+N3 -> 3231.37 | P3: 1844.24 | Q3: =P3+O3 -> 5075.61 | R3: =MAX(L3-Q3,0) -> 213.693 | S3: 0 | T3: 0 | U3: 0 | V3: 0 | W3: 0 | X3: 0 | Y3: =AA3+AF3 -> 0 | Z3: =AC3+AL3 -> 0 | AA3: 0 | AB3: 0 | AC3: 0 | AD3: 0 | AE3: 0 | AF3: 0 | AG3: 0 | AH3: 0 | AI3: 0 | AJ3: 0 | AK3: =AG3+AI3 -> 0 | AL3: =AH3+AJ3 -> 0 | AM3: =AE3+AK3 -> 0 | AN3: =AF3+AL3 -> 0
D4: 3 | E4: BK3 | F4: 0 | G4: 513.847 | H4: 3379.72 | I4: 0 | J4: =F4+G4+H4+I4 -> 3893.567 | K4: 730.99 | L4: =J4+K4 -> 4624.557 | M4: 3184.36 | N4: 0 | O4: =M4+N4 -> 3184.36 | P4: 1253.34 | Q4: =P4+O4 -> 4437.7 | R4: =MAX(L4-Q4,0) -> 186.857 | S4: 0 | T4: 0 | U4: 0 | V4: 0 | W4: 0 | X4: 0 | Y4: =AA4+AF4 -> 0 | Z4: =AC4+AL4 -> 0 | AA4: 0 | AB4: 0 | AC4: 0 | AD4: 0 | AE4: 0 | AF4: 0 | AG4: 0 | AH4: 0 | AI4: 0 | AJ4: 0 | AK4: =AG4+AI4 -> 0 | AL4: =AH4+AJ4 -> 0 | AM4: =AE4+AK4 -> 0 | AN4: =AF4+AL4 -> 0
D5: 4 | E5: BK4 | F5: 0 | G5: 713.662 | H5: 4351.47 | I5: 0 | J5: =F5+G5+H5+I5 -> 5065.132 | K5: 1357.75 | L5: =J5+K5 -> 6422.882 | M5: 3311.51 | N5: 0 | O5: =M5+N5 -> 3311.51 | P5: 2851.85 | Q5: =P5+O5 -> 6163.36 | R5: =MAX(L5-Q5,0) -> 259.522 | S5: 0 | T5: 0 | U5: 0 | V5: 0 | W5: 0 | X5: 0 | Y5: =AA5+AF5 -> 0 | Z5: =AC5+AL5 -> 0 | AA5: 0 | AB5: 0 | AC5: 0 | AD5: 0 | AE5: 0 | AF5: 0 | AG5: 0 | AH5: 0 | AI5: 0 | AJ5: 0 | AK5: =AG5+AI5 -> 0 | AL5: =AH5+AJ5 -> 0 | AM5: =AE5+AK5 -> 0 | AN5: =AF5+AL5 -> 0
D6: 5 | E6: BK5 | F6: 0 | G6: 417.257 | H6: 620.69 | I6: 0 | J6: =F6+G6+H6+I6 -> 1037.947 | K6: 2717.39 | L6: =J6+K6 -> 3755.337 | M6: 3122.9 | N6: 0 | O6: =M6+N6 -> 3122.9 | P6: 480.71 | Q6: =P6+O6 -> 3603.61 | R6: =MAX(L6-Q6,0) -> 151.727 | S6: 0 | T6: 0 | U6: 0 | V6: 0 | W6: 0 | X6: 0 | Y6: =AA6+AF6 -> 0 | Z6: =AC6+AL6 -> 0 | AA6: 0 | AB6: 0 | AC6: 0 | AD6: 0 | AE6: 0 | AF6: 0 | AG6: 0 | AH6: 0 | AI6: 0 | AJ6: 0 | AK6: =AG6+AI6 -> 0 | AL6: =AH6+AJ6 -> 0 | AM6: =AE6+AK6 -> 0 | AN6: =AF6+AL6 -> 0
F7: =SUM(F2:F6) -> 0 | G7: =SUM(G2:G6) -> 2709.584 | H7: =SUM(H2:H6) -> 14286.85 | I7: =SUM(I2:I6) -> 0 | J7: =SUM(J2:J6) -> 16996.434 | K7: =SUM(K2:K6) -> 7389.74 | L7: =SUM(L2:L6) -> 24386.174 | M7: =SUM(M2:M6) -> 16011.13 | ... AN7: =SUM(AN2:AN6) -> 0
A9: 2 | B9: 1 | C9: 1 | D9: 1 | E9: BK1 | F9: 0 | G9: 477.125 | H9: 1631.73 | I9: 0 | J9: =F9+G9+H9+I9 -> 2108.855 | K9: 2185.24 | L9: =J9+K9 -> 4294.095 | M9: 3160.99 | N9: 0 | O9: =M9+N9 -> 3160.99 | P9: 959.6 | Q9: =P9+O9 -> 4120.59 | R9: =MAX(L9-Q9,0) -> 173.505 | S9: 0 | T9: 0 | U9: 0 | V9: 0 | W9: 0 | X9: 0 | Y9: =AA9+AF9 -> 0 | Z9: =AC9+AL9 -> 3160.99 | AA9: 0 | AB9: 0 | AC9: 3160.99 | AD9: 0 | AE9: 0 | AF9: 0 | AG9: 0 | AH9: 0 | AI9: 0 | AJ9: 0 | AK9: =AG9+AI9 -> 0 | AL9: =AH9+AJ9 -> 0 | AM9: =AE9+AK9 -> 0 | AN9: =AF9+AL9 -> 0
D10: 2 | E10: BK2 | F10: 0 | G10: 587.693 | H10: 4303.24 | I10: 0 | J10: =F10+G10+H10+I10 -> 4890.933 | K10: 398.37 | L10: =J10+K10 -> 5289.303 | M10: 3231.37 | N10: 0 | O10: =M10+N10 -> 3231.37 | P10: 1844.24 | Q10: =P10+O10 -> 5075.61 | R10: =MAX(L10-Q10,0) -> 213.693 | S10: 0 | T10: 0 | U10: 0 | V10: 0 | W10: 0 | X10: 0 | Y10: =AA10+AF10 -> 0 | Z10: =AC10+AL10 -> 0 | AA10: 0 | AB10: 0 | AC10: 0 | AD10: 0 | AE10: 0 | AF10: 0 | AG10: 0 | AH10: 0 | AI10: 0 | AJ10: 0 | AK10: =AG10+AI10 -> 0 | AL10: =AH10+AJ10 -> 0 | AM10: =AE10+AK10 -> 0 | AN10: =AF10+AL10 -> 0
D11: 3 | E11: BK3 | F11: 0 | G11: 513.847 | H11: 3379.72 | I11: 0 | J11: =F11+G11+H11+I11 -> 3893.567 | K11: 730.99 | L11: =J11+K11 -> 4624.557 | M11: 3184.36 | N11: 0 | O11: =M11+N11 -> 3184.36 | P11: 1253.34 | Q11: =P11+O11 -> 4437.7 | R11: =MAX(L11-Q11,0) -> 186.857 | S11: 0 | T11: 0 | U11: 0 | V11: 0 | W11: 0 | X11: 0 | Y11: =AA11+AF11 -> 0 | Z11: =AC11+AL11 -> 0 | AA11: 0 | AB11: 0 | AC11: 0 | AD11: 0 | AE11: 0 | AF11: 0 | AG11: 0 | AH11: 0 | AI11: 0 | AJ11: 0 | AK11: =AG11+AI11 -> 0 | AL11: =AH11+AJ11 -> 0 | AM11: =AE11+AK11 -> 0 | AN11: =AF11+AL11 -> 0
D12: 4 | E12: BK4 | F12: 0 | G12: 713.662 | H12: 4351.47 | I12: 0 | J12: =F12+G12+H12+I12 -> 5065.132 | K12: 1357.75 | L12: =J12+K12 -> 6422.882 | M12: 3311.51 | N12: 0 | O12: =M12+N12 -> 3311.51 | P12: 2851.85 | Q12: =P12+O12 -> 6163.36 | R12: =MAX(L12-Q12,0) -> 259.522 | S12: 0 | T12: 0 | U12: 0 | V12: 0 | W12: 0 | X12: 0 | Y12: =AA12+AF12 -> 0 | Z12: =AC12+AL12 -> 0 | AA12: 0 | AB12: 0 | AC12: 0 | AD12: 0 | AE12: 0 | AF12: 0 | AG12: 0 | AH12: 0 | AI12: 0 | AJ12: 0 | AK12: =AG12+AI12 -> 0 | AL12: =AH12+AJ12 -> 0 | AM12: =AE12+AK12 -> 0 | AN12: =AF12+AL12 -> 0
D13: 5 | E13: BK5 | F13: 0 | G13: 417.257 | H13: 620.69 | I13: 0 | J13: =F13+G13+H13+I13 -> 1037.947 | K13: 2717.39 | L13: =J13+K13 -> 3755.337 | M13: 3122.9 | N13: 0 | O13: =M13+N13 -> 3122.9 | P13: 480.71 | Q13: =P13+O13 -> 3603.61 | R13: =MAX(L13-Q13,0) -> 151.727 | S13: 0 | T13: 0 | U13: 0 | V13: 0 | W13: 0 | X13: 0 | Y13: =AA13+AF13 -> 0 | Z13: =AC13+AL13 -> 0 | AA13: 0 | AB13: 0 | AC13: 0 | AD13: 0 | AE13: 0 | AF13: 0 | AG13: 0 | AH13: 0 | AI13: 0 | AJ13: 0 | AK13: =AG13+AI13 -> 0 | AL13: =AH13+AJ13 -> 0 | AM13: =AE13+AK13 -> 0 | AN13: =AF13+AL13 -> 0
F14: =SUM(F9:F13) -> 0 | G14: =SUM(G9:G13) -> 2709.584 | H14: =SUM(H9:H13) -> 14286.85 | I14: =SUM(I9:I13) -> 0 | J14: =SUM(J9:J13) -> 16996.434 | K14: =SUM(K9:K13) -> 7389.74 | L14: =SUM(L9:L13) -> 24386.174 | M14: =SUM(M9:M13) -> 16011.13 | ... AN14: =SUM(AN9:AN13) -> 0
A16: 2 | B16: 2 | C16: 1 | D16: 1 | E16: BK1 | F16: 0 | G16: 477.125 | H16: 1631.73 | I16: 0 | J16: =F16+G16+H16+I16 -> 2108.855 | K16: 2185.24 | L16: =J16+K16 -> 4294.095 | M16: 3160.99 | N16: 0 | O16: =M16+N16 -> 3160.99 | P16: 959.6 | Q16: =P16+O16 -> 4120.59 | R16: =MAX(L16-Q16,0) -> 173.505 | S16: 0 | T16: 0 | U16: 0 | V16: 0 | W16: 0 | X16: 0 | Y16: =AA16+AF16 -> 0 | Z16: =AC16+AL16 -> 3160.99 | AA16: 0 | AB16: 0 | AC16: 3160.99 | AD16: 1147.335 | AE16: 0 | AF16: 0 | AG16: 1536.53 | AH16: 0 | AI16: 0 | AJ16: 0 | AK16: =AG16+AI16 -> 1536.53 | AL16: =AH16+AJ16 -> 0 | AM16: =AE16+AK16 -> 1536.53 | AN16: =AF16+AL16 -> 0
D17: 2 | E17: BK2 | F17: 0 | G17: 587.693 | H17: 4303.24 | I17: 0 | J17: =F17+G17+H17+I17 -> 4890.933 | K17: 398.37 | L17: =J17+K17 -> 5289.303 | M17: 3231.37 | N17: 0 | O17: =M17+N17 -> 3231.37 | P17: 1844.24 | Q17: =P17+O17 -> 5075.61 | R17: =MAX(L17-Q17,0) -> 213.693 | S17: 0 | T17: 0 | U17: 0 | V17: 0 | W17: 0 | X17: 0 | Y17: =AA17+AF17 -> 0 | Z17: =AC17+AL17 -> 1215.41 | AA17: 0 | AB17: 0 | AC17: 0 | AD17: 0 | AE17: 0 | AF17: 0 | AG17: 0 | AH17: 1215.41 | AI17: 0 | AJ17: 0 | AK17: =AG17+AI17 -> 0 | AL17: =AH17+AJ17 -> 1215.41 | AM17: =AE17+AK17 -> 0 | AN17: =AF17+AL17 -> 1215.41
D18: 3 | E18: BK3 | F18: 0 | G18: 513.847 | H18: 3379.72 | I18: 0 | J18: =F18+G18+H18+I18 -> 3893.567 | K18: 730.99 | L18: =J18+K18 -> 4624.557 | M18: 3184.36 | N18: 0 | O18: =M18+N18 -> 3184.36 | P18: 1253.34 | Q18: =P18+O18 -> 4437.7 | R18: =MAX(L18-Q18,0) -> 186.857 | S18: 0 | T18: 0 | U18: 0 | V18: 0 | W18: 0 | X18: 0 | Y18: =AA18+AF18 -> 0 | Z18: =AC18+AL18 -> 0 | AA18: 0 | AB18: 0 | AC18: 0 | AD18: 0 | AE18: 0 | AF18: 0 | AG18: 0 | AH18: 0 | AI18: 0 | AJ18: 0 | AK18: =AG18+AI18 -> 0 | AL18: =AH18+AJ18 -> 0 | AM18: =AE18+AK18 -> 0 | AN18: =AF18+AL18 -> 0
D19: 4 | E19: BK4 | F19: 0 | G19: 713.662 | H19: 4351.47 | I19: 0 | J19: =F19+G19+H19+I19 -> 5065.132 | K19: 1357.75 | L19: =J19+K19 -> 6422.882 | M19: 3311.51 | N19: 0 | O19: =M19+N19 -> 3311.51 | P19: 2851.85 | Q19: =P19+O19 -> 6163.36 | R19: =MAX(L19-Q19,0) -> 259.522 | S19: 0 | T19: 0 | U19: 0 | V19: 0 | W19: 0 | X19: 0 | Y19: =AA19+AF19 -> 0 | Z19: =AC19+AL19 -> 94.5442 | AA19: 0 | AB19: 0 | AC19: 0 | AD19: 0 | AE19: 0 | AF19: 0 | AG19: 0 | AH19: 94.5442 | AI19: 0 | AJ19: 0 | AK19: =AG19+AI19 -> 0 | AL19: =AH19+AJ19 -> 94.5442 | AM19: =AE19+AK19 -> 0 | AN19: =AF19+AL19 -> 94.5442
D20: 5 | E20: BK5 | F20: 0 | G20: 417.257 | H20: 620.69 | I20: 0 | J20: =F20+G20+H20+I20 -> 1037.947 | K20: 2717.39 | L20: =J20+K20 -> 3755.337 | M20: 3122.9 | N20: 0 | O20: =M20+N20 -> 3122.9 | P20: 480.71 | Q20: =P20+O20 -> 3603.61 | R20: =MAX(L20-Q20,0) -> 151.727 | S20: 0 | T20: 0 | U20: 0 | V20: 0 | W20: 0 | X20: 0 | Y20: =AA20+AF20 -> 0 | Z20: =AC20+AL20 -> 226.573 | AA20: 0 | AB20: 0 | AC20: 0 | AD20: 0 | AE20: 0 | AF20: 0 | AG20: 0 | AH20: 226.573 | AI20: 0 | AJ20: 0 | AK20: =AG20+AI20 -> 0 | AL20: =AH20+AJ20 -> 226.573 | AM20: =AE20+AK20 -> 0 | AN20: =AF20+AL20 -> 226.573
F21: =SUM(F16:F20) -> 0 | G21: =SUM(G16:G20) -> 2709.584 | H21: =SUM(H16:H20) -> 14286.85 | I21: =SUM(I16:I20) -> 0 | J21: =SUM(J16:J20) -> 16996.434 | K21: =SUM(K16:K20) -> 7389.74 | L21: =SUM(L16:L20) -> 24386.174 | M21: =SUM(M16:M20) -> 16011.13 | ... AN21: =SUM(AN16:AN20) -> 1536.5272
A23: 2 | B23: 2 | C23: 2 | D23: 1 | E23: BK1 | F23: 0 | G23: 477.125 | H23: 1631.73 | I23: 0 | J23: =F23+G23+H23+I23 -> 2108.855 | K23: 2185.24 | L23: =J23+K23 -> 4294.095 | M23: 3160.99 | N23: 0 | O23: =M23+N23 -> 3160.99 | P23: 959.6 | Q23: =P23+O23 -> 4120.59 | R23: =MAX(L23-Q23,0) -> 173.505 | S23: 477.125 | T23: 1147.335 | U23: 0 | V23: 908.8102 | W23: 0 | X23: 0 | Y23: =AA23+AF23 -> 0 | Z23: =AC23+AL23 -> 3160.99 | AA23: 0 | AB23: 0 | AC23: 3160.99 | AD23: 1147.335 | AE23: 0 | AF23: 0 | AG23: 1536.53 | AH23: 0 | AI23: 0 | AJ23: 0 | AK23: =AG23+AI23 -> 1536.53 | AL23: =AH23+AJ23 -> 0 | AM23: =AE23+AK23 -> 1536.53 | AN23: =AF23+AL23 -> 0
D24: 2 | E24: BK2 | F24: 0 | G24: 587.693 | H24: 4303.24 | I24: 0 | J24: =F24+G24+H24+I24 -> 4890.933 | K24: 398.37 | L24: =J24+K24 -> 5289.303 | M24: 3231.37 | N24: 0 | O24: =M24+N24 -> 3231.37 | P24: 1844.24 | Q24: =P24+O24 -> 5075.61 | R24: =MAX(L24-Q24,0) -> 213.693 | S24: 0 | T24: 0 | U24: 0 | V24: 0 | W24: 0 | X24: 587.693 | Y24: =AA24+AF24 -> 0 | Z24: =AC24+AL24 -> 1215.41 | AA24: 0 | AB24: 0 | AC24: 0 | AD24: 0 | AE24: 0 | AF24: 0 | AG24: 0 | AH24: 1215.41 | AI24: 0 | AJ24: 0 | AK24: =AG24+AI24 -> 0 | AL24: =AH24+AJ24 -> 1215.41 | AM24: =AE24+AK24 -> 0 | AN24: =AF24+AL24 -> 1215.41
D25: 3 | E25: BK3 | F25: 0 | G25: 513.847 | H25: 3379.72 | I25: 0 | J25: =F25+G25+H25+I25 -> 3893.567 | K25: 730.99 | L25: =J25+K25 -> 4624.557 | M25: 3184.36 | N25: 0 | O25: =M25+N25 -> 3184.36 | P25: 1253.34 | Q25: =P25+O25 -> 4437.7 | R25: =MAX(L25-Q25,0) -> 186.857 | S25: 0 | T25: 0 | U25: 0 | V25: 0 | W25: 0 | X25: 0 | Y25: =AA25+AF25 -> 0 | Z25: =AC25+AL25 -> 0 | AA25: 0 | AB25: 0 | AC25: 0 | AD25: 0 | AE25: 0 | AF25: 0 | AG25: 0 | AH25: 0 | AI25: 0 | AJ25: 0 | AK25: =AG25+AI25 -> 0 | AL25: =AH25+AJ25 -> 0 | AM25: =AE25+AK25 -> 0 | AN25: =AF25+AL25 -> 0
D26: 4 | E26: BK4 | F26: 0 | G26: 713.662 | H26: 4351.47 | I26: 0 | J26: =F26+G26+H26+I26 -> 5065.132 | K26: 1357.75 | L26: =J26+K26 -> 6422.882 | M26: 3311.51 | N26: 0 | O26: =M26+N26 -> 3311.51 | P26: 2851.85 | Q26: =P26+O26 -> 6163.36 | R26: =MAX(L26-Q26,0) -> 259.522 | S26: 0 | T26: 0 | U26: 0 | V26: 0 | W26: 0 | X26: 94.5442 | Y26: =AA26+AF26 -> 0 | Z26: =AC26+AL26 -> 94.5442 | AA26: 0 | AB26: 0 | AC26: 0 | AD26: 0 | AE26: 0 | AF26: 0 | AG26: 0 | AH26: 94.5442 | AI26: 0 | AJ26: 0 | AK26: =AG26+AI26 -> 0 | AL26: =AH26+AJ26 -> 94.5442 | AM26: =AE26+AK26 -> 0 | AN26: =AF26+AL26 -> 94.5442
D27: 5 | E27: BK5 | F27: 0 | G27: 417.257 | H27: 620.69 | I27: 0 | J27: =F27+G27+H27+I27 -> 1037.947 | K27: 2717.39 | L27: =J27+K27 -> 3755.337 | M27: 3122.9 | N27: 0 | O27: =M27+N27 -> 3122.9 | P27: 480.71 | Q27: =P27+O27 -> 3603.61 | R27: =MAX(L27-Q27,0) -> 151.727 | S27: 0 | T27: 0 | U27: 0 | V27: 0 | W27: 0 | X27: 226.573 | Y27: =AA27+AF27 -> 0 | Z27: =AC27+AL27 -> 226.573 | AA27: 0 | AB27: 0 | AC27: 0 | AD27: 0 | AE27: 0 | AF27: 0 | AG27: 0 | AH27: 226.573 | AI27: 0 | AJ27: 0 | AK27: =AG27+AI27 -> 0 | AL27: =AH27+AJ27 -> 226.573 | AM27: =AE27+AK27 -> 0 | AN27: =AF27+AL27 -> 226.573
F28: =SUM(F23:F27) -> 0 | G28: =SUM(G23:G27) -> 2709.584 | H28: =SUM(H23:H27) -> 14286.85 | I28: =SUM(I23:I27) -> 0 | J28: =SUM(J23:J27) -> 16996.434 | K28: =SUM(K23:K27) -> 7389.74 | L28: =SUM(L23:L27) -> 24386.174 | M28: =SUM(M23:M27) -> 16011.13 | ... AN28: =SUM(AN23:AN27) -> 1536.5272
A30: 2 | B30: 2 | C30: 3 | D30: 1 | E30: BK1 | F30: 0 | G30: 2056.145 | H30: 484.39502 | I30: 0 | J30: =F30+G30+H30+I30 -> 2540.54 | K30: 1276.4329 | L30: =J30+K30 -> 3816.9729 | M30: 2683.865 | N30: 0 | O30: =M30+N30 -> 2683.865 | P30: 959.6 | Q30: =P30+O30 -> 3643.465 | R30: =MAX(L30-Q30,0) -> 173.50792 | S30: 477.125 | T30: 1147.335 | U30: 0 | V30: 908.8102 | W30: 0 | X30: 0 | Y30: =AA30+AF30 -> 0 | Z30: =AC30+AL30 -> 2683.865 | AA30: 0 | AB30: 0 | AC30: 2683.865 | AD30: 0 | AE30: 0 | AF30: 0 | AG30: 627.7199 | AH30: 0 | AI30: 0 | AJ30: 0 | AK30: =AG30+AI30 -> 627.7199 | AL30: =AH30+AJ30 -> 0 | AM30: =AE30+AK30 -> 627.7199 | AN30: =AF30+AL30 -> 0
D31: 2 | E31: BK2 | F31: 0 | G31: 0 | H31: 4303.24 | I31: 0 | J31: =F31+G31+H31+I31 -> 4303.24 | K31: 398.37 | L31: =J31+K31 -> 4701.61 | M31: 3231.37 | N31: 0 | O31: =M31+N31 -> 3231.37 | P31: 1256.55 | Q31: =P31+O31 -> 4487.92 | R31: =MAX(L31-Q31,0) -> 213.69 | S31: 0 | T31: 0 | U31: 0 | V31: 0 | W31: 0 | X31: 587.693 | Y31: =AA31+AF31 -> 0 | Z31: =AC31+AL31 -> 627.72 | AA31: 0 | AB31: 0 | AC31: 0 | AD31: 0 | AE31: 0 | AF31: 0 | AG31: 0 | AH31: 627.72 | AI31: 0 | AJ31: 0 | AK31: =AG31+AI31 -> 0 | AL31: =AH31+AJ31 -> 627.72 | AM31: =AE31+AK31 -> 0 | AN31: =AF31+AL31 -> 627.72
D32: 3 | E32: BK3 | F32: 0 | G32: 513.847 | H32: 3379.72 | I32: 0 | J32: =F32+G32+H32+I32 -> 3893.567 | K32: 730.99 | L32: =J32+K32 -> 4624.557 | M32: 3184.36 | N32: 0 | O32: =M32+N32 -> 3184.36 | P32: 1253.34 | Q32: =P32+O32 -> 4437.7 | R32: =MAX(L32-Q32,0) -> 186.857 | S32: 0 | T32: 0 | U32: 0 | V32: 0 | W32: 0 | X32: 0 | Y32: =AA32+AF32 -> 0 | Z32: =AC32+AL32 -> 0 | AA32: 0 | AB32: 0 | AC32: 0 | AD32: 0 | AE32: 0 | AF32: 0 | AG32: 0 | AH32: 0 | AI32: 0 | AJ32: 0 | AK32: =AG32+AI32 -> 0 | AL32: =AH32+AJ32 -> 0 | AM32: =AE32+AK32 -> 0 | AN32: =AF32+AL32 -> 0
D33: 4 | E33: BK4 | F33: 0 | G33: 619.11774 | H33: 4351.47 | I33: 0 | J33: =F33+G33+H33+I33 -> 4970.5877 | K33: 1357.75 | L33: =J33+K33 -> 6328.3377 | M33: 3311.51 | N33: 0 | O33: =M33+N33 -> 3311.51 | P33: 2757.3058 | Q33: =P33+O33 -> 6068.8158 | R33: =MAX(L33-Q33,0) -> 259.52194 | S33: 0 | T33: 0 | U33: 0 | V33: 0 | W33: 0 | X33: 94.5442 | Y33: =AA33+AF33 -> 0 | Z33: =AC33+AL33 -> 0 | AA33: 0 | AB33: 0 | AC33: 0 | AD33: 0 | AE33: 0 | AF33: 0 | AG33: 0 | AH33: 0 | AI33: 0 | AJ33: 0 | AK33: =AG33+AI33 -> 0 | AL33: =AH33+AJ33 -> 0 | AM33: =AE33+AK33 -> 0 | AN33: =AF33+AL33 -> 0
D34: 5 | E34: BK5 | F34: 0 | G34: 190.68411 | H34: 620.69 | I34: 0 | J34: =F34+G34+H34+I34 -> 811.37411 | K34: 2717.39 | L34: =J34+K34 -> 3528.7641 | M34: 3122.9 | N34: 0 | O34: =M34+N34 -> 3122.9 | P34: 254.1371 | Q34: =P34+O34 -> 3377.0371 | R34: =MAX(L34-Q34,0) -> 151.72701 | S34: 0 | T34: 0 | U34: 0 | V34: 0 | W34: 0 | X34: 226.573 | Y34: =AA34+AF34 -> 0 | Z34: =AC34+AL34 -> 0 | AA34: 0 | AB34: 0 | AC34: 0 | AD34: 0 | AE34: 0 | AF34: 0 | AG34: 0 | AH34: 0 | AI34: 0 | AJ34: 0 | AK34: =AG34+AI34 -> 0 | AL34: =AH34+AJ34 -> 0 | AM34: =AE34+AK34 -> 0 | AN34: =AF34+AL34 -> 0
F35: =SUM(F30:F34) -> 0 | G35: =SUM(G30:G34) -> 3379.7939 | H35: =SUM(H30:H34) -> 13139.515 | I35: =SUM(I30:I34) -> 0 | J35: =SUM(J30:J34) -> 16519.309 | K35: =SUM(K30:K34) -> 6480.9329 | L35: =SUM(L30:L34) -> 23000.242 | M35: =SUM(M30:M34) -> 15534.005 | ... AN35: =SUM(AN30:AN34) -> 627.72
A37: 2 | B37: 3 | C37: 1 | D37: 1 | E37: BK1 | F37: 0 | G37: 2056.145 | H37: 484.39502 | I37: 0 | J37: =F37+G37+H37+I37 -> 2540.54 | K37: 1276.4329 | L37: =J37+K37 -> 3816.9729 | M37: 2683.865 | N37: 0 | O37: =M37+N37 -> 2683.865 | P37: 959.6 | Q37: =P37+O37 -> 3643.465 | R37: =MAX(L37-Q37,0) -> 173.50792 | S37: 477.125 | T37: 1147.335 | U37: 0 | V37: 908.8102 | W37: 0 | X37: 0 | Y37: =AA37+AF37 -> 0 | Z37: =AC37+AL37 -> 2698.4645 | AA37: 0 | AB37: 0 | AC37: 2683.865 | AD37: 0 | AE37: 0 | AF37: 0 | AG37: 455.03705 | AH37: 14.599504 | AI37: 0 | AJ37: 0 | AK37: =AG37+AI37 -> 455.03705 | AL37: =AH37+AJ37 -> 14.599504 | AM37: =AE37+AK37 -> 455.03705 | AN37: =AF37+AL37 -> 14.599504
D38: 2 | E38: BK2 | F38: 0 | G38: 0 | H38: 4303.24 | I38: 0 | J38: =F38+G38+H38+I38 -> 4303.24 | K38: 398.37 | L38: =J38+K38 -> 4701.61 | M38: 3231.37 | N38: 0 | O38: =M38+N38 -> 3231.37 | P38: 1256.55 | Q38: =P38+O38 -> 4487.92 | R38: =MAX(L38-Q38,0) -> 213.69 | S38: 0 | T38: 0 | U38: 0 | V38: 0 | W38: 0 | X38: 587.693 | Y38: =AA38+AF38 -> 0 | Z38: =AC38+AL38 -> 406.7064 | AA38: 0 | AB38: 0 | AC38: 0 | AD38: 0 | AE38: 0 | AF38: 0 | AG38: 53.187054 | AH38: 406.7064 | AI38: 0 | AJ38: 0 | AK38: =AG38+AI38 -> 53.187054 | AL38: =AH38+AJ38 -> 406.7064 | AM38: =AE38+AK38 -> 53.187054 | AN38: =AF38+AL38 -> 406.7064
D39: 3 | E39: BK3 | F39: 0 | G39: 513.847 | H39: 3379.72 | I39: 0 | J39: =F39+G39+H39+I39 -> 3893.567 | K39: 730.99 | L39: =J39+K39 -> 4624.557 | M39: 3184.36 | N39: 0 | O39: =M39+N39 -> 3184.36 | P39: 1253.34 | Q39: =P39+O39 -> 4437.7 | R39: =MAX(L39-Q39,0) -> 186.857 | S39: 0 | T39: 0 | U39: 0 | V39: 0 | W39: 0 | X39: 0 | Y39: =AA39+AF39 -> 0 | Z39: =AC39+AL39 -> 38.58755 | AA39: 0 | AB39: 0 | AC39: 0 | AD39: 0 | AE39: 0 | AF39: 0 | AG39: 0 | AH39: 38.58755 | AI39: 0 | AJ39: 0 | AK39: =AG39+AI39 -> 0 | AL39: =AH39+AJ39 -> 38.58755 | AM39: =AE39+AK39 -> 0 | AN39: =AF39+AL39 -> 38.58755
D40: 4 | E40: BK4 | F40: 0 | G40: 619.11774 | H40: 4351.47 | I40: 0 | J40: =F40+G40+H40+I40 -> 4970.5877 | K40: 1357.75 | L40: =J40+K40 -> 6328.3377 | M40: 3311.51 | N40: 0 | O40: =M40+N40 -> 3311.51 | P40: 2757.3058 | Q40: =P40+O40 -> 6068.8158 | R40: =MAX(L40-Q40,0) -> 259.52194 | S40: 0 | T40: 0 | U40: 0 | V40: 0 | W40: 0 | X40: 94.5442 | Y40: =AA40+AF40 -> 0 | Z40: =AC40+AL40 -> 14.229652 | AA40: 0 | AB40: 0 | AC40: 0 | AD40: 0 | AE40: 0 | AF40: 0 | AG40: 0 | AH40: 14.229652 | AI40: 0 | AJ40: 0 | AK40: =AG40+AI40 -> 0 | AL40: =AH40+AJ40 -> 14.229652 | AM40: =AE40+AK40 -> 0 | AN40: =AF40+AL40 -> 14.229652
D41: 5 | E41: BK5 | F41: 0 | G41: 190.68411 | H41: 620.69 | I41: 0 | J41: =F41+G41+H41+I41 -> 811.37411 | K41: 2717.39 | L41: =J41+K41 -> 3528.7641 | M41: 3122.9 | N41: 0 | O41: =M41+N41 -> 3122.9 | P41: 254.1371 | Q41: =P41+O41 -> 3377.0371 | R41: =MAX(L41-Q41,0) -> 151.72701 | S41: 0 | T41: 0 | U41: 0 | V41: 0 | W41: 0 | X41: 226.573 | Y41: =AA41+AF41 -> 0 | Z41: =AC41+AL41 -> 34.101 | AA41: 0 | AB41: 0 | AC41: 0 | AD41: 0 | AE41: 0 | AF41: 0 | AG41: 0 | AH41: 34.101 | AI41: 0 | AJ41: 0 | AK41: =AG41+AI41 -> 0 | AL41: =AH41+AJ41 -> 34.101 | AM41: =AE41+AK41 -> 0 | AN41: =AF41+AL41 -> 34.101
F42: =SUM(F37:F41) -> 0 | G42: =SUM(G37:G41) -> 3379.7939 | H42: =SUM(H37:H41) -> 13139.515 | I42: =SUM(I37:I41) -> 0 | J42: =SUM(J37:J41) -> 16519.309 | K42: =SUM(K37:K41) -> 6480.9329 | L42: =SUM(L37:L41) -> 23000.242 | M42: =SUM(M37:M41) -> 15534.005 | ... AN42: =SUM(AN37:AN41) -> 508.22411
A44: 2 | B44: 2 | C44: 2 | D44: 1 | E44: BK1 | F44: 0 | G44: 0 | H44: 1631.73 | I44: 0 | J44: =F44+G44+H44+I44 -> 1631.73 | K44: 2185.24 | L44: =J44+K44 -> 3816.97 | M44: 2683.865 | N44: 0 | O44: =M44+N44 -> 2683.865 | P44: 959.6 | Q44: =P44+O44 -> 3643.465 | R44: =MAX(L44-Q44,0) -> 173.505 | S44: 0 | T44: 0 | U44: 0 | V44: 0 | W44: 0 | X44: 0 | Y44: =AA44+AF44 -> 0 | Z44: =AC44+AL44 -> 2683.865 | AA44: 0 | AB44: 0 | AC44: 2683.865 | AD44: 1147.335 | AE44: 0 | AF44: 0 | AG44: 1536.53 | AH44: 0 | AI44: 0 | AJ44: 0 | AK44: =AG44+AI44 -> 1536.53 | AL44: =AH44+AJ44 -> 0 | AM44: =AE44+AK44 -> 1536.53 | AN44: =AF44+AL44 -> 0
D45: 2 | E45: BK2 | F45: 0 | G45: 587.693 | H45: 4303.24 | I45: 0 | J45: =F45+G45+H45+I45 -> 4890.933 | K45: 398.37 | L45: =J45+K45 -> 5289.303 | M45: 3231.37 | N45: 0 | O45: =M45+N45 -> 3231.37 | P45: 1844.24 | Q45: =P45+O45 -> 5075.61 | R45: =MAX(L45-Q45,0) -> 213.693 | S45: 0 | T45: 0 | U45: 0 | V45: 0 | W45: 0 | X45: 0 | Y45: =AA45+AF45 -> 0 | Z45: =AC45+AL45 -> 1215.41 | AA45: 0 | AB45: 0 | AC45: 0 | AD45: 574.5329 | AE45: 0 | AF45: 0 | AG45: 53.187054 | AH45: 1215.41 | AI45: 0 | AJ45: 0 | AK45: =AG45+AI45 -> 53.187054 | AL45: =AH45+AJ45 -> 1215.41 | AM45: =AE45+AK45 -> 53.187054 | AN45: =AF45+AL45 -> 1215.41
D46: 3 | E46: BK3 | F46: 0 | G46: 513.847 | H46: 3379.72 | I46: 0 | J46: =F46+G46+H46+I46 -> 3893.567 | K46: 730.99 | L46: =J46+K46 -> 4624.557 | M46: 3184.36 | N46: 0 | O46: =M46+N46 -> 3184.36 | P46: 1253.34 | Q46: =P46+O46 -> 4437.7 | R46: =MAX(L46-Q46,0) -> 186.857 | S46: 0 | T46: 0 | U46: 0 | V46: 0 | W46: 0 | X46: 0 | Y46: =AA46+AF46 -> 0 | Z46: =AC46+AL46 -> 0 | AA46: 0 | AB46: 0 | AC46: 0 | AD46: 0 | AE46: 0 | AF46: 0 | AG46: 0 | AH46: 0 | AI46: 0 | AJ46: 0 | AK46: =AG46+AI46 -> 0 | AL46: =AH46+AJ46 -> 0 | AM46: =AE46+AK46 -> 0 | AN46: =AF46+AL46 -> 0
D47: 4 | E47: BK4 | F47: 0 | G47: 713.662 | H47: 4351.47 | I47: 0 | J47: =F47+G47+H47+I47 -> 5065.132 | K47: 1357.75 | L47: =J47+K47 -> 6422.882 | M47: 3311.51 | N47: 0 | O47: =M47+N47 -> 3311.51 | P47: 2851.85 | Q47: =P47+O47 -> 6163.36 | R47: =MAX(L47-Q47,0) -> 259.522 | S47: 0 | T47: 0 | U47: 0 | V47: 0 | W47: 0 | X47: 0 | Y47: =AA47+AF47 -> 0 | Z47: =AC47+AL47 -> 94.5442 | AA47: 0 | AB47: 0 | AC47: 0 | AD47: 0 | AE47: 0 | AF47: 0 | AG47: 0 | AH47: 94.5442 | AI47: 0 | AJ47: 0 | AK47: =AG47+AI47 -> 0 | AL47: =AH47+AJ47 -> 94.5442 | AM47: =AE47+AK47 -> 0 | AN47: =AF47+AL47 -> 94.5442
D48: 5 | E48: BK5 | F48: 0 | G48: 417.257 | H48: 620.69 | I48: 0 | J48: =F48+G48+H48+I48 -> 1037.947 | K48: 2717.39 | L48: =J48+K48 -> 3755.337 | M48: 3122.9 | N48: 0 | O48: =M48+N48 -> 3122.9 | P48: 480.71 | Q48: =P48+O48 -> 3603.61 | R48: =MAX(L48-Q48,0) -> 151.727 | S48: 0 | T48: 0 | U48: 0 | V48: 0 | W48: 0 | X48: 0 | Y48: =AA48+AF48 -> 0 | Z48: =AC48+AL48 -> 226.573 | AA48: 0 | AB48: 0 | AC48: 0 | AD48: 0 | AE48: 0 | AF48: 0 | AG48: 0 | AH48: 226.573 | AI48: 0 | AJ48: 0 | AK48: =AG48+AI48 -> 0 | AL48: =AH48+AJ48 -> 226.573 | AM48: =AE48+AK48 -> 0 | AN48: =AF48+AL48 -> 226.573
F49: =SUM(F44:F48) -> 0 | G49: =SUM(G44:G48) -> 2232.459 | H49: =SUM(H44:H48) -> 14286.85 | I49: =SUM(I44:I48) -> 0 | J49: =SUM(J44:J48) -> 16519.309 | K49: =SUM(K44:K48) -> 7389.74 | L49: =SUM(L44:L48) -> 23909.049 | M49: =SUM(M44:M48) -> 15534.005 | ... AN49: =SUM(AN44:AN48) -> 1536.5272
A51: 2 | B51: 2 | C51: 3 | D51: 1 | E51: BK1 | F51: 0 | G51: 0 | H51: 1631.73 | I51: 0 | J51: =F51+G51+H51+I51 -> 1631.73 | K51: 2185.24 | L51: =J51+K51 -> 3816.97 | M51: 2683.865 | N51: 0 | O51: =M51+N51 -> 2683.865 | P51: 959.6 | Q51: =P51+O51 -> 3643.465 | R51: =MAX(L51-Q51,0) -> 173.505 | S51: 0 | T51: 0 | U51: 0 | V51: 908.8102 | W51: 0 | X51: 0 | Y51: =AA51+AF51 -> 0 | Z51: =AC51+AL51 -> 2683.865 | AA51: 0 | AB51: 0 | AC51: 2683.865 | AD51: 1147.335 | AE51: 0 | AF51: 0 | AG51: 1536.53 | AH51: 0 | AI51: 0 | AJ51: 0 | AK51: =AG51+AI51 -> 1536.53 | AL51: =AH51+AJ51 -> 0 | AM51: =AE51+AK51 -> 1536.53 | AN51: =AF51+AL51 -> 0
D52: 2 | E52: BK2 | F52: 0 | G52: 587.693 | H52: 4303.24 | I52: 0 | J52: =F52+G52+H52+I52 -> 4890.933 | K52: 398.37 | L52: =J52+K52 -> 5289.303 | M52: 3231.37 | N52: 0 | O52: =M52+N52 -> 3231.37 | P52: 1844.24 | Q52: =P52+O52 -> 5075.61 | R52: =MAX(L52-Q52,0) -> 213.693 | S52: 0 | T52: 574.5329 | U52: 0 | V52: 0 | W52: 0 | X52: 587.693 | Y52: =AA52+AF52 -> 0 | Z52: =AC52+AL52 -> 1215.41 | AA52: 0 | AB52: 0 | AC52: 0 | AD52: 574.5329 | AE52: 0 | AF52: 0 | AG52: 53.187054 | AH52: 1215.41 | AI52: 0 | AJ52: 0 | AK52: =AG52+AI52 -> 53.187054 | AL52: =AH52+AJ52 -> 1215.41 | AM52: =AE52+AK52 -> 53.187054 | AN52: =AF52+AL52 -> 1215.41
D53: 3 | E53: BK3 | F53: 0 | G53: 513.847 | H53: 3379.72 | I53: 0 | J53: =F53+G53+H53+I53 -> 3893.567 | K53: 730.99 | L53: =J53+K53 -> 4624.557 | M53: 3184.36 | N53: 0 | O53: =M53+N53 -> 3184.36 | P53: 1253.34 | Q53: =P53+O53 -> 4437.7 | R53: =MAX(L53-Q53,0) -> 186.857 | S53: 0 | T53: 0 | U53: 0 | V53: 0 | W53: 0 | X53: 0 | Y53: =AA53+AF53 -> 0 | Z53: =AC53+AL53 -> 0 | AA53: 0 | AB53: 0 | AC53: 0 | AD53: 0 | AE53: 0 | AF53: 0 | AG53: 0 | AH53: 0 | AI53: 0 | AJ53: 0 | AK53: =AG53+AI53 -> 0 | AL53: =AH53+AJ53 -> 0 | AM53: =AE53+AK53 -> 0 | AN53: =AF53+AL53 -> 0
D54: 4 | E54: BK4 | F54: 0 | G54: 713.662 | H54: 4351.47 | I54: 0 | J54: =F54+G54+H54+I54 -> 5065.132 | K54: 1357.75 | L54: =J54+K54 -> 6422.882 | M54: 3311.51 | N54: 0 | O54: =M54+N54 -> 3311.51 | P54: 2851.85 | Q54: =P54+O54 -> 6163.36 | R54: =MAX(L54-Q54,0) -> 259.522 | S54: 0 | T54: 0 | U54: 0 | V54: 0 | W54: 0 | X54: 94.5442 | Y54: =AA54+AF54 -> 0 | Z54: =AC54+AL54 -> 94.5442 | AA54: 0 | AB54: 0 | AC54: 0 | AD54: 0 | AE54: 0 | AF54: 0 | AG54: 0 | AH54: 94.5442 | AI54: 0 | AJ54: 0 | AK54: =AG54+AI54 -> 0 | AL54: =AH54+AJ54 -> 94.5442 | AM54: =AE54+AK54 -> 0 | AN54: =AF54+AL54 -> 94.5442
D55: 5 | E55: BK5 | F55: 0 | G55: 417.257 | H55: 620.69 | I55: 0 | J55: =F55+G55+H55+I55 -> 1037.947 | K55: 2717.39 | L55: =J55+K55 -> 3755.337 | M55: 3122.9 | N55: 0 | O55: =M55+N55 -> 3122.9 | P55: 480.71 | Q55: =P55+O55 -> 3603.61 | R55: =MAX(L55-Q55,0) -> 151.727 | S55: 0 | T55: 0 | U55: 0 | V55: 0 | W55: 0 | X55: 226.573 | Y55: =AA55+AF55 -> 0 | Z55: =AC55+AL55 -> 226.573 | AA55: 0 | AB55: 0 | AC55: 0 | AD55: 0 | AE55: 0 | AF55: 0 | AG55: 0 | AH55: 226.573 | AI55: 0 | AJ55: 0 | AK55: =AG55+AI55 -> 0 | AL55: =AH55+AJ55 -> 226.573 | AM55: =AE55+AK55 -> 0 | AN55: =AF55+AL55 -> 226.573
F56: =SUM(F51:F55) -> 0 | G56: =SUM(G51:G55) -> 2232.459 | H56: =SUM(H51:H55) -> 14286.85 | I56: =SUM(I51:I55) -> 0 | J56: =SUM(J51:J55) -> 16519.309 | K56: =SUM(K51:K55) -> 7389.74 | L56: =SUM(L51:L55) -> 23909.049 | M56: =SUM(M51:M55) -> 15534.005 | ... AN56: =SUM(AN51:AN55) -> 1536.5272
A58: 2 | B58: 2 | C58: 4 | D58: 1 | E58: BK1 | F58: 0 | G58: 908.8101 | H58: 1631.73 | I58: 0 | J58: =F58+G58+H58+I58 -> 2540.5401 | K58: 1276.4329 | L58: =J58+K58 -> 3816.973 | M58: 2683.865 | N58: 0 | O58: =M58+N58 -> 2683.865 | P58: 959.6 | Q58: =P58+O58 -> 3643.465 | R58: =MAX(L58-Q58,0) -> 173.508 | S58: 0 | T58: 0 | U58: 0 | V58: 0 | W58: 0 | X58: 0 | Y58: =AA58+AF58 -> 0 | Z58: =AC58+AL58 -> 2683.865 | AA58: 0 | AB58: 0 | AC58: 2683.865 | AD58: 1147.335 | AE58: 0 | AF58: 0 | AG58: 627.7199 | AH58: 0 | AI58: 0 | AJ58: 0 | AK58: =AG58+AI58 -> 627.7199 | AL58: =AH58+AJ58 -> 0 | AM58: =AE58+AK58 -> 627.7199 | AN58: =AF58+AL58 -> 0
D59: 2 | E59: BK2 | F59: 0 | G59: 574.53284 | H59: 3728.7073 | I59: 0 | J59: =F59+G59+H59+I59 -> 4303.2401 | K59: 398.37 | L59: =J59+K59 -> 4701.6101 | M59: 3231.37 | N59: 0 | O59: =M59+N59 -> 3231.37 | P59: 1256.55 | Q59: =P59+O59 -> 4487.92 | R59: =MAX(L59-Q59,0) -> 213.69014 | S59: 0 | T59: 0 | U59: 0 | V59: 0 | W59: 0 | X59: 0 | Y59: =AA59+AF59 -> 0 | Z59: =AC59+AL59 -> 627.72 | AA59: 0 | AB59: 0 | AC59: 0 | AD59: 0 | AE59: 0 | AF59: 0 | AG59: 53.187054 | AH59: 627.72 | AI59: 0 | AJ59: 0 | AK59: =AG59+AI59 -> 53.187054 | AL59: =AH59+AJ59 -> 627.72 | AM59: =AE59+AK59 -> 53.187054 | AN59: =AF59+AL59 -> 627.72
D60: 3 | E60: BK3 | F60: 0 | G60: 513.847 | H60: 3379.72 | I60: 0 | J60: =F60+G60+H60+I60 -> 3893.567 | K60: 730.99 | L60: =J60+K60 -> 4624.557 | M60: 3184.36 | N60: 0 | O60: =M60+N60 -> 3184.36 | P60: 1253.34 | Q60: =P60+O60 -> 4437.7 | R60: =MAX(L60-Q60,0) -> 186.857 | S60: 0 | T60: 0 | U60: 0 | V60: 0 | W60: 0 | X60: 0 | Y60: =AA60+AF60 -> 0 | Z60: =AC60+AL60 -> 0 | AA60: 0 | AB60: 0 | AC60: 0 | AD60: 0 | AE60: 0 | AF60: 0 | AG60: 0 | AH60: 0 | AI60: 0 | AJ60: 0 | AK60: =AG60+AI60 -> 0 | AL60: =AH60+AJ60 -> 0 | AM60: =AE60+AK60 -> 0 | AN60: =AF60+AL60 -> 0
D61: 4 | E61: BK4 | F61: 0 | G61: 619.11774 | H61: 4351.47 | I61: 0 | J61: =F61+G61+H61+I61 -> 4970.5877 | K61: 1357.75 | L61: =J61+K61 -> 6328.3377 | M61: 3311.51 | N61: 0 | O61: =M61+N61 -> 3311.51 | P61: 2757.3058 | Q61: =P61+O61 -> 6068.8158 | R61: =MAX(L61-Q61,0) -> 259.52194 | S61: 0 | T61: 0 | U61: 0 | V61: 0 | W61: 0 | X61: 0 | Y61: =AA61+AF61 -> 0 | Z61: =AC61+AL61 -> 0 | AA61: 0 | AB61: 0 | AC61: 0 | AD61: 0 | AE61: 0 | AF61: 0 | AG61: 0 | AH61: 0 | AI61: 0 | AJ61: 0 | AK61: =AG61+AI61 -> 0 | AL61: =AH61+AJ61 -> 0 | AM61: =AE61+AK61 -> 0 | AN61: =AF61+AL61 -> 0
D62: 5 | E62: BK5 | F62: 0 | G62: 190.68411 | H62: 620.69 | I62: 0 | J62: =F62+G62+H62+I62 -> 811.37411 | K62: 2717.39 | L62: =J62+K62 -> 3528.7641 | M62: 3122.9 | N62: 0 | O62: =M62+N62 -> 3122.9 | P62: 254.1371 | Q62: =P62+O62 -> 3377.0371 | R62: =MAX(L62-Q62,0) -> 151.72701 | S62: 0 | T62: 0 | U62: 0 | V62: 0 | W62: 0 | X62: 0 | Y62: =AA62+AF62 -> 0 | Z62: =AC62+AL62 -> 0 | AA62: 0 | AB62: 0 | AC62: 0 | AD62: 0 | AE62: 0 | AF62: 0 | AG62: 0 | AH62: 0 | AI62: 0 | AJ62: 0 | AK62: =AG62+AI62 -> 0 | AL62: =AH62+AJ62 -> 0 | AM62: =AE62+AK62 -> 0 | AN62: =AF62+AL62 -> 0
F63: =SUM(F58:F62) -> 0 | G63: =SUM(G58:G62) -> 2806.9918 | H63: =SUM(H58:H62) -> 13712.317 | I63: =SUM(I58:I62) -> 0 | J63: =SUM(J58:J62) -> 16519.309 | K63: =SUM(K58:K62) -> 6480.9329 | L63: =SUM(L58:L62) -> 23000.242 | M63: =SUM(M58:M62) -> 15534.005 | ... AN63: =SUM(AN58:AN62) -> 627.72
A65: 2 | B65: 3 | C65: 1 | D65: 1 | E65: BK1 | F65: 0 | G65: 908.8101 | H65: 1631.73 | I65: 0 | J65: =F65+G65+H65+I65 -> 2540.5401 | K65: 1276.4329 | L65: =J65+K65 -> 3816.973 | M65: 2683.865 | N65: 0 | O65: =M65+N65 -> 2683.865 | P65: 959.6 | Q65: =P65+O65 -> 3643.465 | R65: =MAX(L65-Q65,0) -> 173.508 | S65: 0 | T65: 0 | U65: 0 | V65: 0 | W65: 0 | X65: 0 | Y65: =AA65+AF65 -> 0 | Z65: =AC65+AL65 -> 2683.865 | AA65: 0 | AB65: 0 | AC65: 2683.865 | AD65: 1147.335 | AE65: 0 | AF65: 0 | AG65: 627.7199 | AH65: 0 | AI65: 0 | AJ65: 0 | AK65: =AG65+AI65 -> 627.7199 | AL65: =AH65+AJ65 -> 0 | AM65: =AE65+AK65 -> 627.7199 | AN65: =AF65+AL65 -> 0
D66: 2 | E66: BK2 | F66: 0 | G66: 574.53284 | H66: 3728.7073 | I66: 0 | J66: =F66+G66+H66+I66 -> 4303.2401 | K66: 398.37 | L66: =J66+K66 -> 4701.6101 | M66: 3231.37 | N66: 0 | O66: =M66+N66 -> 3231.37 | P66: 1256.55 | Q66: =P66+O66 -> 4487.92 | R66: =MAX(L66-Q66,0) -> 213.69014 | S66: 0 | T66: 0 | U66: 0 | V66: 0 | W66: 0 | X66: 0 | Y66: =AA66+AF66 -> 0 | Z66: =AC66+AL66 -> 627.72 | AA66: 0 | AB66: 0 | AC66: 0 | AD66: 0 | AE66: 0 | AF66: 0 | AG66: 53.187054 | AH66: 627.72 | AI66: 0 | AJ66: 0 | AK66: =AG66+AI66 -> 53.187054 | AL66: =AH66+AJ66 -> 627.72 | AM66: =AE66+AK66 -> 53.187054 | AN66: =AF66+AL66 -> 627.72
D67: 3 | E67: BK3 | F67: 0 | G67: 513.847 | H67: 3379.72 | I67: 0 | J67: =F67+G67+H67+I67 -> 3893.567 | K67: 730.99 | L67: =J67+K67 -> 4624.557 | M67: 3184.36 | N67: 0 | O67: =M67+N67 -> 3184.36 | P67: 1253.34 | Q67: =P67+O67 -> 4437.7 | R67: =MAX(L67-Q67,0) -> 186.857 | S67: 0 | T67: 0 | U67: 0 | V67: 0 | W67: 0 | X67: 0 | Y67: =AA67+AF67 -> 0 | Z67: =AC67+AL67 -> 0 | AA67: 0 | AB67: 0 | AC67: 0 | AD67: 0 | AE67: 0 | AF67: 0 | AG67: 0 | AH67: 0 | AI67: 0 | AJ67: 0 | AK67: =AG67+AI67 -> 0 | AL67: =AH67+AJ67 -> 0 | AM67: =AE67+AK67 -> 0 | AN67: =AF67+AL67 -> 0
D68: 4 | E68: BK4 | F68: 0 | G68: 619.11774 | H68: 4351.47 | I68: 0 | J68: =F68+G68+H68+I68 -> 4970.5877 | K68: 1357.75 | L68: =J68+K68 -> 6328.3377 | M68: 3311.51 | N68: 0 | O68: =M68+N68 -> 3311.51 | P68: 2757.3058 | Q68: =P68+O68 -> 6068.8158 | R68: =MAX(L68-Q68,0) -> 259.52194 | S68: 0 | T68: 0 | U68: 0 | V68: 0 | W68: 0 | X68: 0 | Y68: =AA68+AF68 -> 0 | Z68: =AC68+AL68 -> 0 | AA68: 0 | AB68: 0 | AC68: 0 | AD68: 0 | AE68: 0 | AF68: 0 | AG68: 0 | AH68: 0 | AI68: 0 | AJ68: 0 | AK68: =AG68+AI68 -> 0 | AL68: =AH68+AJ68 -> 0 | AM68: =AE68+AK68 -> 0 | AN68: =AF68+AL68 -> 0
D69: 5 | E69: BK5 | F69: 0 | G69: 190.68411 | H69: 620.69 | I69: 0 | J69: =F69+G69+H69+I69 -> 811.37411 | K69: 2717.39 | L69: =J69+K69 -> 3528.7641 | M69: 3122.9 | N69: 0 | O69: =M69+N69 -> 3122.9 | P69: 254.1371 | Q69: =P69+O69 -> 3377.0371 | R69: =MAX(L69-Q69,0) -> 151.72701 | S69: 0 | T69: 0 | U69: 0 | V69: 0 | W69: 0 | X69: 0 | Y69: =AA69+AF69 -> 0 | Z69: =AC69+AL69 -> 0 | AA69: 0 | AB69: 0 | AC69: 0 | AD69: 0 | AE69: 0 | AF69: 0 | AG69: 0 | AH69: 0 | AI69: 0 | AJ69: 0 | AK69: =AG69+AI69 -> 0 | AL69: =AH69+AJ69 -> 0 | AM69: =AE69+AK69 -> 0 | AN69: =AF69+AL69 -> 0
F70: =SUM(F65:F69) -> 0 | G70: =SUM(G65:G69) -> 2806.9918 | H70: =SUM(H65:H69) -> 13712.317 | I70: =SUM(I65:I69) -> 0 | J70: =SUM(J65:J69) -> 16519.309 | K70: =SUM(K65:K69) -> 6480.9329 | L70: =SUM(L65:L69) -> 23000.242 | M70: =SUM(M65:M69) -> 15534.005 | ... AN70: =SUM(AN65:AN69) -> 627.72

Sheet BI之过程-theta_Shock_exBI_t=0_0313
A1: 子过程 | B1: id | C1: tau | D1: t | F1: A_BI | M1: Z_BI | T1: Lo_BI | AA1: Li_BI | AH1: Bi_BI | AO1: Bo_BI | AV1: Shock_BI_def | BC1: Shock_BI_run_ilq | BJ1: Shock_BI_run_br | BQ1: Shock_BI_run
A2: 2 | C2: 1 | D2: 0 | F2: 0 | G2: 1728.55 | H2: 0 | I2: 134.46 | J2: 322.23 | K2: =SUM(F2:J2) -> 2185.24 | M2: 0 | N2: 109.35 | O2: 730.99 | P2: 119.26 | Q2: 0 | R2: =SUM(M2:Q2) -> 959.6 | T2: 0 | U2: 0 | V2: 0 | W2: 0 | X2: 0 | Y2: =SUM(T2:X2) -> 0 | AA2: 0 | AB2: 0 | AC2: 0 | AD2: 0 | AE2: 0 | AF2: =SUM(AA2:AE2) -> 0 | AH2: 0 | AI2: 0 | AJ2: 0 | AK2: 0 | AL2: 0 | AM2: =SUM(AH2:AL2) -> 0 | AO2: 0 | AP2: 0 | AQ2: 0 | AR2: 0 | AS2: 0 | AT2: =SUM(AO2:AS2) -> 0 | AV2: 0 | AW2: 0 | AX2: 0 | AY2: 0 | AZ2: 0 | BA2: =SUM(AV2:AZ2) -> 0 | BC2: 0 | BD2: 0 | BE2: 0 | BF2: 0 | BG2: 0 | BH2: =SUM(BC2:BG2) -> 0 | BJ2: 0 | BK2: 0 | BL2: 0 | BM2: 0 | BN2: 0 | BO2: =SUM(BJ2:BN2) -> 0 | BQ2: =BJ2+BC2 -> 0 | BR2: =BK2+BD2 -> 0 | BS2: =BL2+BE2 -> 0 | BT2: =BM2+BF2 -> 0 | BU2: =BN2+BG2 -> 0 | BV2: =SUM(BQ2:BU2) -> 0
F3: 109.35 | G3: 0 | H3: 289.02 | I3: 0 | J3: 0 | K3: =SUM(F3:J3) -> 398.37 | M3: 1728.55 | N3: 0 | O3: 0 | P3: 115.69 | Q3: 0 | R3: =SUM(M3:Q3) -> 1844.24 | T3: 0 | U3: 0 | V3: 0 | W3: 0 | X3: 0 | Y3: =SUM(T3:X3) -> 0 | AA3: 0 | AB3: 0 | AC3: 0 | AD3: 0 | AE3: 0 | AF3: =SUM(AA3:AE3) -> 0 | AH3: 0 | AI3: 0 | AJ3: 0 | AK3: 0 | AL3: 0 | AM3: =SUM(AH3:AL3) -> 0 | AO3: 0 | AP3: 0 | AQ3: 0 | AR3: 0 | AS3: 0 | AT3: =SUM(AO3:AS3) -> 0 | AV3: 0 | AW3: 0 | AX3: 0 | AY3: 0 | AZ3: 0 | BA3: =SUM(AV3:AZ3) -> 0 | BC3: 0 | BD3: 0 | BE3: 0 | BF3: 0 | BG3: 0 | BH3: =SUM(BC3:BG3) -> 0 | BJ3: 0 | BK3: 0 | BL3: 0 | BM3: 0 | BN3: 0 | BO3: =SUM(BJ3:BN3) -> 0 | BQ3: =BJ3+BC3 -> 0 | BR3: =BK3+BD3 -> 0 | BS3: =BL3+BE3 -> 0 | BT3: =BM3+BF3 -> 0 | BU3: =BN3+BG3 -> 0 | BV3: =SUM(BQ3:BU3) -> 0
F4: 730.99 | G4: 0 | H4: 0 | I4: 0 | J4: 0 | K4: =SUM(F4:J4) -> 730.99 | M4: 0 | N4: 289.02 | O4: 0 | P4: 964.32 | Q4: 0 | R4: =SUM(M4:Q4) -> 1253.34 | T4: 0 | U4: 0 | V4: 0 | W4: 0 | X4: 0 | Y4: =SUM(T4:X4) -> 0 | AA4: 0 | AB4: 0 | AC4: 0 | AD4: 0 | AE4: 0 | AF4: =SUM(AA4:AE4) -> 0 | AH4: 0 | AI4: 0 | AJ4: 0 | AK4: 0 | AL4: 0 | AM4: =SUM(AH4:AL4) -> 0 | AO4: 0 | AP4: 0 | AQ4: 0 | AR4: 0 | AS4: 0 | AT4: =SUM(AO4:AS4) -> 0 | AV4: 0 | AW4: 0 | AX4: 0 | AY4: 0 | AZ4: 0 | BA4: =SUM(AV4:AZ4) -> 0 | BC4: 0 | BD4: 0 | BE4: 0 | BF4: 0 | BG4: 0 | BH4: =SUM(BC4:BG4) -> 0 | BJ4: 0 | BK4: 0 | BL4: 0 | BM4: 0 | BN4: 0 | BO4: =SUM(BJ4:BN4) -> 0 | BQ4: =BJ4+BC4 -> 0 | BR4: =BK4+BD4 -> 0 | BS4: =BL4+BE4 -> 0 | BT4: =BM4+BF4 -> 0 | BU4: =BN4+BG4 -> 0 | BV4: =SUM(BQ4:BU4) -> 0
F5: 119.26 | G5: 115.69 | H5: 964.32 | I5: 0 | J5: 158.48 | K5: =SUM(F5:J5) -> 1357.75 | M5: 134.46 | N5: 0 | O5: 0 | P5: 0 | Q5: 2717.39 | R5: =SUM(M5:Q5) -> 2851.85 | T5: 0 | U5: 0 | V5: 0 | W5: 0 | X5: 0 | Y5: =SUM(T5:X5) -> 0 | AA5: 0 | AB5: 0 | AC5: 0 | AD5: 0 | AE5: 0 | AF5: =SUM(AA5:AE5) -> 0 | AH5: 0 | AI5: 0 | AJ5: 0 | AK5: 0 | AL5: 0 | AM5: =SUM(AH5:AL5) -> 0 | AO5: 0 | AP5: 0 | AQ5: 0 | AR5: 0 | AS5: 0 | AT5: =SUM(AO5:AS5) -> 0 | AV5: 0 | AW5: 0 | AX5: 0 | AY5: 0 | AZ5: 0 | BA5: =SUM(AV5:AZ5) -> 0 | BC5: 0 | BD5: 0 | BE5: 0 | BF5: 0 | BG5: 0 | BH5: =SUM(BC5:BG5) -> 0 | BJ5: 0 | BK5: 0 | BL5: 0 | BM5: 0 | BN5: 0 | BO5: =SUM(BJ5:BN5) -> 0 | BQ5: =BJ5+BC5 -> 0 | BR5: =BK5+BD5 -> 0 | BS5: =BL5+BE5 -> 0 | BT5: =BM5+BF5 -> 0 | BU5: =BN5+BG5 -> 0 | BV5: =SUM(BQ5:BU5) -> 0
F6: 0 | G6: 0 | H6: 0 | I6: 2717.39 | J6: 0 | K6: =SUM(F6:J6) -> 2717.39 | M6: 322.23 | N6: 0 | O6: 0 | P6: 158.48 | Q6: 0 | R6: =SUM(M6:Q6) -> 480.71 | T6: 0 | U6: 0 | V6: 0 | W6: 0 | X6: 0 | Y6: =SUM(T6:X6) -> 0 | AA6: 0 | AB6: 0 | AC6: 0 | AD6: 0 | AE6: 0 | AF6: =SUM(AA6:AE6) -> 0 | AH6: 0 | AI6: 0 | AJ6: 0 | AK6: 0 | AL6: 0 | AM6: =SUM(AH6:AL6) -> 0 | AO6: 0 | AP6: 0 | AQ6: 0 | AR6: 0 | AS6: 0 | AT6: =SUM(AO6:AS6) -> 0 | AV6: 0 | AW6: 0 | AX6: 0 | AY6: 0 | AZ6: 0 | BA6: =SUM(AV6:AZ6) -> 0 | BC6: 0 | BD6: 0 | BE6: 0 | BF6: 0 | BG6: 0 | BH6: =SUM(BC6:BG6) -> 0 | BJ6: 0 | BK6: 0 | BL6: 0 | BM6: 0 | BN6: 0 | BO6: =SUM(BJ6:BN6) -> 0 | BQ6: =BJ6+BC6 -> 0 | BR6: =BK6+BD6 -> 0 | BS6: =BL6+BE6 -> 0 | BT6: =BM6+BF6 -> 0 | BU6: =BN6+BG6 -> 0 | BV6: =SUM(BQ6:BU6) -> 0
F7: =SUM(F2:F6) -> 959.6 | G7: =SUM(G2:G6) -> 1844.24 | H7: =SUM(H2:H6) -> 1253.34 | I7: =SUM(I2:I6) -> 2851.85 | J7: =SUM(J2:J6) -> 480.71 | K7: =SUM(K2:K6) -> 7389.74 | M7: =SUM(M2:M6) -> 2185.24 | N7: =SUM(N2:N6) -> 398.37 | O7: =SUM(O2:O6) -> 730.99 | P7: =SUM(P2:P6) -> 1357.75 | Q7: =SUM(Q2:Q6) -> 2717.39 | R7: =SUM(R2:R6) -> 7389.74 | T7: =SUM(T2:T6) -> 0 | U7: =SUM(U2:U6) -> 0 | V7: =SUM(V2:V6) -> 0 | W7: =SUM(W2:W6) -> 0 | X7: =SUM(X2:X6) -> 0 | Y7: =SUM(Y2:Y6) -> 0 | AA7: =SUM(AA2:AA6) -> 0 | AB7: =SUM(AB2:AB6) -> 0 | AC7: =SUM(AC2:AC6) -> 0 | AD7: =SUM(AD2:AD6) -> 0 | AE7: =SUM(AE2:AE6) -> 0 | AF7: =SUM(AF2:AF6) -> 0 | AH7: =SUM(AH2:AH6) -> 0 | AI7: =SUM(AI2:AI6) -> 0 | AJ7: =SUM(AJ2:AJ6) -> 0 | AK7: =SUM(AK2:AK6) -> 0 | AL7: =SUM(AL2:AL6) -> 0 | AM7: =SUM(AM2:AM6) -> 0 | AO7: =SUM(AO2:AO6) -> 0 | AP7: =SUM(AP2:AP6) -> 0 | AQ7: =SUM(AQ2:AQ6) -> 0 | AR7: =SUM(AR2:AR6) -> 0 | AS7: =SUM(AS2:AS6) -> 0 | AT7: =SUM(AT2:AT6) -> 0 | AV7: =SUM(AV2:AV6) -> 0 | AW7: =SUM(AW2:AW6) -> 0 | AX7: =SUM(AX2:AX6) -> 0 | AY7: =SUM(AY2:AY6) -> 0 | AZ7: =SUM(AZ2:AZ6) -> 0 | BA7: =SUM(BA2:BA6) -> 0 | BC7: =SUM(BC2:BC6) -> 0 | BD7: =SUM(BD2:BD6) -> 0 | BE7: =SUM(BE2:BE6) -> 0 | BF7: =SUM(BF2:BF6) -> 0 | BG7: =SUM(BG2:BG6) -> 0 | BH7: =SUM(BH2:BH6) -> 0 | BJ7: =SUM(BJ2:BJ6) -> 0 | BK7: =SUM(BK2:BK6) -> 0 | BL7: =SUM(BL2:BL6) -> 0 | BM7: =SUM(BM2:BM6) -> 0 | BN7: =SUM(BN2:BN6) -> 0 | BO7: =SUM(BO2:BO6) -> 0 | BQ7: =SUM(BQ2:BQ6) -> 0 | BR7: =SUM(BR2:BR6) -> 0 | BS7: =SUM(BS2:BS6) -> 0 | BT7: =SUM(BT2:BT6) -> 0 | BU7: =SUM(BU2:BU6) -> 0 | BV7: =SUM(BV2:BV6) -> 0
A9: 2 | C9: 2 | D9: 1 | F9: 0 | G9: 1728.55 | H9: 0 | I9: 134.46 | J9: 322.23 | K9: =SUM(F9:J9) -> 2185.24 | M9: 0 | N9: 109.35 | O9: 730.99 | P9: 119.26 | Q9: 0 | R9: =SUM(M9:Q9) -> 959.6 | T9: 0 | U9: 0 | V9: 0 | W9: 0 | X9: 0 | Y9: =SUM(T9:X9) -> 0 | AA9: 0 | AB9: 0 | AC9: 0 | AD9: 0 | AE9: 0 | AF9: =SUM(AA9:AE9) -> 0 | AH9: 0 | AI9: 0 | AJ9: 0 | AK9: 0 | AL9: 0 | AM9: =SUM(AH9:AL9) -> 0 | AO9: 0 | AP9: 0 | AQ9: 0 | AR9: 0 | AS9: 0 | AT9: =SUM(AO9:AS9) -> 0 | AV9: 0 | AW9: 0 | AX9: 0 | AY9: 0 | AZ9: 0 | BA9: =SUM(AV9:AZ9) -> 0 | BC9: 0 | BD9: 0 | BE9: 0 | BF9: 0 | BG9: 0 | BH9: =SUM(BC9:BG9) -> 0 | BJ9: 0 | BK9: 0 | BL9: 0 | BM9: 0 | BN9: 0 | BO9: =SUM(BJ9:BN9) -> 0 | BQ9: =BJ9+BC9 -> 0 | BR9: =BK9+BD9 -> 0 | BS9: =BL9+BE9 -> 0 | BT9: =BM9+BF9 -> 0 | BU9: =BN9+BG9 -> 0 | BV9: =SUM(BQ9:BU9) -> 0
F10: 109.35 | G10: 0 | H10: 289.02 | I10: 0 | J10: 0 | K10: =SUM(F10:J10) -> 398.37 | M10: 1728.55 | N10: 0 | O10: 0 | P10: 115.69 | Q10: 0 | R10: =SUM(M10:Q10) -> 1844.24 | T10: 0 | U10: 0 | V10: 0 | W10: 0 | X10: 0 | Y10: =SUM(T10:X10) -> 0 | AA10: 0 | AB10: 0 | AC10: 0 | AD10: 0 | AE10: 0 | AF10: =SUM(AA10:AE10) -> 0 | AH10: 0 | AI10: 0 | AJ10: 0 | AK10: 0 | AL10: 0 | AM10: =SUM(AH10:AL10) -> 0 | AO10: 0 | AP10: 0 | AQ10: 0 | AR10: 0 | AS10: 0 | AT10: =SUM(AO10:AS10) -> 0 | AV10: 0 | AW10: 0 | AX10: 0 | AY10: 0 | AZ10: 0 | BA10: =SUM(AV10:AZ10) -> 0 | BC10: 1215.41 | BD10: 0 | BE10: 0 | BF10: 0 | BG10: 0 | BH10: =SUM(BC10:BG10) -> 1215.41 | BJ10: 0 | BK10: 0 | BL10: 0 | BM10: 0 | BN10: 0 | BO10: =SUM(BJ10:BN10) -> 0 | BQ10: =BJ10+BC10 -> 1215.41 | BR10: =BK10+BD10 -> 0 | BS10: =BL10+BE10 -> 0 | BT10: =BM10+BF10 -> 0 | BU10: =BN10+BG10 -> 0 | BV10: =SUM(BQ10:BU10) -> 1215.41
F11: 730.99 | G11: 0 | H11: 0 | I11: 0 | J11: 0 | K11: =SUM(F11:J11) -> 730.99 | M11: 0 | N11: 289.02 | O11: 0 | P11: 964.32 | Q11: 0 | R11: =SUM(M11:Q11) -> 1253.34 | T11: 0 | U11: 0 | V11: 0 | W11: 0 | X11: 0 | Y11: =SUM(T11:X11) -> 0 | AA11: 0 | AB11: 0 | AC11: 0 | AD11: 0 | AE11: 0 | AF11: =SUM(AA11:AE11) -> 0 | AH11: 0 | AI11: 0 | AJ11: 0 | AK11: 0 | AL11: 0 | AM11: =SUM(AH11:AL11) -> 0 | AO11: 0 | AP11: 0 | AQ11: 0 | AR11: 0 | AS11: 0 | AT11: =SUM(AO11:AS11) -> 0 | AV11: 0 | AW11: 0 | AX11: 0 | AY11: 0 | AZ11: 0 | BA11: =SUM(AV11:AZ11) -> 0 | BC11: 0 | BD11: 0 | BE11: 0 | BF11: 0 | BG11: 0 | BH11: =SUM(BC11:BG11) -> 0 | BJ11: 0 | BK11: 0 | BL11: 0 | BM11: 0 | BN11: 0 | BO11: =SUM(BJ11:BN11) -> 0 | BQ11: =BJ11+BC11 -> 0 | BR11: =BK11+BD11 -> 0 | BS11: =BL11+BE11 -> 0 | BT11: =BM11+BF11 -> 0 | BU11: =BN11+BG11 -> 0 | BV11: =SUM(BQ11:BU11) -> 0
F12: 119.26 | G12: 115.69 | H12: 964.32 | I12: 0 | J12: 158.48 | K12: =SUM(F12:J12) -> 1357.75 | M12: 134.46 | N12: 0 | O12: 0 | P12: 0 | Q12: 2717.39 | R12: =SUM(M12:Q12) -> 2851.85 | T12: 0 | U12: 0 | V12: 0 | W12: 0 | X12: 0 | Y12: =SUM(T12:X12) -> 0 | AA12: 0 | AB12: 0 | AC12: 0 | AD12: 0 | AE12: 0 | AF12: =SUM(AA12:AE12) -> 0 | AH12: 0 | AI12: 0 | AJ12: 0 | AK12: 0 | AL12: 0 | AM12: =SUM(AH12:AL12) -> 0 | AO12: 0 | AP12: 0 | AQ12: 0 | AR12: 0 | AS12: 0 | AT12: =SUM(AO12:AS12) -> 0 | AV12: 0 | AW12: 0 | AX12: 0 | AY12: 0 | AZ12: 0 | BA12: =SUM(AV12:AZ12) -> 0 | BC12: 94.5442 | BD12: 0 | BE12: 0 | BF12: 0 | BG12: 0 | BH12: =SUM(BC12:BG12) -> 94.5442 | BJ12: 0 | BK12: 0 | BL12: 0 | BM12: 0 | BN12: 0 | BO12: =SUM(BJ12:BN12) -> 0 | BQ12: =BJ12+BC12 -> 94.5442 | BR12: =BK12+BD12 -> 0 | BS12: =BL12+BE12 -> 0 | BT12: =BM12+BF12 -> 0 | BU12: =BN12+BG12 -> 0 | BV12: =SUM(BQ12:BU12) -> 94.5442
F13: 0 | G13: 0 | H13: 0 | I13: 2717.39 | J13: 0 | K13: =SUM(F13:J13) -> 2717.39 | M13: 322.23 | N13: 0 | O13: 0 | P13: 158.48 | Q13: 0 | R13: =SUM(M13:Q13) -> 480.71 | T13: 0 | U13: 0 | V13: 0 | W13: 0 | X13: 0 | Y13: =SUM(T13:X13) -> 0 | AA13: 0 | AB13: 0 | AC13: 0 | AD13: 0 | AE13: 0 | AF13: =SUM(AA13:AE13) -> 0 | AH13: 0 | AI13: 0 | AJ13: 0 | AK13: 0 | AL13: 0 | AM13: =SUM(AH13:AL13) -> 0 | AO13: 0 | AP13: 0 | AQ13: 0 | AR13: 0 | AS13: 0 | AT13: =SUM(AO13:AS13) -> 0 | AV13: 0 | AW13: 0 | AX13: 0 | AY13: 0 | AZ13: 0 | BA13: =SUM(AV13:AZ13) -> 0 | BC13: 226.573 | BD13: 0 | BE13: 0 | BF13: 0 | BG13: 0 | BH13: =SUM(BC13:BG13) -> 226.573 | BJ13: 0 | BK13: 0 | BL13: 0 | BM13: 0 | BN13: 0 | BO13: =SUM(BJ13:BN13) -> 0 | BQ13: =BJ13+BC13 -> 226.573 | BR13: =BK13+BD13 -> 0 | BS13: =BL13+BE13 -> 0 | BT13: =BM13+BF13 -> 0 | BU13: =BN13+BG13 -> 0 | BV13: =SUM(BQ13:BU13) -> 226.573
F14: =SUM(F9:F13) -> 959.6 | G14: =SUM(G9:G13) -> 1844.24 | H14: =SUM(H9:H13) -> 1253.34 | I14: =SUM(I9:I13) -> 2851.85 | J14: =SUM(J9:J13) -> 480.71 | K14: =SUM(K9:K13) -> 7389.74 | M14: =SUM(M9:M13) -> 2185.24 | N14: =SUM(N9:N13) -> 398.37 | O14: =SUM(O9:O13) -> 730.99 | P14: =SUM(P9:P13) -> 1357.75 | Q14: =SUM(Q9:Q13) -> 2717.39 | R14: =SUM(R9:R13) -> 7389.74 | T14: =SUM(T9:T13) -> 0 | U14: =SUM(U9:U13) -> 0 | V14: =SUM(V9:V13) -> 0 | W14: =SUM(W9:W13) -> 0 | X14: =SUM(X9:X13) -> 0 | Y14: =SUM(Y9:Y13) -> 0 | AA14: =SUM(AA9:AA13) -> 0 | AB14: =SUM(AB9:AB13) -> 0 | AC14: =SUM(AC9:AC13) -> 0 | AD14: =SUM(AD9:AD13) -> 0 | AE14: =SUM(AE9:AE13) -> 0 | AF14: =SUM(AF9:AF13) -> 0 | AH14: =SUM(AH9:AH13) -> 0 | AI14: =SUM(AI9:AI13) -> 0 | AJ14: =SUM(AJ9:AJ13) -> 0 | AK14: =SUM(AK9:AK13) -> 0 | AL14: =SUM(AL9:AL13) -> 0 | AM14: =SUM(AM9:AM13) -> 0 | AO14: =SUM(AO9:AO13) -> 0 | AP14: =SUM(AP9:AP13) -> 0 | AQ14: =SUM(AQ9:AQ13) -> 0 | AR14: =SUM(AR9:AR13) -> 0 | AS14: =SUM(AS9:AS13) -> 0 | AT14: =SUM(AT9:AT13) -> 0 | AV14: =SUM(AV9:AV13) -> 0 | AW14: =SUM(AW9:AW13) -> 0 | AX14: =SUM(AX9:AX13) -> 0 | AY14: =SUM(AY9:AY13) -> 0 | AZ14: =SUM(AZ9:AZ13) -> 0 | BA14: =SUM(BA9:BA13) -> 0 | BC14: =SUM(BC9:BC13) -> 1536.5272 | BD14: =SUM(BD9:BD13) -> 0 | BE14: =SUM(BE9:BE13) -> 0 | BF14: =SUM(BF9:BF13) -> 0 | BG14: =SUM(BG9:BG13) -> 0 | BH14: =SUM(BH9:BH13) -> 1536.5272 | BJ14: =SUM(BJ9:BJ13) -> 0 | BK14: =SUM(BK9:BK13) -> 0 | BL14: =SUM(BL9:BL13) -> 0 | BM14: =SUM(BM9:BM13) -> 0 | BN14: =SUM(BN9:BN13) -> 0 | BO14: =SUM(BO9:BO13) -> 0 | BQ14: =SUM(BQ9:BQ13) -> 1536.5272 | BR14: =SUM(BR9:BR13) -> 0 | BS14: =SUM(BS9:BS13) -> 0 | BT14: =SUM(BT9:BT13) -> 0 | BU14: =SUM(BU9:BU13) -> 0 | BV14: =SUM(BV9:BV13) -> 1536.5272
A16: 2 | C16: 2 | D16: 2 | F16: 0 | G16: 1728.55 | H16: 0 | I16: 134.46 | J16: 322.23 | K16: =SUM(F16:J16) -> 2185.24 | M16: 0 | N16: 109.35 | O16: 730.99 | P16: 119.26 | Q16: 0 | R16: =SUM(M16:Q16) -> 959.6 | T16: 0 | U16: 0 | V16: 0 | W16: 0 | X16: 0 | Y16: =SUM(T16:X16) -> 0 | AA16: 0 | AB16: 587.693 | AC16: 0 | AD16: 94.5442 | AE16: 226.573 | AF16: =SUM(AA16:AE16) -> 908.8102 | AH16: 0 | AI16: 0 | AJ16: 0 | AK16: 0 | AL16: 0 | AM16: =SUM(AH16:AL16) -> 0 | AO16: 0 | AP16: 0 | AQ16: 0 | AR16: 0 | AS16: 0 | AT16: =SUM(AO16:AS16) -> 0 | AV16: 0 | AW16: 0 | AX16: 0 | AY16: 0 | AZ16: 0 | BA16: =SUM(AV16:AZ16) -> 0 | BC16: 0 | BD16: 0 | BE16: 0 | BF16: 0 | BG16: 0 | BH16: =SUM(BC16:BG16) -> 0 | BJ16: 0 | BK16: 0 | BL16: 0 | BM16: 0 | BN16: 0 | BO16: =SUM(BJ16:BN16) -> 0 | BQ16: =BJ16+BC16 -> 0 | BR16: =BK16+BD16 -> 0 | BS16: =BL16+BE16 -> 0 | BT16: =BM16+BF16 -> 0 | BU16: =BN16+BG16 -> 0 | BV16: =SUM(BQ16:BU16) -> 0
F17: 109.35 | G17: 0 | H17: 289.02 | I17: 0 | J17: 0 | K17: =SUM(F17:J17) -> 398.37 | M17: 1728.55 | N17: 0 | O17: 0 | P17: 115.69 | Q17: 0 | R17: =SUM(M17:Q17) -> 1844.24 | T17: 0 | U17: 0 | V17: 0 | W17: 0 | X17: 0 | Y17: =SUM(T17:X17) -> 0 | AA17: 0 | AB17: 0 | AC17: 0 | AD17: 0 | AE17: 0 | AF17: =SUM(AA17:AE17) -> 0 | AH17: 0 | AI17: 0 | AJ17: 0 | AK17: 0 | AL17: 0 | AM17: =SUM(AH17:AL17) -> 0 | AO17: 587.693 | AP17: 0 | AQ17: 0 | AR17: 0 | AS17: 0 | AT17: =SUM(AO17:AS17) -> 587.693 | AV17: 0 | AW17: 0 | AX17: 0 | AY17: 0 | AZ17: 0 | BA17: =SUM(AV17:AZ17) -> 0 | BC17: 1215.41 | BD17: 0 | BE17: 0 | BF17: 0 | BG17: 0 | BH17: =SUM(BC17:BG17) -> 1215.41 | BJ17: 0 | BK17: 0 | BL17: 0 | BM17: 0 | BN17: 0 | BO17: =SUM(BJ17:BN17) -> 0 | BQ17: =BJ17+BC17 -> 1215.41 | BR17: =BK17+BD17 -> 0 | BS17: =BL17+BE17 -> 0 | BT17: =BM17+BF17 -> 0 | BU17: =BN17+BG17 -> 0 | BV17: =SUM(BQ17:BU17) -> 1215.41
F18: 730.99 | G18: 0 | H18: 0 | I18: 0 | J18: 0 | K18: =SUM(F18:J18) -> 730.99 | M18: 0 | N18: 289.02 | O18: 0 | P18: 964.32 | Q18: 0 | R18: =SUM(M18:Q18) -> 1253.34 | T18: 0 | U18: 0 | V18: 0 | W18: 0 | X18: 0 | Y18: =SUM(T18:X18) -> 0 | AA18: 0 | AB18: 0 | AC18: 0 | AD18: 0 | AE18: 0 | AF18: =SUM(AA18:AE18) -> 0 | AH18: 0 | AI18: 0 | AJ18: 0 | AK18: 0 | AL18: 0 | AM18: =SUM(AH18:AL18) -> 0 | AO18: 0 | AP18: 0 | AQ18: 0 | AR18: 0 | AS18: 0 | AT18: =SUM(AO18:AS18) -> 0 | AV18: 0 | AW18: 0 | AX18: 0 | AY18: 0 | AZ18: 0 | BA18: =SUM(AV18:AZ18) -> 0 | BC18: 0 | BD18: 0 | BE18: 0 | BF18: 0 | BG18: 0 | BH18: =SUM(BC18:BG18) -> 0 | BJ18: 0 | BK18: 0 | BL18: 0 | BM18: 0 | BN18: 0 | BO18: =SUM(BJ18:BN18) -> 0 | BQ18: =BJ18+BC18 -> 0 | BR18: =BK18+BD18 -> 0 | BS18: =BL18+BE18 -> 0 | BT18: =BM18+BF18 -> 0 | BU18: =BN18+BG18 -> 0 | BV18: =SUM(BQ18:BU18) -> 0
F19: 119.26 | G19: 115.69 | H19: 964.32 | I19: 0 | J19: 158.48 | K19: =SUM(F19:J19) -> 1357.75 | M19: 134.46 | N19: 0 | O19: 0 | P19: 0 | Q19: 2717.39 | R19: =SUM(M19:Q19) -> 2851.85 | T19: 0 | U19: 0 | V19: 0 | W19: 0 | X19: 0 | Y19: =SUM(T19:X19) -> 0 | AA19: 0 | AB19: 0 | AC19: 0 | AD19: 0 | AE19: 0 | AF19: =SUM(AA19:AE19) -> 0 | AH19: 0 | AI19: 0 | AJ19: 0 | AK19: 0 | AL19: 0 | AM19: =SUM(AH19:AL19) -> 0 | AO19: 94.5442 | AP19: 0 | AQ19: 0 | AR19: 0 | AS19: 0 | AT19: =SUM(AO19:AS19) -> 94.5442 | AV19: 0 | AW19: 0 | AX19: 0 | AY19: 0 | AZ19: 0 | BA19: =SUM(AV19:AZ19) -> 0 | BC19: 94.5442 | BD19: 0 | BE19: 0 | BF19: 0 | BG19: 0 | BH19: =SUM(BC19:BG19) -> 94.5442 | BJ19: 0 | BK19: 0 | BL19: 0 | BM19: 0 | BN19: 0 | BO19: =SUM(BJ19:BN19) -> 0 | BQ19: =BJ19+BC19 -> 94.5442 | BR19: =BK19+BD19 -> 0 | BS19: =BL19+BE19 -> 0 | BT19: =BM19+BF19 -> 0 | BU19: =BN19+BG19 -> 0 | BV19: =SUM(BQ19:BU19) -> 94.5442
F20: 0 | G20: 0 | H20: 0 | I20: 2717.39 | J20: 0 | K20: =SUM(F20:J20) -> 2717.39 | M20: 322.23 | N20: 0 | O20: 0 | P20: 158.48 | Q20: 0 | R20: =SUM(M20:Q20) -> 480.71 | T20: 0 | U20: 0 | V20: 0 | W20: 0 | X20: 0 | Y20: =SUM(T20:X20) -> 0 | AA20: 0 | AB20: 0 | AC20: 0 | AD20: 0 | AE20: 0 | AF20: =SUM(AA20:AE20) -> 0 | AH20: 0 | AI20: 0 | AJ20: 0 | AK20: 0 | AL20: 0 | AM20: =SUM(AH20:AL20) -> 0 | AO20: 226.573 | AP20: 0 | AQ20: 0 | AR20: 0 | AS20: 0 | AT20: =SUM(AO20:AS20) -> 226.573 | AV20: 0 | AW20: 0 | AX20: 0 | AY20: 0 | AZ20: 0 | BA20: =SUM(AV20:AZ20) -> 0 | BC20: 226.573 | BD20: 0 | BE20: 0 | BF20: 0 | BG20: 0 | BH20: =SUM(BC20:BG20) -> 226.573 | BJ20: 0 | BK20: 0 | BL20: 0 | BM20: 0 | BN20: 0 | BO20: =SUM(BJ20:BN20) -> 0 | BQ20: =BJ20+BC20 -> 226.573 | BR20: =BK20+BD20 -> 0 | BS20: =BL20+BE20 -> 0 | BT20: =BM20+BF20 -> 0 | BU20: =BN20+BG20 -> 0 | BV20: =SUM(BQ20:BU20) -> 226.573
F21: =SUM(F16:F20) -> 959.6 | G21: =SUM(G16:G20) -> 1844.24 | H21: =SUM(H16:H20) -> 1253.34 | I21: =SUM(I16:I20) -> 2851.85 | J21: =SUM(J16:J20) -> 480.71 | K21: =SUM(K16:K20) -> 7389.74 | M21: =SUM(M16:M20) -> 2185.24 | N21: =SUM(N16:N20) -> 398.37 | O21: =SUM(O16:O20) -> 730.99 | P21: =SUM(P16:P20) -> 1357.75 | Q21: =SUM(Q16:Q20) -> 2717.39 | R21: =SUM(R16:R20) -> 7389.74 | T21: =SUM(T16:T20) -> 0 | U21: =SUM(U16:U20) -> 0 | V21: =SUM(V16:V20) -> 0 | W21: =SUM(W16:W20) -> 0 | X21: =SUM(X16:X20) -> 0 | Y21: =SUM(Y16:Y20) -> 0 | AA21: =SUM(AA16:AA20) -> 0 | AB21: =SUM(AB16:AB20) -> 587.693 | AC21: =SUM(AC16:AC20) -> 0 | AD21: =SUM(AD16:AD20) -> 94.5442 | AE21: =SUM(AE16:AE20) -> 226.573 | AF21: =SUM(AF16:AF20) -> 908.8102 | AH21: =SUM(AH16:AH20) -> 0 | AI21: =SUM(AI16:AI20) -> 0 | AJ21: =SUM(AJ16:AJ20) -> 0 | AK21: =SUM(AK16:AK20) -> 0 | AL21: =SUM(AL16:AL20) -> 0 | AM21: =SUM(AM16:AM20) -> 0 | AO21: =SUM(AO16:AO20) -> 908.8102 | AP21: =SUM(AP16:AP20) -> 0 | AQ21: =SUM(AQ16:AQ20) -> 0 | AR21: =SUM(AR16:AR20) -> 0 | AS21: =SUM(AS16:AS20) -> 0 | AT21: =SUM(AT16:AT20) -> 908.8102 | AV21: =SUM(AV16:AV20) -> 0 | AW21: =SUM(AW16:AW20) -> 0 | AX21: =SUM(AX16:AX20) -> 0 | AY21: =SUM(AY16:AY20) -> 0 | AZ21: =SUM(AZ16:AZ20) -> 0 | BA21: =SUM(BA16:BA20) -> 0 | BC21: =SUM(BC16:BC20) -> 1536.5272 | BD21: =SUM(BD16:BD20) -> 0 | BE21: =SUM(BE16:BE20) -> 0 | BF21: =SUM(BF16:BF20) -> 0 | BG21: =SUM(BG16:BG20) -> 0 | BH21: =SUM(BH16:BH20) -> 1536.5272 | BJ21: =SUM(BJ16:BJ20) -> 0 | BK21: =SUM(BK16:BK20) -> 0 | BL21: =SUM(BL16:BL20) -> 0 | BM21: =SUM(BM16:BM20) -> 0 | BN21: =SUM(BN16:BN20) -> 0 | BO21: =SUM(BO16:BO20) -> 0 | BQ21: =SUM(BQ16:BQ20) -> 1536.5272 | BR21: =SUM(BR16:BR20) -> 0 | BS21: =SUM(BS16:BS20) -> 0 | BT21: =SUM(BT16:BT20) -> 0 | BU21: =SUM(BU16:BU20) -> 0 | BV21: =SUM(BV16:BV20) -> 1536.5272
A23: 2 | C23: 2 | D23: 3 | F23: 0 | G23: 1140.86 | H23: 0 | I23: 39.9158 | J23: 95.6571 | K23: =SUM(F23:J23) -> 1276.4329 | M23: 0 | N23: 109.35 | O23: 730.99 | P23: 119.26 | Q23: 0 | R23: =SUM(M23:Q23) -> 959.6 | T23: 0 | U23: 0 | V23: 0 | W23: 0 | X23: 0 | Y23: =SUM(T23:X23) -> 0 | AA23: 0 | AB23: 0 | AC23: 0 | AD23: 0 | AE23: 0 | AF23: =SUM(AA23:AE23) -> 0 | AH23: 0 | AI23: 0 | AJ23: 0 | AK23: 0 | AL23: 0 | AM23: =SUM(AH23:AL23) -> 0 | AO23: 0 | AP23: 0 | AQ23: 0 | AR23: 0 | AS23: 0 | AT23: =SUM(AO23:AS23) -> 0 | AV23: 0 | AW23: 0 | AX23: 0 | AY23: 0 | AZ23: 0 | BA23: =SUM(AV23:AZ23) -> 0 | BC23: 0 | BD23: 0 | BE23: 0 | BF23: 0 | BG23: 0 | BH23: =SUM(BC23:BG23) -> 0 | BJ23: 0 | BK23: 0 | BL23: 0 | BM23: 0 | BN23: 0 | BO23: =SUM(BJ23:BN23) -> 0 | BQ23: =BJ23+BC23 -> 0 | BR23: =BK23+BD23 -> 0 | BS23: =BL23+BE23 -> 0 | BT23: =BM23+BF23 -> 0 | BU23: =BN23+BG23 -> 0 | BV23: =SUM(BQ23:BU23) -> 0
F24: 109.35 | G24: 0 | H24: 289.02 | I24: 0 | J24: 0 | K24: =SUM(F24:J24) -> 398.37 | M24: 1140.86 | N24: 0 | O24: 0 | P24: 115.69 | Q24: 0 | R24: =SUM(M24:Q24) -> 1256.55 | T24: 0 | U24: 0 | V24: 0 | W24: 0 | X24: 0 | Y24: =SUM(T24:X24) -> 0 | AA24: 587.693 | AB24: 0 | AC24: 0 | AD24: 0 | AE24: 0 | AF24: =SUM(AA24:AE24) -> 587.693 | AH24: 0 | AI24: 0 | AJ24: 0 | AK24: 0 | AL24: 0 | AM24: =SUM(AH24:AL24) -> 0 | AO24: 587.693 | AP24: 0 | AQ24: 0 | AR24: 0 | AS24: 0 | AT24: =SUM(AO24:AS24) -> 587.693 | AV24: 0 | AW24: 0 | AX24: 0 | AY24: 0 | AZ24: 0 | BA24: =SUM(AV24:AZ24) -> 0 | BC24: 627.72 | BD24: 0 | BE24: 0 | BF24: 0 | BG24: 0 | BH24: =SUM(BC24:BG24) -> 627.72 | BJ24: 0 | BK24: 0 | BL24: 0 | BM24: 0 | BN24: 0 | BO24: =SUM(BJ24:BN24) -> 0 | BQ24: =BJ24+BC24 -> 627.72 | BR24: =BK24+BD24 -> 0 | BS24: =BL24+BE24 -> 0 | BT24: =BM24+BF24 -> 0 | BU24: =BN24+BG24 -> 0 | BV24: =SUM(BQ24:BU24) -> 627.72
F25: 730.99 | G25: 0 | H25: 0 | I25: 0 | J25: 0 | K25: =SUM(F25:J25) -> 730.99 | M25: 0 | N25: 289.02 | O25: 0 | P25: 964.32 | Q25: 0 | R25: =SUM(M25:Q25) -> 1253.34 | T25: 0 | U25: 0 | V25: 0 | W25: 0 | X25: 0 | Y25: =SUM(T25:X25) -> 0 | AA25: 0 | AB25: 0 | AC25: 0 | AD25: 0 | AE25: 0 | AF25: =SUM(AA25:AE25) -> 0 | AH25: 0 | AI25: 0 | AJ25: 0 | AK25: 0 | AL25: 0 | AM25: =SUM(AH25:AL25) -> 0 | AO25: 0 | AP25: 0 | AQ25: 0 | AR25: 0 | AS25: 0 | AT25: =SUM(AO25:AS25) -> 0 | AV25: 0 | AW25: 0 | AX25: 0 | AY25: 0 | AZ25: 0 | BA25: =SUM(AV25:AZ25) -> 0 | BC25: 0 | BD25: 0 | BE25: 0 | BF25: 0 | BG25: 0 | BH25: =SUM(BC25:BG25) -> 0 | BJ25: 0 | BK25: 0 | BL25: 0 | BM25: 0 | BN25: 0 | BO25: =SUM(BJ25:BN25) -> 0 | BQ25: =BJ25+BC25 -> 0 | BR25: =BK25+BD25 -> 0 | BS25: =BL25+BE25 -> 0 | BT25: =BM25+BF25 -> 0 | BU25: =BN25+BG25 -> 0 | BV25: =SUM(BQ25:BU25) -> 0
F26: 119.26 | G26: 115.69 | H26: 964.32 | I26: 0 | J26: 158.48 | K26: =SUM(F26:J26) -> 1357.75 | M26: 39.9158 | N26: 0 | O26: 0 | P26: 0 | Q26: 2717.39 | R26: =SUM(M26:Q26) -> 2757.3058 | T26: 0 | U26: 0 | V26: 0 | W26: 0 | X26: 0 | Y26: =SUM(T26:X26) -> 0 | AA26: 94.5442 | AB26: 0 | AC26: 0 | AD26: 0 | AE26: 0 | AF26: =SUM(AA26:AE26) -> 94.5442 | AH26: 0 | AI26: 0 | AJ26: 0 | AK26: 0 | AL26: 0 | AM26: =SUM(AH26:AL26) -> 0 | AO26: 94.5442 | AP26: 0 | AQ26: 0 | AR26: 0 | AS26: 0 | AT26: =SUM(AO26:AS26) -> 94.5442 | AV26: 0 | AW26: 0 | AX26: 0 | AY26: 0 | AZ26: 0 | BA26: =SUM(AV26:AZ26) -> 0 | BC26: 0 | BD26: 0 | BE26: 0 | BF26: 0 | BG26: 0 | BH26: =SUM(BC26:BG26) -> 0 | BJ26: 0 | BK26: 0 | BL26: 0 | BM26: 0 | BN26: 0 | BO26: =SUM(BJ26:BN26) -> 0 | BQ26: =BJ26+BC26 -> 0 | BR26: =BK26+BD26 -> 0 | BS26: =BL26+BE26 -> 0 | BT26: =BM26+BF26 -> 0 | BU26: =BN26+BG26 -> 0 | BV26: =SUM(BQ26:BU26) -> 0
F27: 0 | G27: 0 | H27: 0 | I27: 2717.39 | J27: 0 | K27: =SUM(F27:J27) -> 2717.39 | M27: 95.6571 | N27: 0 | O27: 0 | P27: 158.48 | Q27: 0 | R27: =SUM(M27:Q27) -> 254.1371 | T27: 0 | U27: 0 | V27: 0 | W27: 0 | X27: 0 | Y27: =SUM(T27:X27) -> 0 | AA27: 226.573 | AB27: 0 | AC27: 0 | AD27: 0 | AE27: 0 | AF27: =SUM(AA27:AE27) -> 226.573 | AH27: 0 | AI27: 0 | AJ27: 0 | AK27: 0 | AL27: 0 | AM27: =SUM(AH27:AL27) -> 0 | AO27: 226.573 | AP27: 0 | AQ27: 0 | AR27: 0 | AS27: 0 | AT27: =SUM(AO27:AS27) -> 226.573 | AV27: 0 | AW27: 0 | AX27: 0 | AY27: 0 | AZ27: 0 | BA27: =SUM(AV27:AZ27) -> 0 | BC27: 0 | BD27: 0 | BE27: 0 | BF27: 0 | BG27: 0 | BH27: =SUM(BC27:BG27) -> 0 | BJ27: 0 | BK27: 0 | BL27: 0 | BM27: 0 | BN27: 0 | BO27: =SUM(BJ27:BN27) -> 0 | BQ27: =BJ27+BC27 -> 0 | BR27: =BK27+BD27 -> 0 | BS27: =BL27+BE27 -> 0 | BT27: =BM27+BF27 -> 0 | BU27: =BN27+BG27 -> 0 | BV27: =SUM(BQ27:BU27) -> 0
F28: =SUM(F23:F27) -> 959.6 | G28: =SUM(G23:G27) -> 1256.55 | H28: =SUM(H23:H27) -> 1253.34 | I28: =SUM(I23:I27) -> 2757.3058 | J28: =SUM(J23:J27) -> 254.1371 | K28: =SUM(K23:K27) -> 6480.9329 | M28: =SUM(M23:M27) -> 1276.4329 | N28: =SUM(N23:N27) -> 398.37 | O28: =SUM(O23:O27) -> 730.99 | P28: =SUM(P23:P27) -> 1357.75 | Q28: =SUM(Q23:Q27) -> 2717.39 | R28: =SUM(R23:R27) -> 6480.9329 | T28: =SUM(T23:T27) -> 0 | U28: =SUM(U23:U27) -> 0 | V28: =SUM(V23:V27) -> 0 | W28: =SUM(W23:W27) -> 0 | X28: =SUM(X23:X27) -> 0 | Y28: =SUM(Y23:Y27) -> 0 | AA28: =SUM(AA23:AA27) -> 908.8102 | AB28: =SUM(AB23:AB27) -> 0 | AC28: =SUM(AC23:AC27) -> 0 | AD28: =SUM(AD23:AD27) -> 0 | AE28: =SUM(AE23:AE27) -> 0 | AF28: =SUM(AF23:AF27) -> 908.8102 | AH28: =SUM(AH23:AH27) -> 0 | AI28: =SUM(AI23:AI27) -> 0 | AJ28: =SUM(AJ23:AJ27) -> 0 | AK28: =SUM(AK23:AK27) -> 0 | AL28: =SUM(AL23:AL27) -> 0 | AM28: =SUM(AM23:AM27) -> 0 | AO28: =SUM(AO23:AO27) -> 908.8102 | AP28: =SUM(AP23:AP27) -> 0 | AQ28: =SUM(AQ23:AQ27) -> 0 | AR28: =SUM(AR23:AR27) -> 0 | AS28: =SUM(AS23:AS27) -> 0 | AT28: =SUM(AT23:AT27) -> 908.8102 | AV28: =SUM(AV23:AV27) -> 0 | AW28: =SUM(AW23:AW27) -> 0 | AX28: =SUM(AX23:AX27) -> 0 | AY28: =SUM(AY23:AY27) -> 0 | AZ28: =SUM(AZ23:AZ27) -> 0 | BA28: =SUM(BA23:BA27) -> 0 | BC28: =SUM(BC23:BC27) -> 627.72 | BD28: =SUM(BD23:BD27) -> 0 | BE28: =SUM(BE23:BE27) -> 0 | BF28: =SUM(BF23:BF27) -> 0 | BG28: =SUM(BG23:BG27) -> 0 | BH28: =SUM(BH23:BH27) -> 627.72 | BJ28: =SUM(BJ23:BJ27) -> 0 | BK28: =SUM(BK23:BK27) -> 0 | BL28: =SUM(BL23:BL27) -> 0 | BM28: =SUM(BM23:BM27) -> 0 | BN28: =SUM(BN23:BN27) -> 0 | BO28: =SUM(BO23:BO27) -> 0 | BQ28: =SUM(BQ23:BQ27) -> 627.72 | BR28: =SUM(BR23:BR27) -> 0 | BS28: =SUM(BS23:BS27) -> 0 | BT28: =SUM(BT23:BT27) -> 0 | BU28: =SUM(BU23:BU27) -> 0 | BV28: =SUM(BV23:BV27) -> 627.72
A30: 2 | C30: 3 | D30: 1 | F30: 0 | G30: 1140.86 | H30: 0 | I30: 39.9158 | J30: 95.6571 | K30: =SUM(F30:J30) -> 1276.4329 | M30: 0 | N30: 109.35 | O30: 730.99 | P30: 119.26 | Q30: 0 | R30: =SUM(M30:Q30) -> 959.6 | T30: 0 | U30: 0 | V30: 0 | W30: 0 | X30: 0 | Y30: =SUM(T30:X30) -> 0 | AA30: 0 | AB30: 0 | AC30: 0 | AD30: 0 | AE30: 0 | AF30: =SUM(AA30:AE30) -> 0 | AH30: 0 | AI30: 0 | AJ30: 0 | AK30: 0 | AL30: 0 | AM30: =SUM(AH30:AL30) -> 0 | AO30: 0 | AP30: 0 | AQ30: 0 | AR30: 0 | AS30: 0 | AT30: =SUM(AO30:AS30) -> 0 | AV30: 0 | AW30: 0 | AX30: 0 | AY30: 0 | AZ30: 0 | BA30: =SUM(AV30:AZ30) -> 0 | BC30: 0 | BD30: 14.5995 | BE30: 0 | BF30: 0 | BG30: 0 | BH30: =SUM(BC30:BG30) -> 14.5995 | BJ30: 0 | BK30: 0 | BL30: 0 | BM30: 0 | BN30: 0 | BO30: =SUM(BJ30:BN30) -> 0 | BQ30: =BJ30+BC30 -> 0 | BR30: =BK30+BD30 -> 14.5995 | BS30: =BL30+BE30 -> 0 | BT30: =BM30+BF30 -> 0 | BU30: =BN30+BG30 -> 0 | BV30: =SUM(BQ30:BU30) -> 14.5995
F31: 109.35 | G31: 0 | H31: 289.02 | I31: 0 | J31: 0 | K31: =SUM(F31:J31) -> 398.37 | M31: 1140.86 | N31: 0 | O31: 0 | P31: 115.69 | Q31: 0 | R31: =SUM(M31:Q31) -> 1256.55 | T31: 0 | U31: 0 | V31: 0 | W31: 0 | X31: 0 | Y31: =SUM(T31:X31) -> 0 | AA31: 0 | AB31: 0 | AC31: 0 | AD31: 0 | AE31: 0 | AF31: =SUM(AA31:AE31) -> 0 | AH31: 0 | AI31: 0 | AJ31: 0 | AK31: 0 | AL31: 0 | AM31: =SUM(AH31:AL31) -> 0 | AO31: 0 | AP31: 0 | AQ31: 0 | AR31: 0 | AS31: 0 | AT31: =SUM(AO31:AS31) -> 0 | AV31: 0 | AW31: 0 | AX31: 0 | AY31: 0 | AZ31: 0 | BA31: =SUM(AV31:AZ31) -> 0 | BC31: 406.706 | BD31: 0 | BE31: 0 | BF31: 0 | BG31: 0 | BH31: =SUM(BC31:BG31) -> 406.706 | BJ31: 0 | BK31: 0 | BL31: 0 | BM31: 0 | BN31: 0 | BO31: =SUM(BJ31:BN31) -> 0 | BQ31: =BJ31+BC31 -> 406.706 | BR31: =BK31+BD31 -> 0 | BS31: =BL31+BE31 -> 0 | BT31: =BM31+BF31 -> 0 | BU31: =BN31+BG31 -> 0 | BV31: =SUM(BQ31:BU31) -> 406.706
F32: 730.99 | G32: 0 | H32: 0 | I32: 0 | J32: 0 | K32: =SUM(F32:J32) -> 730.99 | M32: 0 | N32: 289.02 | O32: 0 | P32: 964.32 | Q32: 0 | R32: =SUM(M32:Q32) -> 1253.34 | T32: 0 | U32: 0 | V32: 0 | W32: 0 | X32: 0 | Y32: =SUM(T32:X32) -> 0 | AA32: 0 | AB32: 0 | AC32: 0 | AD32: 0 | AE32: 0 | AF32: =SUM(AA32:AE32) -> 0 | AH32: 0 | AI32: 0 | AJ32: 0 | AK32: 0 | AL32: 0 | AM32: =SUM(AH32:AL32) -> 0 | AO32: 0 | AP32: 0 | AQ32: 0 | AR32: 0 | AS32: 0 | AT32: =SUM(AO32:AS32) -> 0 | AV32: 0 | AW32: 0 | AX32: 0 | AY32: 0 | AZ32: 0 | BA32: =SUM(AV32:AZ32) -> 0 | BC32: 0 | BD32: 38.5876 | BE32: 0 | BF32: 0 | BG32: 0 | BH32: =SUM(BC32:BG32) -> 38.5876 | BJ32: 0 | BK32: 0 | BL32: 0 | BM32: 0 | BN32: 0 | BO32: =SUM(BJ32:BN32) -> 0 | BQ32: =BJ32+BC32 -> 0 | BR32: =BK32+BD32 -> 38.5876 | BS32: =BL32+BE32 -> 0 | BT32: =BM32+BF32 -> 0 | BU32: =BN32+BG32 -> 0 | BV32: =SUM(BQ32:BU32) -> 38.5876
F33: 119.26 | G33: 115.69 | H33: 964.32 | I33: 0 | J33: 158.48 | K33: =SUM(F33:J33) -> 1357.75 | M33: 39.9158 | N33: 0 | O33: 0 | P33: 0 | Q33: 2717.39 | R33: =SUM(M33:Q33) -> 2757.3058 | T33: 0 | U33: 0 | V33: 0 | W33: 0 | X33: 0 | Y33: =SUM(T33:X33) -> 0 | AA33: 0 | AB33: 0 | AC33: 0 | AD33: 0 | AE33: 0 | AF33: =SUM(AA33:AE33) -> 0 | AH33: 0 | AI33: 0 | AJ33: 0 | AK33: 0 | AL33: 0 | AM33: =SUM(AH33:AL33) -> 0 | AO33: 0 | AP33: 0 | AQ33: 0 | AR33: 0 | AS33: 0 | AT33: =SUM(AO33:AS33) -> 0 | AV33: 0 | AW33: 0 | AX33: 0 | AY33: 0 | AZ33: 0 | BA33: =SUM(AV33:AZ33) -> 0 | BC33: 14.2298 | BD33: 0 | BE33: 0 | BF33: 0 | BG33: 0 | BH33: =SUM(BC33:BG33) -> 14.2298 | BJ33: 0 | BK33: 0 | BL33: 0 | BM33: 0 | BN33: 0 | BO33: =SUM(BJ33:BN33) -> 0 | BQ33: =BJ33+BC33 -> 14.2298 | BR33: =BK33+BD33 -> 0 | BS33: =BL33+BE33 -> 0 | BT33: =BM33+BF33 -> 0 | BU33: =BN33+BG33 -> 0 | BV33: =SUM(BQ33:BU33) -> 14.2298
F34: 0 | G34: 0 | H34: 0 | I34: 2717.39 | J34: 0 | K34: =SUM(F34:J34) -> 2717.39 | M34: 95.6571 | N34: 0 | O34: 0 | P34: 158.48 | Q34: 0 | R34: =SUM(M34:Q34) -> 254.1371 | T34: 0 | U34: 0 | V34: 0 | W34: 0 | X34: 0 | Y34: =SUM(T34:X34) -> 0 | AA34: 0 | AB34: 0 | AC34: 0 | AD34: 0 | AE34: 0 | AF34: =SUM(AA34:AE34) -> 0 | AH34: 0 | AI34: 0 | AJ34: 0 | AK34: 0 | AL34: 0 | AM34: =SUM(AH34:AL34) -> 0 | AO34: 0 | AP34: 0 | AQ34: 0 | AR34: 0 | AS34: 0 | AT34: =SUM(AO34:AS34) -> 0 | AV34: 0 | AW34: 0 | AX34: 0 | AY34: 0 | AZ34: 0 | BA34: =SUM(AV34:AZ34) -> 0 | BC34: 34.101 | BD34: 0 | BE34: 0 | BF34: 0 | BG34: 0 | BH34: =SUM(BC34:BG34) -> 34.101 | BJ34: 0 | BK34: 0 | BL34: 0 | BM34: 0 | BN34: 0 | BO34: =SUM(BJ34:BN34) -> 0 | BQ34: =BJ34+BC34 -> 34.101 | BR34: =BK34+BD34 -> 0 | BS34: =BL34+BE34 -> 0 | BT34: =BM34+BF34 -> 0 | BU34: =BN34+BG34 -> 0 | BV34: =SUM(BQ34:BU34) -> 34.101
F35: =SUM(F30:F34) -> 959.6 | G35: =SUM(G30:G34) -> 1256.55 | H35: =SUM(H30:H34) -> 1253.34 | I35: =SUM(I30:I34) -> 2757.3058 | J35: =SUM(J30:J34) -> 254.1371 | K35: =SUM(K30:K34) -> 6480.9329 | M35: =SUM(M30:M34) -> 1276.4329 | N35: =SUM(N30:N34) -> 398.37 | O35: =SUM(O30:O34) -> 730.99 | P35: =SUM(P30:P34) -> 1357.75 | Q35: =SUM(Q30:Q34) -> 2717.39 | R35: =SUM(R30:R34) -> 6480.9329 | T35: =SUM(T30:T34) -> 0 | U35: =SUM(U30:U34) -> 0 | V35: =SUM(V30:V34) -> 0 | W35: =SUM(W30:W34) -> 0 | X35: =SUM(X30:X34) -> 0 | Y35: =SUM(Y30:Y34) -> 0 | AA35: =SUM(AA30:AA34) -> 0 | AB35: =SUM(AB30:AB34) -> 0 | AC35: =SUM(AC30:AC34) -> 0 | AD35: =SUM(AD30:AD34) -> 0 | AE35: =SUM(AE30:AE34) -> 0 | AF35: =SUM(AF30:AF34) -> 0 | AH35: =SUM(AH30:AH34) -> 0 | AI35: =SUM(AI30:AI34) -> 0 | AJ35: =SUM(AJ30:AJ34) -> 0 | AK35: =SUM(AK30:AK34) -> 0 | AL35: =SUM(AL30:AL34) -> 0 | AM35: =SUM(AM30:AM34) -> 0 | AO35: =SUM(AO30:AO34) -> 0 | AP35: =SUM(AP30:AP34) -> 0 | AQ35: =SUM(AQ30:AQ34) -> 0 | AR35: =SUM(AR30:AR34) -> 0 | AS35: =SUM(AS30:AS34) -> 0 | AT35: =SUM(AT30:AT34) -> 0 | AV35: =SUM(AV30:AV34) -> 0 | AW35: =SUM(AW30:AW34) -> 0 | AX35: =SUM(AX30:AX34) -> 0 | AY35: =SUM(AY30:AY34) -> 0 | AZ35: =SUM(AZ30:AZ34) -> 0 | BA35: =SUM(BA30:BA34) -> 0 | BC35: =SUM(BC30:BC34) -> 455.0368 | BD35: =SUM(BD30:BD34) -> 53.1871 | BE35: =SUM(BE30:BE34) -> 0 | BF35: =SUM(BF30:BF34) -> 0 | BG35: =SUM(BG30:BG34) -> 0 | BH35: =SUM(BH30:BH34) -> 508.2239 | BJ35: =SUM(BJ30:BJ34) -> 0 | BK35: =SUM(BK30:BK34) -> 0 | BL35: =SUM(BL30:BL34) -> 0 | BM35: =SUM(BM30:BM34) -> 0 | BN35: =SUM(BN30:BN34) -> 0 | BO35: =SUM(BO30:BO34) -> 0 | BQ35: =SUM(BQ30:BQ34) -> 455.0368 | BR35: =SUM(BR30:BR34) -> 53.1871 | BS35: =SUM(BS30:BS34) -> 0 | BT35: =SUM(BT30:BT34) -> 0 | BU35: =SUM(BU30:BU34) -> 0 | BV35: =SUM(BV30:BV34) -> 508.2239

Sheet BB之过程-theta_Shock_exBI_t=0
A1: 子过程 | B1: tau | C1: t | D1: id | E1: name | F1: A_R | G1: A_Q | H1: A_P | I1: A_other | J1: A_exBI | K1: A_BI_all | L1: A_all | M1: Z_D | N1: Z_other | O1: Z_exBI | P1: Z_BI_all | Q1: Z_all | R1: E_all | S1: Shock_B_A | T1: Shock_B_Z | U1: BB.Shock_P_s | V1: BB.Shock_D_s | W1: BB.Shock_BI_def_s | X1: BB.Shock_BI_run_ilq_s | Y1: BB.Shock_BI_run_br_s | Z1: BB.Shock_BI_def_t | AA1: BB.Shock_BI_run_ilq_t | AB1: BB.Shock_BI_run_br_t | AC1: BB.Shock_BI_run_s | AD1: BB.Shock_BI_run_t | AE1: BB.Shock_BI_s | AF1: BB.Shock_BI_t | AH1: name | AI1: A_R | AJ1: A_Q | AK1: A_P | AL1: A_other | AM1: A_exBI | AN1: A_BI_all | AO1: A_all | AP1: Z_D | AQ1: Z_other | AR1: Z_exBI | AS1: Z_BI_all | AT1: Z_all | AU1: E_all | AV1: Shock_B_A | AW1: Shock_B_Z | AX1: BB.Shock_L_exBI_s | AY1: BB.Shock_D_s | AZ1: BB.Shock_BI_def_s | BA1: BB.Shock_BI_run_ilq_s | BB1: BB.Shock_BI_run_br_s | BC1: BB.Shock_BI_def_t | BD1: BB.Shock_BI_run_ilq_t | BE1: BB.Shock_BI_run_br_t | BF1: BB.Shock_BI_run_s | BG1: BB.Shock_BI_run_t | BH1: BB.Shock_BI_s | BI1: BB.Shock_BI_t
A2: 2 | B2: 1 | C2: 0 | D2: 1 | E2: BK1 | F2: 0 | G2: 477.125 | H2: 1631.73 | I2: 0 | J2: =F2+G2+H2+I2 -> 2108.855 | K2: 2185.24 | L2: =J2+K2 -> 4294.095 | M2: 3160.99 | N2: 0 | O2: =M2+N2 -> 3160.99 | P2: 959.6 | Q2: =P2+O2 -> 4120.59 | R2: =MAX(L2-Q2,0) -> 173.505 | S2: 0 | T2: 0 | U2: 0 | V2: 0 | W2: 0 | X2: 0 | Y2: 0 | Z2: 0 | AA2: 0 | AB2: 0 | AC2: =X2+Y2 -> 0 | AD2: =AA2+AB2 -> 0 | AE2: =W2+AC2 -> 0 | AF2: =Z2+AD2 -> 0
D3: 2 | E3: BK2 | F3: 0 | G3: 587.693 | H3: 4303.24 | I3: 0 | J3: =F3+G3+H3+I3 -> 4890.933 | K3: 398.37 | L3: =J3+K3 -> 5289.303 | M3: 3231.37 | N3: 0 | O3: =M3+N3 -> 3231.37 | P3: 1844.24 | Q3: =P3+O3 -> 5075.61 | R3: =MAX(L3-Q3,0) -> 213.693 | S3: 0 | T3: 0 | U3: 0 | V3: 0 | W3: 0 | X3: 0 | Y3: 0 | Z3: 0 | AA3: 0 | AB3: 0 | AC3: =X3+Y3 -> 0 | AD3: =AA3+AB3 -> 0 | AE3: =W3+AC3 -> 0 | AF3: =Z3+AD3 -> 0
D4: 3 | E4: BK3 | F4: 0 | G4: 513.847 | H4: 3379.72 | I4: 0 | J4: =F4+G4+H4+I4 -> 3893.567 | K4: 730.99 | L4: =J4+K4 -> 4624.557 | M4: 3184.36 | N4: 0 | O4: =M4+N4 -> 3184.36 | P4: 1253.34 | Q4: =P4+O4 -> 4437.7 | R4: =MAX(L4-Q4,0) -> 186.857 | S4: 0 | T4: 0 | U4: 0 | V4: 0 | W4: 0 | X4: 0 | Y4: 0 | Z4: 0 | AA4: 0 | AB4: 0 | AC4: =X4+Y4 -> 0 | AD4: =AA4+AB4 -> 0 | AE4: =W4+AC4 -> 0 | AF4: =Z4+AD4 -> 0
D5: 4 | E5: BK4 | F5: 0 | G5: 713.662 | H5: 4351.47 | I5: 0 | J5: =F5+G5+H5+I5 -> 5065.132 | K5: 1357.75 | L5: =J5+K5 -> 6422.882 | M5: 3311.51 | N5: 0 | O5: =M5+N5 -> 3311.51 | P5: 2851.85 | Q5: =P5+O5 -> 6163.36 | R5: =MAX(L5-Q5,0) -> 259.522 | S5: 0 | T5: 0 | U5: 0 | V5: 0 | W5: 0 | X5: 0 | Y5: 0 | Z5: 0 | AA5: 0 | AB5: 0 | AC5: =X5+Y5 -> 0 | AD5: =AA5+AB5 -> 0 | AE5: =W5+AC5 -> 0 | AF5: =Z5+AD5 -> 0
D6: 5 | E6: BK5 | F6: 0 | G6: 417.257 | H6: 620.69 | I6: 0 | J6: =F6+G6+H6+I6 -> 1037.947 | K6: 2717.39 | L6: =J6+K6 -> 3755.337 | M6: 3122.9 | N6: 0 | O6: =M6+N6 -> 3122.9 | P6: 480.71 | Q6: =P6+O6 -> 3603.61 | R6: =MAX(L6-Q6,0) -> 151.727 | S6: 0 | T6: 0 | U6: 0 | V6: 0 | W6: 0 | X6: 0 | Y6: 0 | Z6: 0 | AA6: 0 | AB6: 0 | AC6: =X6+Y6 -> 0 | AD6: =AA6+AB6 -> 0 | AE6: =W6+AC6 -> 0 | AF6: =Z6+AD6 -> 0
F7: =SUM(F2:F6) -> 0 | G7: =SUM(G2:G6) -> 2709.584 | H7: =SUM(H2:H6) -> 14286.85 | I7: =SUM(I2:I6) -> 0 | J7: =SUM(J2:J6) -> 16996.434 | K7: =SUM(K2:K6) -> 7389.74 | L7: =SUM(L2:L6) -> 24386.174 | M7: =SUM(M2:M6) -> 16011.13 | ... AF7: =SUM(AF2:AF6) -> 0
B9: 1 | C9: 1-2 | D9: 1 | E9: BK1 | F9: 0 | G9: 477.125 | H9: 1631.73 | I9: 0 | J9: =F9+G9+H9+I9 -> 2108.855 | K9: 2185.24 | L9: =J9+K9 -> 4294.095 | M9: 3160.99 | N9: 0 | O9: =M9+N9 -> 3160.99 | P9: 959.6 | Q9: =P9+O9 -> 4120.59 | R9: =MAX(L9-Q9,0) -> 173.505 | S9: 0 | T9: 3160.99 | U9: 0 | V9: 0 | W9: 0 | X9: 0 | Y9: 0 | Z9: 0 | AA9: 0 | AB9: 0 | AC9: =X9+Y9 -> 0 | AD9: =AA9+AB9 -> 0 | AE9: =W9+AC9 -> 0 | AF9: =Z9+AD9 -> 0
D10: 2 | E10: BK2 | F10: 0 | G10: 587.693 | H10: 4303.24 | I10: 0 | J10: =F10+G10+H10+I10 -> 4890.933 | K10: 398.37 | L10: =J10+K10 -> 5289.303 | M10: 3231.37 | N10: 0 | O10: =M10+N10 -> 3231.37 | P10: 1844.24 | Q10: =P10+O10 -> 5075.61 | R10: =MAX(L10-Q10,0) -> 213.693 | S10: 0 | T10: 0 | U10: 0 | V10: 0 | W10: 0 | X10: 0 | Y10: 0 | Z10: 0 | AA10: 0 | AB10: 0 | AC10: =X10+Y10 -> 0 | AD10: =AA10+AB10 -> 0 | AE10: =W10+AC10 -> 0 | AF10: =Z10+AD10 -> 0
D11: 3 | E11: BK3 | F11: 0 | G11: 513.847 | H11: 3379.72 | I11: 0 | J11: =F11+G11+H11+I11 -> 3893.567 | K11: 730.99 | L11: =J11+K11 -> 4624.557 | M11: 3184.36 | N11: 0 | O11: =M11+N11 -> 3184.36 | P11: 1253.34 | Q11: =P11+O11 -> 4437.7 | R11: =MAX(L11-Q11,0) -> 186.857 | S11: 0 | T11: 0 | U11: 0 | V11: 0 | W11: 0 | X11: 0 | Y11: 0 | Z11: 0 | AA11: 0 | AB11: 0 | AC11: =X11+Y11 -> 0 | AD11: =AA11+AB11 -> 0 | AE11: =W11+AC11 -> 0 | AF11: =Z11+AD11 -> 0
D12: 4 | E12: BK4 | F12: 0 | G12: 713.662 | H12: 4351.47 | I12: 0 | J12: =F12+G12+H12+I12 -> 5065.132 | K12: 1357.75 | L12: =J12+K12 -> 6422.882 | M12: 3311.51 | N12: 0 | O12: =M12+N12 -> 3311.51 | P12: 2851.85 | Q12: =P12+O12 -> 6163.36 | R12: =MAX(L12-Q12,0) -> 259.522 | S12: 0 | T12: 0 | U12: 0 | V12: 0 | W12: 0 | X12: 0 | Y12: 0 | Z12: 0 | AA12: 0 | AB12: 0 | AC12: =X12+Y12 -> 0 | AD12: =AA12+AB12 -> 0 | AE12: =W12+AC12 -> 0 | AF12: =Z12+AD12 -> 0
D13: 5 | E13: BK5 | F13: 0 | G13: 417.257 | H13: 620.69 | I13: 0 | J13: =F13+G13+H13+I13 -> 1037.947 | K13: 2717.39 | L13: =J13+K13 -> 3755.337 | M13: 3122.9 | N13: 0 | O13: =M13+N13 -> 3122.9 | P13: 480.71 | Q13: =P13+O13 -> 3603.61 | R13: =MAX(L13-Q13,0) -> 151.727 | S13: 0 | T13: 0 | U13: 0 | V13: 0 | W13: 0 | X13: 0 | Y13: 0 | Z13: 0 | AA13: 0 | AB13: 0 | AC13: =X13+Y13 -> 0 | AD13: =AA13+AB13 -> 0 | AE13: =W13+AC13 -> 0 | AF13: =Z13+AD13 -> 0
F14: =SUM(F9:F13) -> 0 | G14: =SUM(G9:G13) -> 2709.584 | H14: =SUM(H9:H13) -> 14286.85 | I14: =SUM(I9:I13) -> 0 | J14: =SUM(J9:J13) -> 16996.434 | K14: =SUM(K9:K13) -> 7389.74 | L14: =SUM(L9:L13) -> 24386.174 | M14: =SUM(M9:M13) -> 16011.13 | ... AF14: =SUM(AF9:AF13) -> 0
B16: 1 | C16: 2-2 | D16: 1 | E16: BK1 | F16: 0 | G16: 0 | H16: 484.39502 | I16: 0 | J16: =F16+G16+H16+I16 -> 484.39502 | K16: 648.70996 | L16: =J16+K16 -> 1133.105 | M16: 0 | N16: 0 | O16: =M16+N16 -> 0 | P16: 959.6 | Q16: =P16+O16 -> 959.6 | R16: =MAX(L16-Q16,0) -> 173.50498 | S16: 0 | T16: 3160.99 | U16: 0 | V16: 0 | W16: 0 | X16: 1536.53 | Y16: 0 | Z16: 0 | AA16: 0 | AB16: 0 | AC16: =X16+Y16 -> 1536.53 | AD16: =AA16+AB16 -> 0 | AE16: =W16+AC16 -> 1536.53 | AF16: =Z16+AD16 -> 0
D17: 2 | E17: BK2 | F17: 0 | G17: 587.693 | H17: 4303.24 | I17: 0 | J17: =F17+G17+H17+I17 -> 4890.933 | K17: 398.37 | L17: =J17+K17 -> 5289.303 | M17: 3231.37 | N17: 0 | O17: =M17+N17 -> 3231.37 | P17: 1844.24 | Q17: =P17+O17 -> 5075.61 | R17: =MAX(L17-Q17,0) -> 213.693 | S17: 0 | T17: 0 | U17: 0 | V17: 0 | W17: 0 | X17: 0 | Y17: 0 | Z17: 0 | AA17: 0 | AB17: 0 | AC17: =X17+Y17 -> 0 | AD17: =AA17+AB17 -> 0 | AE17: =W17+AC17 -> 0 | AF17: =Z17+AD17 -> 0
D18: 3 | E18: BK3 | F18: 0 | G18: 513.847 | H18: 3379.72 | I18: 0 | J18: =F18+G18+H18+I18 -> 3893.567 | K18: 730.99 | L18: =J18+K18 -> 4624.557 | M18: 3184.36 | N18: 0 | O18: =M18+N18 -> 3184.36 | P18: 1253.34 | Q18: =P18+O18 -> 4437.7 | R18: =MAX(L18-Q18,0) -> 186.857 | S18: 0 | T18: 0 | U18: 0 | V18: 0 | W18: 0 | X18: 0 | Y18: 0 | Z18: 0 | AA18: 0 | AB18: 0 | AC18: =X18+Y18 -> 0 | AD18: =AA18+AB18 -> 0 | AE18: =W18+AC18 -> 0 | AF18: =Z18+AD18 -> 0
D19: 4 | E19: BK4 | F19: 0 | G19: 713.662 | H19: 4351.47 | I19: 0 | J19: =F19+G19+H19+I19 -> 5065.132 | K19: 1357.75 | L19: =J19+K19 -> 6422.882 | M19: 3311.51 | N19: 0 | O19: =M19+N19 -> 3311.51 | P19: 2851.85 | Q19: =P19+O19 -> 6163.36 | R19: =MAX(L19-Q19,0) -> 259.522 | S19: 0 | T19: 0 | U19: 0 | V19: 0 | W19: 0 | X19: 0 | Y19: 0 | Z19: 0 | AA19: 0 | AB19: 0 | AC19: =X19+Y19 -> 0 | AD19: =AA19+AB19 -> 0 | AE19: =W19+AC19 -> 0 | AF19: =Z19+AD19 -> 0
D20: 5 | E20: BK5 | F20: 0 | G20: 417.257 | H20: 620.69 | I20: 0 | J20: =F20+G20+H20+I20 -> 1037.947 | K20: 2717.39 | L20: =J20+K20 -> 3755.337 | M20: 3122.9 | N20: 0 | O20: =M20+N20 -> 3122.9 | P20: 480.71 | Q20: =P20+O20 -> 3603.61 | R20: =MAX(L20-Q20,0) -> 151.727 | S20: 0 | T20: 0 | U20: 0 | V20: 0 | W20: 0 | X20: 0 | Y20: 0 | Z20: 0 | AA20: 0 | AB20: 0 | AC20: =X20+Y20 -> 0 | AD20: =AA20+AB20 -> 0 | AE20: =W20+AC20 -> 0 | AF20: =Z20+AD20 -> 0
F21: =SUM(F16:F20) -> 0 | G21: =SUM(G16:G20) -> 2232.459 | H21: =SUM(H16:H20) -> 13139.515 | I21: =SUM(I16:I20) -> 0 | J21: =SUM(J16:J20) -> 15371.974 | K21: =SUM(K16:K20) -> 5853.21 | L21: =SUM(L16:L20) -> 21225.184 | M21: =SUM(M16:M20) -> 12850.14 | ... AF21: =SUM(AF16:AF20) -> 0
B23: 2 | C23: 1-2 | D23: 1 | E23: BK1 | F23: 0 | G23: 0 | H23: 484.39502 | I23: 0 | J23: =F23+G23+H23+I23 -> 484.39502 | K23: 648.70996 | L23: =J23+K23 -> 1133.105 | M23: 0 | N23: 0 | O23: =M23+N23 -> 0 | P23: 959.6 | Q23: =P23+O23 -> 959.6 | R23: =MAX(L23-Q23,0) -> 173.50498 | S23: 0 | T23: 0 | U23: 0 | V23: 0 | W23: 0 | X23: 1536.53 | Y23: 0 | Z23: 0 | AA23: 0 | AB23: 0 | AC23: =X23+Y23 -> 1536.53 | AD23: =AA23+AB23 -> 0 | AE23: =W23+AC23 -> 1536.53 | AF23: =Z23+AD23 -> 0
D24: 2 | E24: BK2 | F24: 0 | G24: 587.693 | H24: 4303.24 | I24: 0 | J24: =F24+G24+H24+I24 -> 4890.933 | K24: 398.37 | L24: =J24+K24 -> 5289.303 | M24: 3231.37 | N24: 0 | O24: =M24+N24 -> 3231.37 | P24: 1844.24 | Q24: =P24+O24 -> 5075.61 | R24: =MAX(L24-Q24,0) -> 213.693 | S24: 0 | T24: 1215.41 | U24: 0 | V24: 0 | W24: 0 | X24: 0 | Y24: 0 | Z24: 0 | AA24: 1215.41 | AB24: 0 | AC24: =X24+Y24 -> 0 | AD24: =AA24+AB24 -> 1215.41 | AE24: =W24+AC24 -> 0 | AF24: =Z24+AD24 -> 1215.41
D25: 3 | E25: BK3 | F25: 0 | G25: 513.847 | H25: 3379.72 | I25: 0 | J25: =F25+G25+H25+I25 -> 3893.567 | K25: 730.99 | L25: =J25+K25 -> 4624.557 | M25: 3184.36 | N25: 0 | O25: =M25+N25 -> 3184.36 | P25: 1253.34 | Q25: =P25+O25 -> 4437.7 | R25: =MAX(L25-Q25,0) -> 186.857 | S25: 0 | T25: 0 | U25: 0 | V25: 0 | W25: 0 | X25: 0 | Y25: 0 | Z25: 0 | AA25: 0 | AB25: 0 | AC25: =X25+Y25 -> 0 | AD25: =AA25+AB25 -> 0 | AE25: =W25+AC25 -> 0 | AF25: =Z25+AD25 -> 0
D26: 4 | E26: BK4 | F26: 0 | G26: 713.662 | H26: 4351.47 | I26: 0 | J26: =F26+G26+H26+I26 -> 5065.132 | K26: 1357.75 | L26: =J26+K26 -> 6422.882 | M26: 3311.51 | N26: 0 | O26: =M26+N26 -> 3311.51 | P26: 2851.85 | Q26: =P26+O26 -> 6163.36 | R26: =MAX(L26-Q26,0) -> 259.522 | S26: 0 | T26: 94.5442 | U26: 0 | V26: 0 | W26: 0 | X26: 0 | Y26: 0 | Z26: 0 | AA26: 94.5442 | AB26: 0 | AC26: =X26+Y26 -> 0 | AD26: =AA26+AB26 -> 94.5442 | AE26: =W26+AC26 -> 0 | AF26: =Z26+AD26 -> 94.5442
D27: 5 | E27: BK5 | F27: 0 | G27: 417.257 | H27: 620.69 | I27: 0 | J27: =F27+G27+H27+I27 -> 1037.947 | K27: 2717.39 | L27: =J27+K27 -> 3755.337 | M27: 3122.9 | N27: 0 | O27: =M27+N27 -> 3122.9 | P27: 480.71 | Q27: =P27+O27 -> 3603.61 | R27: =MAX(L27-Q27,0) -> 151.727 | S27: 0 | T27: 226.573 | U27: 0 | V27: 0 | W27: 0 | X27: 0 | Y27: 0 | Z27: 0 | AA27: 226.573 | AB27: 0 | AC27: =X27+Y27 -> 0 | AD27: =AA27+AB27 -> 226.573 | AE27: =W27+AC27 -> 0 | AF27: =Z27+AD27 -> 226.573
F28: =SUM(F23:F27) -> 0 | G28: =SUM(G23:G27) -> 2232.459 | H28: =SUM(H23:H27) -> 13139.515 | I28: =SUM(I23:I27) -> 0 | J28: =SUM(J23:J27) -> 15371.974 | K28: =SUM(K23:K27) -> 5853.21 | L28: =SUM(L23:L27) -> 21225.184 | M28: =SUM(M23:M27) -> 12850.14 | ... AF28: =SUM(AF23:AF27) -> 1536.5272
B30: 2 | C30: 2-2 | D30: 1 | E30: BK1 | F30: 0 | G30: 0 | H30: 484.39502 | I30: 0 | J30: =F30+G30+H30+I30 -> 484.39502 | K30: 648.70996 | L30: =J30+K30 -> 1133.105 | M30: 0 | N30: 0 | O30: =M30+N30 -> 0 | P30: 959.6 | Q30: =P30+O30 -> 959.6 | R30: =MAX(L30-Q30,0) -> 173.50498 | S30: 0 | T30: 0 | U30: 0 | V30: 0 | W30: 0 | X30: 0 | Y30: 0 | Z30: 0 | AA30: 0 | AB30: 0 | AC30: =X30+Y30 -> 0 | AD30: =AA30+AB30 -> 0 | AE30: =W30+AC30 -> 0 | AF30: =Z30+AD30 -> 0
D31: 2 | E31: BK2 | F31: 0 | G31: 0 | H31: 3728.7073 | I31: 0 | J31: =F31+G31+H31+I31 -> 3728.7073 | K31: 345.18295 | L31: =J31+K31 -> 4073.8902 | M31: 3231.37 | N31: 0 | O31: =M31+N31 -> 3231.37 | P31: 628.827 | Q31: =P31+O31 -> 3860.197 | R31: =MAX(L31-Q31,0) -> 213.69325 | S31: 0 | T31: 1215.41 | U31: 574.53296 | V31: 0 | W31: 0 | X31: 53.187042 | Y31: 0 | Z31: 0 | AA31: 0 | AB31: 0 | AC31: =X31+Y31 -> 53.187042 | AD31: =AA31+AB31 -> 0 | AE31: =W31+AC31 -> 53.187042 | AF31: =Z31+AD31 -> 0
D32: 3 | E32: BK3 | F32: 0 | G32: 513.847 | H32: 3379.72 | I32: 0 | J32: =F32+G32+H32+I32 -> 3893.567 | K32: 730.99 | L32: =J32+K32 -> 4624.557 | M32: 3184.36 | N32: 0 | O32: =M32+N32 -> 3184.36 | P32: 1253.34 | Q32: =P32+O32 -> 4437.7 | R32: =MAX(L32-Q32,0) -> 186.857 | S32: 0 | T32: 0 | U32: 0 | V32: 0 | W32: 0 | X32: 0 | Y32: 0 | Z32: 0 | AA32: 0 | AB32: 0 | AC32: =X32+Y32 -> 0 | AD32: =AA32+AB32 -> 0 | AE32: =W32+AC32 -> 0 | AF32: =Z32+AD32 -> 0
D33: 4 | E33: BK4 | F33: 0 | G33: 619.11774 | H33: 4351.47 | I33: 0 | J33: =F33+G33+H33+I33 -> 4970.5877 | K33: 1357.75 | L33: =J33+K33 -> 6328.3377 | M33: 3311.51 | N33: 0 | O33: =M33+N33 -> 3311.51 | P33: 2757.3057 | Q33: =P33+O33 -> 6068.8157 | R33: =MAX(L33-Q33,0) -> 259.52204 | S33: 0 | T33: 94.5442 | U33: 0 | V33: 0 | W33: 0 | X33: 0 | Y33: 0 | Z33: 0 | AA33: 0 | AB33: 0 | AC33: =X33+Y33 -> 0 | AD33: =AA33+AB33 -> 0 | AE33: =W33+AC33 -> 0 | AF33: =Z33+AD33 -> 0
D34: 5 | E34: BK5 | F34: 0 | G34: 190.68411 | H34: 620.69 | I34: 0 | J34: =F34+G34+H34+I34 -> 811.37411 | K34: 2717.39 | L34: =J34+K34 -> 3528.7641 | M34: 3122.9 | N34: 0 | O34: =M34+N34 -> 3122.9 | P34: 254.13715 | Q34: =P34+O34 -> 3377.0372 | R34: =MAX(L34-Q34,0) -> 151.72696 | S34: 0 | T34: 226.573 | U34: 0 | V34: 0 | W34: 0 | X34: 0 | Y34: 0 | Z34: 0 | AA34: 0 | AB34: 0 | AC34: =X34+Y34 -> 0 | AD34: =AA34+AB34 -> 0 | AE34: =W34+AC34 -> 0 | AF34: =Z34+AD34 -> 0
F35: =SUM(F30:F34) -> 0 | G35: =SUM(G30:G34) -> 1323.6488 | H35: =SUM(H30:H34) -> 12564.982 | I35: =SUM(I30:I34) -> 0 | J35: =SUM(J30:J34) -> 13888.631 | K35: =SUM(K30:K34) -> 5800.0229 | L35: =SUM(L30:L34) -> 19688.654 | M35: =SUM(M30:M34) -> 12850.14 | ... AF35: =SUM(AF30:AF34) -> 0
B37: 3 | C37: 1-2 | D37: 1 | E37: BK1 | F37: 0 | G37: 0 | H37: 484.39502 | I37: 0 | J37: =F37+G37+H37+I37 -> 484.39502 | K37: 648.70996 | L37: =J37+K37 -> 1133.105 | M37: 0 | N37: 0 | O37: =M37+N37 -> 0 | P37: 959.6 | Q37: =P37+O37 -> 959.6 | R37: =MAX(L37-Q37,0) -> 173.50498 | S37: 0 | T37: 14.5995 | U37: 0 | V37: 0 | W37: 0 | X37: 0 | Y37: 0 | Z37: 14.5995 | AA37: 0 | AB37: 0 | AC37: =X37+Y37 -> 0 | AD37: =AA37+AB37 -> 0 | AE37: =W37+AC37 -> 0 | AF37: =Z37+AD37 -> 14.5995
D38: 2 | E38: BK2 | F38: 0 | G38: 0 | H38: 3728.7073 | I38: 0 | J38: =F38+G38+H38+I38 -> 3728.7073 | K38: 345.18295 | L38: =J38+K38 -> 4073.8902 | M38: 3231.37 | N38: 0 | O38: =M38+N38 -> 3231.37 | P38: 628.827 | Q38: =P38+O38 -> 3860.197 | R38: =MAX(L38-Q38,0) -> 213.69325 | S38: 0 | T38: 0 | U38: 574.53296 | V38: 0 | W38: 0 | X38: 53.187042 | Y38: 0 | Z38: 0 | AA38: 0 | AB38: 0 | AC38: =X38+Y38 -> 53.187042 | AD38: =AA38+AB38 -> 0 | AE38: =W38+AC38 -> 53.187042 | AF38: =Z38+AD38 -> 0
D39: 3 | E39: BK3 | F39: 0 | G39: 513.847 | H39: 3379.72 | I39: 0 | J39: =F39+G39+H39+I39 -> 3893.567 | K39: 730.99 | L39: =J39+K39 -> 4624.557 | M39: 3184.36 | N39: 0 | O39: =M39+N39 -> 3184.36 | P39: 1253.34 | Q39: =P39+O39 -> 4437.7 | R39: =MAX(L39-Q39,0) -> 186.857 | S39: 0 | T39: 38.5875 | U39: 0 | V39: 0 | W39: 0 | X39: 0 | Y39: 0 | Z39: 38.5875 | AA39: 0 | AB39: 0 | AC39: =X39+Y39 -> 0 | AD39: =AA39+AB39 -> 0 | AE39: =W39+AC39 -> 0 | AF39: =Z39+AD39 -> 38.5875
D40: 4 | E40: BK4 | F40: 0 | G40: 619.11774 | H40: 4351.47 | I40: 0 | J40: =F40+G40+H40+I40 -> 4970.5877 | K40: 1357.75 | L40: =J40+K40 -> 6328.3377 | M40: 3311.51 | N40: 0 | O40: =M40+N40 -> 3311.51 | P40: 2757.3057 | Q40: =P40+O40 -> 6068.8157 | R40: =MAX(L40-Q40,0) -> 259.52204 | S40: 0 | T40: 0 | U40: 0 | V40: 0 | W40: 0 | X40: 0 | Y40: 0 | Z40: 0 | AA40: 0 | AB40: 0 | AC40: =X40+Y40 -> 0 | AD40: =AA40+AB40 -> 0 | AE40: =W40+AC40 -> 0 | AF40: =Z40+AD40 -> 0
D41: 5 | E41: BK5 | F41: 0 | G41: 190.68411 | H41: 620.69 | I41: 0 | J41: =F41+G41+H41+I41 -> 811.37411 | K41: 2717.39 | L41: =J41+K41 -> 3528.7641 | M41: 3122.9 | N41: 0 | O41: =M41+N41 -> 3122.9 | P41: 254.13715 | Q41: =P41+O41 -> 3377.0372 | R41: =MAX(L41-Q41,0) -> 151.72696 | S41: 0 | T41: 0 | U41: 0 | V41: 0 | W41: 0 | X41: 0 | Y41: 0 | Z41: 0 | AA41: 0 | AB41: 0 | AC41: =X41+Y41 -> 0 | AD41: =AA41+AB41 -> 0 | AE41: =W41+AC41 -> 0 | AF41: =Z41+AD41 -> 0
F42: =SUM(F37:F41) -> 0 | G42: =SUM(G37:G41) -> 1323.6488 | H42: =SUM(H37:H41) -> 12564.982 | I42: =SUM(I37:I41) -> 0 | J42: =SUM(J37:J41) -> 13888.631 | K42: =SUM(K37:K41) -> 5800.0229 | L42: =SUM(L37:L41) -> 19688.654 | M42: =SUM(M37:M41) -> 12850.14 | ... AF42: =SUM(AF37:AF41) -> 53.187
B44: 3 | C44: 2-2 | D44: 1 | E44: BK1 | F44: 0 | G44: 0 | H44: 478.15384 | I44: 0 | J44: =F44+G44+H44+I44 -> 478.15384 | K44: 640.3516 | L44: =J44+K44 -> 1118.5054 | M44: 0 | N44: 0 | O44: =M44+N44 -> 0 | P44: 945.0005 | Q44: =P44+O44 -> 945.0005 | R44: =MAX(L44-Q44,0) -> 173.50494 | S44: 0 | T44: 14.5995 | U44: 0 | V44: 0 | W44: 0 | X44: 0 | Y44: 0 | Z44: 0 | AA44: 0 | AB44: 0 | AC44: =X44+Y44 -> 0 | AD44: =AA44+AB44 -> 0 | AE44: =W44+AC44 -> 0 | AF44: =Z44+AD44 -> 0
D45: 2 | E45: BK2 | F45: 0 | G45: 0 | H45: 3728.7073 | I45: 0 | J45: =F45+G45+H45+I45 -> 3728.7073 | K45: 345.18295 | L45: =J45+K45 -> 4073.8902 | M45: 3231.37 | N45: 0 | O45: =M45+N45 -> 3231.37 | P45: 628.827 | Q45: =P45+O45 -> 3860.197 | R45: =MAX(L45-Q45,0) -> 213.69325 | S45: 0 | T45: 0 | U45: 0 | V45: 0 | W45: 0 | X45: 0 | Y45: 0 | Z45: 0 | AA45: 0 | AB45: 0 | AC45: =X45+Y45 -> 0 | AD45: =AA45+AB45 -> 0 | AE45: =W45+AC45 -> 0 | AF45: =Z45+AD45 -> 0
D46: 3 | E46: BK3 | F46: 0 | G46: 475.25946 | H46: 3379.72 | I46: 0 | J46: =F46+G46+H46+I46 -> 3854.9795 | K46: 730.99 | L46: =J46+K46 -> 4585.9695 | M46: 3184.36 | N46: 0 | O46: =M46+N46 -> 3184.36 | P46: 1214.7524 | Q46: =P46+O46 -> 4399.1124 | R46: =MAX(L46-Q46,0) -> 186.85706 | S46: 0 | T46: 38.5875 | U46: 0 | V46: 0 | W46: 0 | X46: 0 | Y46: 0 | Z46: 0 | AA46: 0 | AB46: 0 | AC46: =X46+Y46 -> 0 | AD46: =AA46+AB46 -> 0 | AE46: =W46+AC46 -> 0 | AF46: =Z46+AD46 -> 0
D47: 4 | E47: BK4 | F47: 0 | G47: 619.11774 | H47: 4351.47 | I47: 0 | J47: =F47+G47+H47+I47 -> 4970.5877 | K47: 1357.75 | L47: =J47+K47 -> 6328.3377 | M47: 3311.51 | N47: 0 | O47: =M47+N47 -> 3311.51 | P47: 2757.3057 | Q47: =P47+O47 -> 6068.8157 | R47: =MAX(L47-Q47,0) -> 259.52204 | S47: 0 | T47: 0 | U47: 0 | V47: 0 | W47: 0 | X47: 0 | Y47: 0 | Z47: 0 | AA47: 0 | AB47: 0 | AC47: =X47+Y47 -> 0 | AD47: =AA47+AB47 -> 0 | AE47: =W47+AC47 -> 0 | AF47: =Z47+AD47 -> 0
D48: 5 | E48: BK5 | F48: 0 | G48: 190.68411 | H48: 620.69 | I48: 0 | J48: =F48+G48+H48+I48 -> 811.37411 | K48: 2717.39 | L48: =J48+K48 -> 3528.7641 | M48: 3122.9 | N48: 0 | O48: =M48+N48 -> 3122.9 | P48: 254.13715 | Q48: =P48+O48 -> 3377.0372 | R48: =MAX(L48-Q48,0) -> 151.72696 | S48: 0 | T48: 0 | U48: 0 | V48: 0 | W48: 0 | X48: 0 | Y48: 0 | Z48: 0 | AA48: 0 | AB48: 0 | AC48: =X48+Y48 -> 0 | AD48: =AA48+AB48 -> 0 | AE48: =W48+AC48 -> 0 | AF48: =Z48+AD48 -> 0
F49: =SUM(F44:F48) -> 0 | G49: =SUM(G44:G48) -> 1285.0613 | H49: =SUM(H44:H48) -> 12558.741 | I49: =SUM(I44:I48) -> 0 | J49: =SUM(J44:J48) -> 13843.802 | K49: =SUM(K44:K48) -> 5791.6645 | L49: =SUM(L44:L48) -> 19635.467 | M49: =SUM(M44:M48) -> 12850.14 | ... AF49: =SUM(AF44:AF48) -> 0

Sheet BI之过程-theta_Shock_exBI_t=0
A1: 子过程 | B1: id | C1: tau | D1: t | F1: A_BI | M1: Z_BI | T1: Shock_BI_def | AA1: Shock_BI_run_ilq | AH1: Shock_BI_run_br | AO1: Shock_BI_run
A2: 2 | C2: 1 | D2: 0 | F2: 0 | G2: 1728.55 | H2: 0 | I2: 134.46 | J2: 322.23 | K2: =SUM(F2:J2) -> 2185.24 | M2: 0 | N2: 109.35 | O2: 730.99 | P2: 119.26 | Q2: 0 | R2: =SUM(M2:Q2) -> 959.6 | T2: 0 | U2: 0 | V2: 0 | W2: 0 | X2: 0 | Y2: =SUM(T2:X2) -> 0 | AA2: 0 | AB2: 0 | AC2: 0 | AD2: 0 | AE2: 0 | AF2: =SUM(AA2:AE2) -> 0 | AH2: 0 | AI2: 0 | AJ2: 0 | AK2: 0 | AL2: 0 | AM2: =SUM(AH2:AL2) -> 0 | AO2: =AH2+AA2 -> 0 | AP2: =AI2+AB2 -> 0 | AQ2: =AJ2+AC2 -> 0 | AR2: =AK2+AD2 -> 0 | AS2: =AL2+AE2 -> 0 | AT2: =SUM(AO2:AS2) -> 0
F3: 109.35 | G3: 0 | H3: 289.02 | I3: 0 | J3: 0 | K3: =SUM(F3:J3) -> 398.37 | M3: 1728.55 | N3: 0 | O3: 0 | P3: 115.69 | Q3: 0 | R3: =SUM(M3:Q3) -> 1844.24 | T3: 0 | U3: 0 | V3: 0 | W3: 0 | X3: 0 | Y3: =SUM(T3:X3) -> 0 | AA3: 0 | AB3: 0 | AC3: 0 | AD3: 0 | AE3: 0 | AF3: =SUM(AA3:AE3) -> 0 | AH3: 0 | AI3: 0 | AJ3: 0 | AK3: 0 | AL3: 0 | AM3: =SUM(AH3:AL3) -> 0 | AO3: =AH3+AA3 -> 0 | AP3: =AI3+AB3 -> 0 | AQ3: =AJ3+AC3 -> 0 | AR3: =AK3+AD3 -> 0 | AS3: =AL3+AE3 -> 0 | AT3: =SUM(AO3:AS3) -> 0
F4: 730.99 | G4: 0 | H4: 0 | I4: 0 | J4: 0 | K4: =SUM(F4:J4) -> 730.99 | M4: 0 | N4: 289.02 | O4: 0 | P4: 964.32 | Q4: 0 | R4: =SUM(M4:Q4) -> 1253.34 | T4: 0 | U4: 0 | V4: 0 | W4: 0 | X4: 0 | Y4: =SUM(T4:X4) -> 0 | AA4: 0 | AB4: 0 | AC4: 0 | AD4: 0 | AE4: 0 | AF4: =SUM(AA4:AE4) -> 0 | AH4: 0 | AI4: 0 | AJ4: 0 | AK4: 0 | AL4: 0 | AM4: =SUM(AH4:AL4) -> 0 | AO4: =AH4+AA4 -> 0 | AP4: =AI4+AB4 -> 0 | AQ4: =AJ4+AC4 -> 0 | AR4: =AK4+AD4 -> 0 | AS4: =AL4+AE4 -> 0 | AT4: =SUM(AO4:AS4) -> 0
F5: 119.26 | G5: 115.69 | H5: 964.32 | I5: 0 | J5: 158.48 | K5: =SUM(F5:J5) -> 1357.75 | M5: 134.46 | N5: 0 | O5: 0 | P5: 0 | Q5: 2717.39 | R5: =SUM(M5:Q5) -> 2851.85 | T5: 0 | U5: 0 | V5: 0 | W5: 0 | X5: 0 | Y5: =SUM(T5:X5) -> 0 | AA5: 0 | AB5: 0 | AC5: 0 | AD5: 0 | AE5: 0 | AF5: =SUM(AA5:AE5) -> 0 | AH5: 0 | AI5: 0 | AJ5: 0 | AK5: 0 | AL5: 0 | AM5: =SUM(AH5:AL5) -> 0 | AO5: =AH5+AA5 -> 0 | AP5: =AI5+AB5 -> 0 | AQ5: =AJ5+AC5 -> 0 | AR5: =AK5+AD5 -> 0 | AS5: =AL5+AE5 -> 0 | AT5: =SUM(AO5:AS5) -> 0
F6: 0 | G6: 0 | H6: 0 | I6: 2717.39 | J6: 0 | K6: =SUM(F6:J6) -> 2717.39 | M6: 322.23 | N6: 0 | O6: 0 | P6: 158.48 | Q6: 0 | R6: =SUM(M6:Q6) -> 480.71 | T6: 0 | U6: 0 | V6: 0 | W6: 0 | X6: 0 | Y6: =SUM(T6:X6) -> 0 | AA6: 0 | AB6: 0 | AC6: 0 | AD6: 0 | AE6: 0 | AF6: =SUM(AA6:AE6) -> 0 | AH6: 0 | AI6: 0 | AJ6: 0 | AK6: 0 | AL6: 0 | AM6: =SUM(AH6:AL6) -> 0 | AO6: =AH6+AA6 -> 0 | AP6: =AI6+AB6 -> 0 | AQ6: =AJ6+AC6 -> 0 | AR6: =AK6+AD6 -> 0 | AS6: =AL6+AE6 -> 0 | AT6: =SUM(AO6:AS6) -> 0
F7: =SUM(F2:F6) -> 959.6 | G7: =SUM(G2:G6) -> 1844.24 | H7: =SUM(H2:H6) -> 1253.34 | I7: =SUM(I2:I6) -> 2851.85 | J7: =SUM(J2:J6) -> 480.71 | K7: =SUM(K2:K6) -> 7389.74 | M7: =SUM(M2:M6) -> 2185.24 | N7: =SUM(N2:N6) -> 398.37 | O7: =SUM(O2:O6) -> 730.99 | P7: =SUM(P2:P6) -> 1357.75 | Q7: =SUM(Q2:Q6) -> 2717.39 | R7: =SUM(R2:R6) -> 7389.74 | T7: =SUM(T2:T6) -> 0 | U7: =SUM(U2:U6) -> 0 | V7: =SUM(V2:V6) -> 0 | W7: =SUM(W2:W6) -> 0 | X7: =SUM(X2:X6) -> 0 | Y7: =SUM(Y2:Y6) -> 0 | AA7: =SUM(AA2:AA6) -> 0 | AB7: =SUM(AB2:AB6) -> 0 | AC7: =SUM(AC2:AC6) -> 0 | AD7: =SUM(AD2:AD6) -> 0 | AE7: =SUM(AE2:AE6) -> 0 | AF7: =SUM(AF2:AF6) -> 0 | AH7: =SUM(AH2:AH6) -> 0 | AI7: =SUM(AI2:AI6) -> 0 | AJ7: =SUM(AJ2:AJ6) -> 0 | AK7: =SUM(AK2:AK6) -> 0 | AL7: =SUM(AL2:AL6) -> 0 | AM7: =SUM(AM2:AM6) -> 0 | AO7: =SUM(AO2:AO6) -> 0 | AP7: =SUM(AP2:AP6) -> 0 | AQ7: =SUM(AQ2:AQ6) -> 0 | AR7: =SUM(AR2:AR6) -> 0 | AS7: =SUM(AS2:AS6) -> 0 | AT7: =SUM(AT2:AT6) -> 0
C9: 2 | D9: 1-2 | F9: 0 | G9: 513.137 | H9: 0 | I9: 39.9158 | J9: 95.6571 | K9: =SUM(F9:J9) -> 648.7099 | M9: 0 | N9: 109.35 | O9: 730.99 | P9: 119.26 | Q9: 0 | R9: =SUM(M9:Q9) -> 959.6 | T9: 0 | U9: 0 | V9: 0 | W9: 0 | X9: 0 | Y9: =SUM(T9:X9) -> 0 | AA9: 0 | AB9: 0 | AC9: 0 | AD9: 0 | AE9: 0 | AF9: =SUM(AA9:AE9) -> 0 | AH9: 0 | AI9: 0 | AJ9: 0 | AK9: 0 | AL9: 0 | AM9: =SUM(AH9:AL9) -> 0 | AO9: =AH9+AA9 -> 0 | AP9: =AI9+AB9 -> 0 | AQ9: =AJ9+AC9 -> 0 | AR9: =AK9+AD9 -> 0 | AS9: =AL9+AE9 -> 0 | AT9: =SUM(AO9:AS9) -> 0
F10: 109.35 | G10: 0 | H10: 289.02 | I10: 0 | J10: 0 | K10: =SUM(F10:J10) -> 398.37 | M10: 513.137 | N10: 0 | O10: 0 | P10: 115.69 | Q10: 0 | R10: =SUM(M10:Q10) -> 628.827 | T10: 0 | U10: 0 | V10: 0 | W10: 0 | X10: 0 | Y10: =SUM(T10:X10) -> 0 | AA10: 1215.41 | AB10: 0 | AC10: 0 | AD10: 0 | AE10: 0 | AF10: =SUM(AA10:AE10) -> 1215.41 | AH10: 0 | AI10: 0 | AJ10: 0 | AK10: 0 | AL10: 0 | AM10: =SUM(AH10:AL10) -> 0 | AO10: =AH10+AA10 -> 1215.41 | AP10: =AI10+AB10 -> 0 | AQ10: =AJ10+AC10 -> 0 | AR10: =AK10+AD10 -> 0 | AS10: =AL10+AE10 -> 0 | AT10: =SUM(AO10:AS10) -> 1215.41
F11: 730.99 | G11: 0 | H11: 0 | I11: 0 | J11: 0 | K11: =SUM(F11:J11) -> 730.99 | M11: 0 | N11: 289.02 | O11: 0 | P11: 964.32 | Q11: 0 | R11: =SUM(M11:Q11) -> 1253.34 | T11: 0 | U11: 0 | V11: 0 | W11: 0 | X11: 0 | Y11: =SUM(T11:X11) -> 0 | AA11: 0 | AB11: 0 | AC11: 0 | AD11: 0 | AE11: 0 | AF11: =SUM(AA11:AE11) -> 0 | AH11: 0 | AI11: 0 | AJ11: 0 | AK11: 0 | AL11: 0 | AM11: =SUM(AH11:AL11) -> 0 | AO11: =AH11+AA11 -> 0 | AP11: =AI11+AB11 -> 0 | AQ11: =AJ11+AC11 -> 0 | AR11: =AK11+AD11 -> 0 | AS11: =AL11+AE11 -> 0 | AT11: =SUM(AO11:AS11) -> 0
F12: 119.26 | G12: 115.69 | H12: 964.32 | I12: 0 | J12: 158.48 | K12: =SUM(F12:J12) -> 1357.75 | M12: 39.9158 | N12: 0 | O12: 0 | P12: 0 | Q12: 2717.39 | R12: =SUM(M12:Q12) -> 2757.3058 | T12: 0 | U12: 0 | V12: 0 | W12: 0 | X12: 0 | Y12: =SUM(T12:X12) -> 0 | AA12: 94.5442 | AB12: 0 | AC12: 0 | AD12: 0 | AE12: 0 | AF12: =SUM(AA12:AE12) -> 94.5442 | AH12: 0 | AI12: 0 | AJ12: 0 | AK12: 0 | AL12: 0 | AM12: =SUM(AH12:AL12) -> 0 | AO12: =AH12+AA12 -> 94.5442 | AP12: =AI12+AB12 -> 0 | AQ12: =AJ12+AC12 -> 0 | AR12: =AK12+AD12 -> 0 | AS12: =AL12+AE12 -> 0 | AT12: =SUM(AO12:AS12) -> 94.5442
F13: 0 | G13: 0 | H13: 0 | I13: 2717.39 | J13: 0 | K13: =SUM(F13:J13) -> 2717.39 | M13: 95.6571 | N13: 0 | O13: 0 | P13: 158.48 | Q13: 0 | R13: =SUM(M13:Q13) -> 254.1371 | T13: 0 | U13: 0 | V13: 0 | W13: 0 | X13: 0 | Y13: =SUM(T13:X13) -> 0 | AA13: 226.573 | AB13: 0 | AC13: 0 | AD13: 0 | AE13: 0 | AF13: =SUM(AA13:AE13) -> 226.573 | AH13: 0 | AI13: 0 | AJ13: 0 | AK13: 0 | AL13: 0 | AM13: =SUM(AH13:AL13) -> 0 | AO13: =AH13+AA13 -> 226.573 | AP13: =AI13+AB13 -> 0 | AQ13: =AJ13+AC13 -> 0 | AR13: =AK13+AD13 -> 0 | AS13: =AL13+AE13 -> 0 | AT13: =SUM(AO13:AS13) -> 226.573
F14: =SUM(F9:F13) -> 959.6 | G14: =SUM(G9:G13) -> 628.827 | H14: =SUM(H9:H13) -> 1253.34 | I14: =SUM(I9:I13) -> 2757.3058 | J14: =SUM(J9:J13) -> 254.1371 | K14: =SUM(K9:K13) -> 5853.2099 | M14: =SUM(M9:M13) -> 648.7099 | N14: =SUM(N9:N13) -> 398.37 | O14: =SUM(O9:O13) -> 730.99 | P14: =SUM(P9:P13) -> 1357.75 | Q14: =SUM(Q9:Q13) -> 2717.39 | R14: =SUM(R9:R13) -> 5853.2099 | T14: =SUM(T9:T13) -> 0 | U14: =SUM(U9:U13) -> 0 | V14: =SUM(V9:V13) -> 0 | W14: =SUM(W9:W13) -> 0 | X14: =SUM(X9:X13) -> 0 | Y14: =SUM(Y9:Y13) -> 0 | AA14: =SUM(AA9:AA13) -> 1536.5272 | AB14: =SUM(AB9:AB13) -> 0 | AC14: =SUM(AC9:AC13) -> 0 | AD14: =SUM(AD9:AD13) -> 0 | AE14: =SUM(AE9:AE13) -> 0 | AF14: =SUM(AF9:AF13) -> 1536.5272 | AH14: =SUM(AH9:AH13) -> 0 | AI14: =SUM(AI9:AI13) -> 0 | AJ14: =SUM(AJ9:AJ13) -> 0 | AK14: =SUM(AK9:AK13) -> 0 | AL14: =SUM(AL9:AL13) -> 0 | AM14: =SUM(AM9:AM13) -> 0 | AO14: =SUM(AO9:AO13) -> 1536.5272 | AP14: =SUM(AP9:AP13) -> 0 | AQ14: =SUM(AQ9:AQ13) -> 0 | AR14: =SUM(AR9:AR13) -> 0 | AS14: =SUM(AS9:AS13) -> 0 | AT14: =SUM(AT9:AT13) -> 1536.5272
C16: 3 | D16: 1-2 | F16: 0 | G16: 513.137 | H16: 0 | I16: 39.9158 | J16: 95.6571 | K16: =SUM(F16:J16) -> 648.7099 | M16: 0 | N16: 94.7505 | O16: 730.99 | P16: 119.26 | Q16: 0 | R16: =SUM(M16:Q16) -> 945.0005 | T16: 0 | U16: 0 | V16: 0 | W16: 0 | X16: 0 | Y16: =SUM(T16:X16) -> 0 | AA16: 0 | AB16: 14.5995 | AC16: 0 | AD16: 0 | AE16: 0 | AF16: =SUM(AA16:AE16) -> 14.5995 | AH16: 0 | AI16: 0 | AJ16: 0 | AK16: 0 | AL16: 0 | AM16: =SUM(AH16:AL16) -> 0 | AO16: =AH16+AA16 -> 0 | AP16: =AI16+AB16 -> 14.5995 | AQ16: =AJ16+AC16 -> 0 | AR16: =AK16+AD16 -> 0 | AS16: =AL16+AE16 -> 0 | AT16: =SUM(AO16:AS16) -> 14.5995
F17: 94.7505 | G17: 0 | H17: 250.432 | I17: 0 | J17: 0 | K17: =SUM(F17:J17) -> 345.1825 | M17: 513.137 | N17: 0 | O17: 0 | P17: 115.69 | Q17: 0 | R17: =SUM(M17:Q17) -> 628.827 | T17: 0 | U17: 0 | V17: 0 | W17: 0 | X17: 0 | Y17: =SUM(T17:X17) -> 0 | AA17: 0 | AB17: 0 | AC17: 0 | AD17: 0 | AE17: 0 | AF17: =SUM(AA17:AE17) -> 0 | AH17: 0 | AI17: 0 | AJ17: 0 | AK17: 0 | AL17: 0 | AM17: =SUM(AH17:AL17) -> 0 | AO17: =AH17+AA17 -> 0 | AP17: =AI17+AB17 -> 0 | AQ17: =AJ17+AC17 -> 0 | AR17: =AK17+AD17 -> 0 | AS17: =AL17+AE17 -> 0 | AT17: =SUM(AO17:AS17) -> 0
F18: 730.99 | G18: 0 | H18: 0 | I18: 0 | J18: 0 | K18: =SUM(F18:J18) -> 730.99 | M18: 0 | N18: 250.432 | O18: 0 | P18: 964.32 | Q18: 0 | R18: =SUM(M18:Q18) -> 1214.752 | T18: 0 | U18: 0 | V18: 0 | W18: 0 | X18: 0 | Y18: =SUM(T18:X18) -> 0 | AA18: 0 | AB18: 38.5875 | AC18: 0 | AD18: 0 | AE18: 0 | AF18: =SUM(AA18:AE18) -> 38.5875 | AH18: 0 | AI18: 0 | AJ18: 0 | AK18: 0 | AL18: 0 | AM18: =SUM(AH18:AL18) -> 0 | AO18: =AH18+AA18 -> 0 | AP18: =AI18+AB18 -> 38.5875 | AQ18: =AJ18+AC18 -> 0 | AR18: =AK18+AD18 -> 0 | AS18: =AL18+AE18 -> 0 | AT18: =SUM(AO18:AS18) -> 38.5875
F19: 119.26 | G19: 115.69 | H19: 964.32 | I19: 0 | J19: 158.48 | K19: =SUM(F19:J19) -> 1357.75 | M19: 39.9158 | N19: 0 | O19: 0 | P19: 0 | Q19: 2717.39 | R19: =SUM(M19:Q19) -> 2757.3058 | T19: 0 | U19: 0 | V19: 0 | W19: 0 | X19: 0 | Y19: =SUM(T19:X19) -> 0 | AA19: 0 | AB19: 0 | AC19: 0 | AD19: 0 | AE19: 0 | AF19: =SUM(AA19:AE19) -> 0 | AH19: 0 | AI19: 0 | AJ19: 0 | AK19: 0 | AL19: 0 | AM19: =SUM(AH19:AL19) -> 0 | AO19: =AH19+AA19 -> 0 | AP19: =AI19+AB19 -> 0 | AQ19: =AJ19+AC19 -> 0 | AR19: =AK19+AD19 -> 0 | AS19: =AL19+AE19 -> 0 | AT19: =SUM(AO19:AS19) -> 0
F20: 0 | G20: 0 | H20: 0 | I20: 2717.39 | J20: 0 | K20: =SUM(F20:J20) -> 2717.39 | M20: 95.6571 | N20: 0 | O20: 0 | P20: 158.48 | Q20: 0 | R20: =SUM(M20:Q20) -> 254.1371 | T20: 0 | U20: 0 | V20: 0 | W20: 0 | X20: 0 | Y20: =SUM(T20:X20) -> 0 | AA20: 0 | AB20: 0 | AC20: 0 | AD20: 0 | AE20: 0 | AF20: =SUM(AA20:AE20) -> 0 | AH20: 0 | AI20: 0 | AJ20: 0 | AK20: 0 | AL20: 0 | AM20: =SUM(AH20:AL20) -> 0 | AO20: =AH20+AA20 -> 0 | AP20: =AI20+AB20 -> 0 | AQ20: =AJ20+AC20 -> 0 | AR20: =AK20+AD20 -> 0 | AS20: =AL20+AE20 -> 0 | AT20: =SUM(AO20:AS20) -> 0
F21: =SUM(F16:F20) -> 945.0005 | G21: =SUM(G16:G20) -> 628.827 | H21: =SUM(H16:H20) -> 1214.752 | I21: =SUM(I16:I20) -> 2757.3058 | J21: =SUM(J16:J20) -> 254.1371 | K21: =SUM(K16:K20) -> 5800.0224 | M21: =SUM(M16:M20) -> 648.7099 | N21: =SUM(N16:N20) -> 345.1825 | O21: =SUM(O16:O20) -> 730.99 | P21: =SUM(P16:P20) -> 1357.75 | Q21: =SUM(Q16:Q20) -> 2717.39 | R21: =SUM(R16:R20) -> 5800.0224 | T21: =SUM(T16:T20) -> 0 | U21: =SUM(U16:U20) -> 0 | V21: =SUM(V16:V20) -> 0 | W21: =SUM(W16:W20) -> 0 | X21: =SUM(X16:X20) -> 0 | Y21: =SUM(Y16:Y20) -> 0 | AA21: =SUM(AA16:AA20) -> 0 | AB21: =SUM(AB16:AB20) -> 53.187 | AC21: =SUM(AC16:AC20) -> 0 | AD21: =SUM(AD16:AD20) -> 0 | AE21: =SUM(AE16:AE20) -> 0 | AF21: =SUM(AF16:AF20) -> 53.187 | AH21: =SUM(AH16:AH20) -> 0 | AI21: =SUM(AI16:AI20) -> 0 | AJ21: =SUM(AJ16:AJ20) -> 0 | AK21: =SUM(AK16:AK20) -> 0 | AL21: =SUM(AL16:AL20) -> 0 | AM21: =SUM(AM16:AM20) -> 0 | AO21: =SUM(AO16:AO20) -> 0 | AP21: =SUM(AP16:AP20) -> 53.187 | AQ21: =SUM(AQ16:AQ20) -> 0 | AR21: =SUM(AR16:AR20) -> 0 | AS21: =SUM(AS16:AS20) -> 0 | AT21: =SUM(AT16:AT20) -> 53.187

Sheet 原始节点权重
A1: 0 | B1: 1728.55 | C1: 0 | D1: 134.46 | E1: 322.23 | F1: =SUM(A1:E1) -> 2185.24
A2: 109.35 | B2: 0 | C2: 289.02 | D2: 0 | E2: 0 | F2: =SUM(A2:E2) -> 398.37
A3: 730.99 | B3: 0 | C3: 0 | D3: 0 | E3: 0 | F3: =SUM(A3:E3) -> 730.99
A4: 119.26 | B4: 115.69 | C4: 964.32 | D4: 0 | E4: 158.48 | F4: =SUM(A4:E4) -> 1357.75
A5: 0 | B5: 0 | C5: 0 | D5: 2717.39 | E5: 0 | F5: =SUM(A5:E5) -> 2717.39
A6: =SUM(A1:A5) -> 959.6 | B6: =SUM(B1:B5) -> 1844.24 | C6: =SUM(C1:C5) -> 1253.34 | D6: =SUM(D1:D5) -> 2851.85 | E6: =SUM(E1:E5) -> 480.71 | F6: =SUM(F1:F5) -> 7389.74
A13: W

Sheet 按照书中认为的设定的节点权重
A1: =原始节点权重!A1*(1-参数!$A$3) -> 0 | B1: =原始节点权重!B1*(1-参数!$A$3) -> 1037.13 | C1: =原始节点权重!C1*(1-参数!$A$3) -> 0 | D1: =原始节点权重!D1*(1-参数!$A$3) -> 80.676 | E1: =原始节点权重!E1*(1-参数!$A$3) -> 193.338 | F1: =SUM(A1:E1) -> 1311.144
A2: =原始节点权重!A2*(1-参数!$A$3) -> 65.61 | B2: =原始节点权重!B2*(1-参数!$A$3) -> 0 | C2: =原始节点权重!C2*(1-参数!$A$3) -> 173.412 | D2: =原始节点权重!D2*(1-参数!$A$3) -> 0 | E2: =原始节点权重!E2*(1-参数!$A$3) -> 0 | F2: =SUM(A2:E2) -> 239.022
A3: =原始节点权重!A3*(1-参数!$A$3) -> 438.594 | B3: =原始节点权重!B3*(1-参数!$A$3) -> 0 | C3: =原始节点权重!C3*(1-参数!$A$3) -> 0 | D3: =原始节点权重!D3*(1-参数!$A$3) -> 0 | E3: =原始节点权重!E3*(1-参数!$A$3) -> 0 | F3: =SUM(A3:E3) -> 438.594
A4: =原始节点权重!A4*(1-参数!$A$3) -> 71.556 | B4: =原始节点权重!B4*(1-参数!$A$3) -> 69.414 | C4: =原始节点权重!C4*(1-参数!$A$3) -> 578.592 | D4: =原始节点权重!D4*(1-参数!$A$3) -> 0 | E4: =原始节点权重!E4*(1-参数!$A$3) -> 95.088 | F4: =SUM(A4:E4) -> 814.65
A5: =原始节点权重!A5*(1-参数!$A$3) -> 0 | B5: =原始节点权重!B5*(1-参数!$A$3) -> 0 | C5: =原始节点权重!C5*(1-参数!$A$3) -> 0 | D5: =原始节点权重!D5*(1-参数!$A$3) -> 1630.434 | E5: =原始节点权重!E5*(1-参数!$A$3) -> 0 | F5: =SUM(A5:E5) -> 1630.434
A6: =SUM(A1:A5) -> 575.76 | B6: =SUM(B1:B5) -> 1106.544 | C6: =SUM(C1:C5) -> 752.004 | D6: =SUM(D1:D5) -> 1711.11 | E6: =SUM(E1:E5) -> 288.426 | F6: =SUM(F1:F5) -> 4433.844
A12: W*(1-LGD)
B16: =1728.55+134.46+322.23 -> 2185.24

Sheet 原始资产负债表
A1: id | B1: name | C1: A_Q-1 | D1: A_Q-2 | E1: A_P | F1: A_BI | G1: Z_D | H1: Z_BI | I1: E_all | J1: A_all
A2: 1 | B2: BK1 | C2: 86.75 | D2: 433.75 | E2: 1631.73 | F2: 2185.24 | G2: 3160.99 | H2: 959.6 | I2: 216.83 | J2: 4337.46
A3: 2 | B3: BK2 | C3: 106.85 | D3: 534.27 | E3: 4303.24 | F3: 398.37 | G3: 3231.37 | H3: 1844.24 | I3: 267.13 | J3: 5342.74
A4: 3 | B4: BK3 | C4: 93.43 | D4: 467.13 | E4: 3379.72 | F4: 730.99 | G4: 3184.36 | H4: 1253.34 | I4: 233.56 | J4: 4671.26
A5: 4 | B5: BK4 | C5: 129.76 | D5: 648.78 | E5: 4351.47 | F5: 1357.75 | G5: 3311.51 | H5: 2851.85 | I5: 324.39 | J5: 6487.75
A6: 5 | B6: BK5 | C6: 75.86 | D6: 379.33 | E6: 620.69 | F6: 2717.39 | G6: 3122.9 | H6: 480.71 | I6: 189.66 | J6: 3793.27

Sheet 我设定的Bank之初始
A1: id | B1: name | C1: A_Q | D1: A_P | E1: A_BI | F1: Z_D | G1: Z_BI | H1: E_all | I1: A_all | K1: A_all | L1: Z_all | M1: E_all
A2: 1 | B2: BK1 | C2: =原始资产负债表!C2+原始资产负债表!D2*(1-参数!$B$3) -> 477.125 | D2: 1631.73 | E2: 2185.24 | F2: 3160.99 | G2: 959.6 | H2: 216.83 | I2: 4337.46 | K2: =E2+D2+C2 -> 4294.095 | L2: =F2+G2 -> 4120.59 | M2: =K2-L2 -> 173.505
A3: 2 | B3: BK2 | C3: =原始资产负债表!C3+原始资产负债表!D3*(1-参数!$B$3) -> 587.693 | D3: 4303.24 | E3: 398.37 | F3: 3231.37 | G3: 1844.24 | H3: 267.13 | I3: 5342.74 | K3: =E3+D3+C3 -> 5289.303 | L3: =F3+G3 -> 5075.61 | M3: =K3-L3 -> 213.693
A4: 3 | B4: BK3 | C4: =原始资产负债表!C4+原始资产负债表!D4*(1-参数!$B$3) -> 513.847 | D4: 3379.72 | E4: 730.99 | F4: 3184.36 | G4: 1253.34 | H4: 233.56 | I4: 4671.26 | K4: =E4+D4+C4 -> 4624.557 | L4: =F4+G4 -> 4437.7 | M4: =K4-L4 -> 186.857
A5: 4 | B5: BK4 | C5: =原始资产负债表!C5+原始资产负债表!D5*(1-参数!$B$3) -> 713.662 | D5: 4351.47 | E5: 1357.75 | F5: 3311.51 | G5: 2851.85 | H5: 324.39 | I5: 6487.75 | K5: =E5+D5+C5 -> 6422.882 | L5: =F5+G5 -> 6163.36 | M5: =K5-L5 -> 259.522
A6: 5 | B6: BK5 | C6: =原始资产负债表!C6+原始资产负债表!D6*(1-参数!$B$3) -> 417.257 | D6: 620.69 | E6: 2717.39 | F6: 3122.9 | G6: 480.71 | H6: 189.66 | I6: 3793.27 | K6: =E6+D6+C6 -> 3755.337 | L6: =F6+G6 -> 3603.61 | M6: =K6-L6 -> 151.727
C8: =SUM(C2:C7) -> 2709.584 | D8: =SUM(D2:D7) -> 14286.85 | E8: =SUM(E2:E7) -> 7389.74 | F8: =SUM(F2:F7) -> 16011.13 | G8: =SUM(G2:G7) -> 7389.74 | H8: =SUM(H2:H7) -> 1231.57 | I8: =SUM(I2:I7) -> 24632.48
A10: tau | B10: t | C10: id | D10: name | E10: A_R | F10: A_Q | G10: A_P | H10: A_BI_all | I10: Z_D | J10: Z_BI_all | K10: A_exBI | L10: A_all | M10: Z_exBI | N10: Z_all | O10: E_all | P10: Shock_B_A | Q10: Shock_B_Z | R10: BB.Shock_BI_def_s | S10: BB.Shock_BI_def_t | T10: BB.Shock_BI_run_ilq_s | U10: BB.Shock_BI_run_ilq_t | V10: BB.Shock_BI_run_br_s | W10: BB.Shock_BI_run_br_t | X10: BB.Shock_BI_run_s | Y10: BB.Shock_BI_run_t
A11: 1 | B11: 1 | C11: 1 | D11: BK1 | E11: 0 | F11: 477.125 | G11: 1631.73 | H11: 2185.24 | I11: 3160.99 | J11: 959.6 | K11: =E11+F11+G11 -> 2108.855 | L11: =K11+H11 -> 4294.095 | M11: =I11 -> 3160.99 | N11: =J11+M11 -> 4120.59 | O11: =MAX(L11-N11,0) -> 173.505 | P11: 0 | Q11: 0 | R11: 0 | S11: 0 | T11: 0 | U11: 0 | V11: 0 | W11: 0 | X11: =T11+V11 -> 0 | Y11: =U11+W11 -> 0
C12: 2 | D12: BK2 | E12: 0 | F12: 587.693 | G12: 4303.24 | H12: 398.37 | I12: 3231.37 | J12: 1844.24 | K12: =E12+F12+G12 -> 4890.933 | L12: =K12+H12 -> 5289.303 | M12: =I12 -> 3231.37 | N12: =J12+M12 -> 5075.61 | O12: =MAX(L12-N12,0) -> 213.693 | P12: 0 | Q12: 0 | R12: 0 | S12: 0 | T12: 0 | U12: 0 | V12: 0 | W12: 0 | X12: =T12+V12 -> 0 | Y12: =U12+W12 -> 0
C13: 3 | D13: BK3 | E13: 0 | F13: 513.847 | G13: 3379.72 | H13: 730.99 | I13: 3184.36 | J13: 1253.34 | K13: =E13+F13+G13 -> 3893.567 | L13: =K13+H13 -> 4624.557 | M13: =I13 -> 3184.36 | N13: =J13+M13 -> 4437.7 | O13: =MAX(L13-N13,0) -> 186.857 | P13: 0 | Q13: 0 | R13: 0 | S13: 0 | T13: 0 | U13: 0 | V13: 0 | W13: 0 | X13: =T13+V13 -> 0 | Y13: =U13+W13 -> 0
C14: 4 | D14: BK4 | E14: 0 | F14: 713.662 | G14: 4351.47 | H14: 1357.75 | I14: 3311.51 | J14: 2851.85 | K14: =E14+F14+G14 -> 5065.132 | L14: =K14+H14 -> 6422.882 | M14: =I14 -> 3311.51 | N14: =J14+M14 -> 6163.36 | O14: =MAX(L14-N14,0) -> 259.522 | P14: 0 | Q14: 0 | R14: 0 | S14: 0 | T14: 0 | U14: 0 | V14: 0 | W14: 0 | X14: =T14+V14 -> 0 | Y14: =U14+W14 -> 0
C15: 5 | D15: BK5 | E15: 0 | F15: 417.257 | G15: 620.69 | H15: 2717.39 | I15: 3122.9 | J15: 480.71 | K15: =E15+F15+G15 -> 1037.947 | L15: =K15+H15 -> 3755.337 | M15: =I15 -> 3122.9 | N15: =J15+M15 -> 3603.61 | O15: =MAX(L15-N15,0) -> 151.727 | P15: 0 | Q15: 0 | R15: 0 | S15: 0 | T15: 0 | U15: 0 | V15: 0 | W15: 0 | X15: =T15+V15 -> 0 | Y15: =U15+W15 -> 0
E16: =SUM(E11:E15) -> 0 | F16: =SUM(F11:F15) -> 2709.584 | G16: =SUM(G11:G15) -> 14286.85 | H16: =SUM(H11:H15) -> 7389.74 | I16: =SUM(I11:I15) -> 16011.13 | J16: =SUM(J11:J15) -> 7389.74 | K16: =SUM(K11:K15) -> 16996.434 | L16: =SUM(L11:L15) -> 24386.174 | ... Y16: =SUM(Y11:Y15) -> 0

Sheet 我设定的Bank Interbank之初始
A1: 0 | B1: 1728.55 | C1: 0 | D1: 134.46 | E1: 322.23 | F1: =SUM(A1:E1) -> 2185.24
A2: 109.35 | B2: 0 | C2: 289.02 | D2: 0 | E2: 0 | F2: =SUM(A2:E2) -> 398.37
A3: 730.99 | B3: 0 | C3: 0 | D3: 0 | E3: 0 | F3: =SUM(A3:E3) -> 730.99
A4: 119.26 | B4: 115.69 | C4: 964.32 | D4: 0 | E4: 158.48 | F4: =SUM(A4:E4) -> 1357.75
A5: 0 | B5: 0 | C5: 0 | D5: 2717.39 | E5: 0 | F5: =SUM(A5:E5) -> 2717.39
A6: =SUM(A1:A5) -> 959.6 | B6: =SUM(B1:B5) -> 1844.24 | C6: =SUM(C1:C5) -> 1253.34 | D6: =SUM(D1:D5) -> 2851.85 | E6: =SUM(E1:E5) -> 480.71 | F6: =SUM(F1:F5) -> 7389.74
A12: W*(1-LGD)
B16: =1728.55+134.46+322.23 -> 2185.24
A18: id | B18: tau | C18: t | E18: A_BI | L18: Z_BI | S18: Shock_BI_def | Z18: Shock_BI_run_br | AG18: Shock_BI_run_ilq | AN18: Shock_BI_run
B20: 1 | C20: 1 | E20: 0 | F20: 1728.55 | G20: 0 | H20: 134.46 | I20: 322.23 | J20: =SUM(E20:I20) -> 2185.24 | L20: 0 | M20: 109.35 | N20: 730.99 | O20: 119.26 | P20: 0 | Q20: =SUM(L20:P20) -> 959.6 | S20: 0 | T20: 0 | U20: 0 | V20: 0 | W20: 0 | X20: =SUM(S20:W20) -> 0 | Z20: 0 | AA20: 0 | AB20: 0 | AC20: 0 | AD20: 0 | AE20: =SUM(Z20:AD20) -> 0 | AG20: 0 | AH20: 0 | AI20: 0 | AJ20: 0 | AK20: 0 | AL20: =SUM(AG20:AK20) -> 0 | AN20: =Z20+AG20 -> 0 | AO20: =AA20+AH20 -> 0 | AP20: =AB20+AI20 -> 0 | AQ20: =AC20+AJ20 -> 0 | AR20: =AD20+AK20 -> 0 | AS20: =SUM(AN20:AR20) -> 0
E21: 109.35 | F21: 0 | G21: 289.02 | H21: 0 | I21: 0 | J21: =SUM(E21:I21) -> 398.37 | L21: 1728.55 | M21: 0 | N21: 0 | O21: 115.69 | P21: 0 | Q21: =SUM(L21:P21) -> 1844.24 | S21: 0 | T21: 0 | U21: 0 | V21: 0 | W21: 0 | X21: =SUM(S21:W21) -> 0 | Z21: 0 | AA21: 0 | AB21: 0 | AC21: 0 | AD21: 0 | AE21: =SUM(Z21:AD21) -> 0 | AG21: 0 | AH21: 0 | AI21: 0 | AJ21: 0 | AK21: 0 | AL21: =SUM(AG21:AK21) -> 0 | AN21: =Z21+AG21 -> 0 | AO21: =AA21+AH21 -> 0 | AP21: =AB21+AI21 -> 0 | AQ21: =AC21+AJ21 -> 0 | AR21: =AD21+AK21 -> 0 | AS21: =SUM(AN21:AR21) -> 0
E22: 730.99 | F22: 0 | G22: 0 | H22: 0 | I22: 0 | J22: =SUM(E22:I22) -> 730.99 | L22: 0 | M22: 289.02 | N22: 0 | O22: 964.32 | P22: 0 | Q22: =SUM(L22:P22) -> 1253.34 | S22: 0 | T22: 0 | U22: 0 | V22: 0 | W22: 0 | X22: =SUM(S22:W22) -> 0 | Z22: 0 | AA22: 0 | AB22: 0 | AC22: 0 | AD22: 0 | AE22: =SUM(Z22:AD22) -> 0 | AG22: 0 | AH22: 0 | AI22: 0 | AJ22: 0 | AK22: 0 | AL22: =SUM(AG22:AK22) -> 0 | AN22: =Z22+AG22 -> 0 | AO22: =AA22+AH22 -> 0 | AP22: =AB22+AI22 -> 0 | AQ22: =AC22+AJ22 -> 0 | AR22: =AD22+AK22 -> 0 | AS22: =SUM(AN22:AR22) -> 0
E23: 119.26 | F23: 115.69 | G23: 964.32 | H23: 0 | I23: 158.48 | J23: =SUM(E23:I23) -> 1357.75 | L23: 134.46 | M23: 0 | N23: 0 | O23: 0 | P23: 2717.39 | Q23: =SUM(L23:P23) -> 2851.85 | S23: 0 | T23: 0 | U23: 0 | V23: 0 | W23: 0 | X23: =SUM(S23:W23) -> 0 | Z23: 0 | AA23: 0 | AB23: 0 | AC23: 0 | AD23: 0 | AE23: =SUM(Z23:AD23) -> 0 | AG23: 0 | AH23: 0 | AI23: 0 | AJ23: 0 | AK23: 0 | AL23: =SUM(AG23:AK23) -> 0 | AN23: =Z23+AG23 -> 0 | AO23: =AA23+AH23 -> 0 | AP23: =AB23+AI23 -> 0 | AQ23: =AC23+AJ23 -> 0 | AR23: =AD23+AK23 -> 0 | AS23: =SUM(AN23:AR23) -> 0
E24: 0 | F24: 0 | G24: 0 | H24: 2717.39 | I24: 0 | J24: =SUM(E24:I24) -> 2717.39 | L24: 322.23 | M24: 0 | N24: 0 | O24: 158.48 | P24: 0 | Q24: =SUM(L24:P24) -> 480.71 | S24: 0 | T24: 0 | U24: 0 | V24: 0 | W24: 0 | X24: =SUM(S24:W24) -> 0 | Z24: 0 | AA24: 0 | AB24: 0 | AC24: 0 | AD24: 0 | AE24: =SUM(Z24:AD24) -> 0 | AG24: 0 | AH24: 0 | AI24: 0 | AJ24: 0 | AK24: 0 | AL24: =SUM(AG24:AK24) -> 0 | AN24: =Z24+AG24 -> 0 | AO24: =AA24+AH24 -> 0 | AP24: =AB24+AI24 -> 0 | AQ24: =AC24+AJ24 -> 0 | AR24: =AD24+AK24 -> 0 | AS24: =SUM(AN24:AR24) -> 0
E25: =SUM(E20:E24) -> 959.6 | F25: =SUM(F20:F24) -> 1844.24 | G25: =SUM(G20:G24) -> 1253.34 | H25: =SUM(H20:H24) -> 2851.85 | I25: =SUM(I20:I24) -> 480.71 | J25: =SUM(J20:J24) -> 7389.74 | L25: =SUM(L20:L24) -> 2185.24 | M25: =SUM(M20:M24) -> 398.37 | N25: =SUM(N20:N24) -> 730.99 | O25: =SUM(O20:O24) -> 1357.75 | P25: =SUM(P20:P24) -> 2717.39 | Q25: =SUM(Q20:Q24) -> 7389.74 | S25: =SUM(S20:S24) -> 0 | T25: =SUM(T20:T24) -> 0 | U25: =SUM(U20:U24) -> 0 | V25: =SUM(V20:V24) -> 0 | W25: =SUM(W20:W24) -> 0 | X25: =SUM(X20:X24) -> 0 | Z25: =SUM(Z20:Z24) -> 0 | AA25: =SUM(AA20:AA24) -> 0 | AB25: =SUM(AB20:AB24) -> 0 | AC25: =SUM(AC20:AC24) -> 0 | AD25: =SUM(AD20:AD24) -> 0 | AE25: =SUM(AE20:AE24) -> 0 | AG25: =SUM(AG20:AG24) -> 0 | AH25: =SUM(AH20:AH24) -> 0 | AI25: =SUM(AI20:AI24) -> 0 | AJ25: =SUM(AJ20:AJ24) -> 0 | AK25: =SUM(AK20:AK24) -> 0 | AL25: =SUM(AL20:AL24) -> 0 | AN25: =SUM(AN20:AN24) -> 0 | AO25: =SUM(AO20:AO24) -> 0 | AP25: =SUM(AP20:AP24) -> 0 | AQ25: =SUM(AQ20:AQ24) -> 0 | AR25: =SUM(AR20:AR24) -> 0 | AS25: =SUM(AS20:AS24) -> 0

Sheet 我设定的Bank之过程-20220307
A1: tau | B1: t | C1: id | D1: name | E1: A_R | F1: A_Q | G1: A_P | H1: A_other | I1: A_exBI | J1: A_BI_all | K1: A_all | L1: Z_D | M1: Z_other | N1: Z_exBI | O1: Z_BI_all | P1: Z_all | Q1: E_all | R1: Shock_B_A | S1: Shock_B_Z | T1: BB.Shock_L_exBI_s | U1: BB.Shock_D_s | V1: BB.Shock_BI_def_s | W1: BB.Shock_BI_run_ilq_s | X1: BB.Shock_BI_run_br_s | Y1: BB.Shock_BI_def_t | Z1: BB.Shock_BI_run_ilq_t | AA1: BB.Shock_BI_run_br_t | AB1: BB.Shock_BI_run_s | AC1: BB.Shock_BI_run_t | AD1: BB.Shock_BI_s | AE1: BB.Shock_BI_t | AG1: name | AH1: A_R | AI1: A_Q | AJ1: A_P | AK1: A_other | AL1: A_exBI | AM1: A_BI_all | AN1: A_all | AO1: Z_D | AP1: Z_other | AQ1: Z_exBI | AR1: Z_BI_all | AS1: Z_all | AT1: E_all | AU1: Shock_B_A | AV1: Shock_B_Z | AW1: BB.Shock_L_exBI_s | AX1: BB.Shock_D_s | AY1: BB.Shock_BI_def_s | AZ1: BB.Shock_BI_run_ilq_s | BA1: BB.Shock_BI_run_br_s | BB1: BB.Shock_BI_def_t | BC1: BB.Shock_BI_run_ilq_t | BD1: BB.Shock_BI_run_br_t | BE1: BB.Shock_BI_run_s | BF1: BB.Shock_BI_run_t | BG1: BB.Shock_BI_s | BH1: BB.Shock_BI_t
A2: 1 | B2: 0 | C2: 1 | D2: BK1 | E2: 0 | F2: 477.125 | G2: 1631.73 | H2: 0 | I2: =E2+F2+G2+H2 -> 2108.855 | J2: 2185.24 | K2: =I2+J2 -> 4294.095 | L2: 3160.99 | M2: 0 | N2: =L2+M2 -> 3160.99 | O2: 959.6 | P2: =O2+N2 -> 4120.59 | Q2: =MAX(K2-P2,0) -> 173.505 | R2: 0 | S2: 0 | T2: 0 | U2: 0 | V2: 0 | W2: 0 | X2: 0 | Y2: 0 | Z2: 0 | AA2: 0 | AB2: =W2+X2 -> 0 | AC2: =Z2+AA2 -> 0 | AD2: =V2+AB2 -> 0 | AE2: =Y2+AC2 -> 0
C3: 2 | D3: BK2 | E3: 0 | F3: 587.693 | G3: 4303.24 | H3: 0 | I3: =E3+F3+G3+H3 -> 4890.933 | J3: 398.37 | K3: =I3+J3 -> 5289.303 | L3: 3231.37 | M3: 0 | N3: =L3+M3 -> 3231.37 | O3: 1844.24 | P3: =O3+N3 -> 5075.61 | Q3: =MAX(K3-P3,0) -> 213.693 | R3: 0 | S3: 0 | T3: 0 | U3: 0 | V3: 0 | W3: 0 | X3: 0 | Y3: 0 | Z3: 0 | AA3: 0 | AB3: =W3+X3 -> 0 | AC3: =Z3+AA3 -> 0 | AD3: =V3+AB3 -> 0 | AE3: =Y3+AC3 -> 0
C4: 3 | D4: BK3 | E4: 0 | F4: 513.847 | G4: 3379.72 | H4: 0 | I4: =E4+F4+G4+H4 -> 3893.567 | J4: 730.99 | K4: =I4+J4 -> 4624.557 | L4: 3184.36 | M4: 0 | N4: =L4+M4 -> 3184.36 | O4: 1253.34 | P4: =O4+N4 -> 4437.7 | Q4: =MAX(K4-P4,0) -> 186.857 | R4: 0 | S4: 0 | T4: 0 | U4: 0 | V4: 0 | W4: 0 | X4: 0 | Y4: 0 | Z4: 0 | AA4: 0 | AB4: =W4+X4 -> 0 | AC4: =Z4+AA4 -> 0 | AD4: =V4+AB4 -> 0 | AE4: =Y4+AC4 -> 0
C5: 4 | D5: BK4 | E5: 0 | F5: 713.662 | G5: 4351.47 | H5: 0 | I5: =E5+F5+G5+H5 -> 5065.132 | J5: 1357.75 | K5: =I5+J5 -> 6422.882 | L5: 3311.51 | M5: 0 | N5: =L5+M5 -> 3311.51 | O5: 2851.85 | P5: =O5+N5 -> 6163.36 | Q5: =MAX(K5-P5,0) -> 259.522 | R5: 0 | S5: 0 | T5: 0 | U5: 0 | V5: 0 | W5: 0 | X5: 0 | Y5: 0 | Z5: 0 | AA5: 0 | AB5: =W5+X5 -> 0 | AC5: =Z5+AA5 -> 0 | AD5: =V5+AB5 -> 0 | AE5: =Y5+AC5 -> 0
C6: 5 | D6: BK5 | E6: 0 | F6: 417.257 | G6: 620.69 | H6: 0 | I6: =E6+F6+G6+H6 -> 1037.947 | J6: 2717.39 | K6: =I6+J6 -> 3755.337 | L6: 3122.9 | M6: 0 | N6: =L6+M6 -> 3122.9 | O6: 480.71 | P6: =O6+N6 -> 3603.61 | Q6: =MAX(K6-P6,0) -> 151.727 | R6: 0 | S6: 0 | T6: 0 | U6: 0 | V6: 0 | W6: 0 | X6: 0 | Y6: 0 | Z6: 0 | AA6: 0 | AB6: =W6+X6 -> 0 | AC6: =Z6+AA6 -> 0 | AD6: =V6+AB6 -> 0 | AE6: =Y6+AC6 -> 0
E7: =SUM(E2:E6) -> 0 | F7: =SUM(F2:F6) -> 2709.584 | G7: =SUM(G2:G6) -> 14286.85 | H7: =SUM(H2:H6) -> 0 | I7: =SUM(I2:I6) -> 16996.434 | J7: =SUM(J2:J6) -> 7389.74 | K7: =SUM(K2:K6) -> 24386.174 | L7: =SUM(L2:L6) -> 16011.13 | ... AE7: =SUM(AE2:AE6) -> 0
A9: 1 | B9: 1-1 | C9: 1 | D9: BK1 | E9: 0 | F9: 477.125 | G9: 1631.73 | H9: 0 | I9: =E9+F9+G9+H9 -> 2108.855 | J9: 2185.24 | K9: =I9+J9 -> 4294.095 | L9: 3160.99 | M9: 0 | N9: =L9+M9 -> 3160.99 | O9: 959.6 | P9: =O9+N9 -> 4120.59 | Q9: =MAX(K9-P9,0) -> 173.505 | R9: 1631.73 | S9: 0 | T9: 0 | U9: 0 | V9: 0 | W9: 0 | X9: 0 | Y9: 0 | Z9: 0 | AA9: 0 | AB9: =W9+X9 -> 0 | AC9: =Z9+AA9 -> 0 | AD9: =V9+AB9 -> 0 | AE9: =Y9+AC9 -> 0
C10: 2 | D10: BK2 | E10: 0 | F10: 587.693 | G10: 4303.24 | H10: 0 | I10: =E10+F10+G10+H10 -> 4890.933 | J10: 398.37 | K10: =I10+J10 -> 5289.303 | L10: 3231.37 | M10: 0 | N10: =L10+M10 -> 3231.37 | O10: 1844.24 | P10: =O10+N10 -> 5075.61 | Q10: =MAX(K10-P10,0) -> 213.693 | R10: 0 | S10: 0 | T10: 0 | U10: 0 | V10: 0 | W10: 0 | X10: 0 | Y10: 0 | Z10: 0 | AA10: 0 | AB10: =W10+X10 -> 0 | AC10: =Z10+AA10 -> 0 | AD10: =V10+AB10 -> 0 | AE10: =Y10+AC10 -> 0
C11: 3 | D11: BK3 | E11: 0 | F11: 513.847 | G11: 3379.72 | H11: 0 | I11: =E11+F11+G11+H11 -> 3893.567 | J11: 730.99 | K11: =I11+J11 -> 4624.557 | L11: 3184.36 | M11: 0 | N11: =L11+M11 -> 3184.36 | O11: 1253.34 | P11: =O11+N11 -> 4437.7 | Q11: =MAX(K11-P11,0) -> 186.857 | R11: 0 | S11: 0 | T11: 0 | U11: 0 | V11: 0 | W11: 0 | X11: 0 | Y11: 0 | Z11: 0 | AA11: 0 | AB11: =W11+X11 -> 0 | AC11: =Z11+AA11 -> 0 | AD11: =V11+AB11 -> 0 | AE11: =Y11+AC11 -> 0
C12: 4 | D12: BK4 | E12: 0 | F12: 713.662 | G12: 4351.47 | H12: 0 | I12: =E12+F12+G12+H12 -> 5065.132 | J12: 1357.75 | K12: =I12+J12 -> 6422.882 | L12: 3311.51 | M12: 0 | N12: =L12+M12 -> 3311.51 | O12: 2851.85 | P12: =O12+N12 -> 6163.36 | Q12: =MAX(K12-P12,0) -> 259.522 | R12: 0 | S12: 0 | T12: 0 | U12: 0 | V12: 0 | W12: 0 | X12: 0 | Y12: 0 | Z12: 0 | AA12: 0 | AB12: =W12+X12 -> 0 | AC12: =Z12+AA12 -> 0 | AD12: =V12+AB12 -> 0 | AE12: =Y12+AC12 -> 0
C13: 5 | D13: BK5 | E13: 0 | F13: 417.257 | G13: 620.69 | H13: 0 | I13: =E13+F13+G13+H13 -> 1037.947 | J13: 2717.39 | K13: =I13+J13 -> 3755.337 | L13: 3122.9 | M13: 0 | N13: =L13+M13 -> 3122.9 | O13: 480.71 | P13: =O13+N13 -> 3603.61 | Q13: =MAX(K13-P13,0) -> 151.727 | R13: 0 | S13: 0 | T13: 0 | U13: 0 | V13: 0 | W13: 0 | X13: 0 | Y13: 0 | Z13: 0 | AA13: 0 | AB13: =W13+X13 -> 0 | AC13: =Z13+AA13 -> 0 | AD13: =V13+AB13 -> 0 | AE13: =Y13+AC13 -> 0
E14: =SUM(E9:E13) -> 0 | F14: =SUM(F9:F13) -> 2709.584 | G14: =SUM(G9:G13) -> 14286.85 | H14: =SUM(H9:H13) -> 0 | I14: =SUM(I9:I13) -> 16996.434 | J14: =SUM(J9:J13) -> 7389.74 | K14: =SUM(K9:K13) -> 24386.174 | L14: =SUM(L9:L13) -> 16011.13 | ... AE14: =SUM(AE9:AE13) -> 0
A16: 1 | B16: 1-2 | C16: 1 | D16: BK1 | E16: 0 | F16: 477.125 | G16: 1631.73 | H16: 0 | I16: =E16+F16+G16+H16 -> 2108.855 | J16: 2185.24 | K16: =I16+J16 -> 4294.095 | L16: 3160.99 | M16: 0 | N16: =L16+M16 -> 3160.99 | O16: 959.6 | P16: =O16+N16 -> 4120.59 | Q16: =MAX(K16-P16,0) -> 173.505 | R16: 1631.73 | S16: 0 | T16: 0 | U16: 0 | V16: 0 | W16: 0 | X16: 0 | Y16: 0 | Z16: 0 | AA16: 0 | AB16: =W16+X16 -> 0 | AC16: =Z16+AA16 -> 0 | AD16: =V16+AB16 -> 0 | AE16: =Y16+AC16 -> 0
C17: 2 | D17: BK2 | E17: 0 | F17: 587.693 | G17: 4303.24 | H17: 0 | I17: =E17+F17+G17+H17 -> 4890.933 | J17: 398.37 | K17: =I17+J17 -> 5289.303 | L17: 3231.37 | M17: 0 | N17: =L17+M17 -> 3231.37 | O17: 1844.24 | P17: =O17+N17 -> 5075.61 | Q17: =MAX(K17-P17,0) -> 213.693 | R17: 0 | S17: 0 | T17: 0 | U17: 0 | V17: 0 | W17: 0 | X17: 0 | Y17: 0 | Z17: 0 | AA17: 0 | AB17: =W17+X17 -> 0 | AC17: =Z17+AA17 -> 0 | AD17: =V17+AB17 -> 0 | AE17: =Y17+AC17 -> 0
C18: 3 | D18: BK3 | E18: 0 | F18: 513.847 | G18: 3379.72 | H18: 0 | I18: =E18+F18+G18+H18 -> 3893.567 | J18: 730.99 | K18: =I18+J18 -> 4624.557 | L18: 3184.36 | M18: 0 | N18: =L18+M18 -> 3184.36 | O18: 1253.34 | P18: =O18+N18 -> 4437.7 | Q18: =MAX(K18-P18,0) -> 186.857 | R18: 0 | S18: 0 | T18: 0 | U18: 0 | V18: 0 | W18: 0 | X18: 0 | Y18: 0 | Z18: 0 | AA18: 0 | AB18: =W18+X18 -> 0 | AC18: =Z18+AA18 -> 0 | AD18: =V18+AB18 -> 0 | AE18: =Y18+AC18 -> 0
C19: 4 | D19: BK4 | E19: 0 | F19: 713.662 | G19: 4351.47 | H19: 0 | I19: =E19+F19+G19+H19 -> 5065.132 | J19: 1357.75 | K19: =I19+J19 -> 6422.882 | L19: 3311.51 | M19: 0 | N19: =L19+M19 -> 3311.51 | O19: 2851.85 | P19: =O19+N19 -> 6163.36 | Q19: =MAX(K19-P19,0) -> 259.522 | R19: 0 | S19: 0 | T19: 0 | U19: 0 | V19: 0 | W19: 0 | X19: 0 | Y19: 0 | Z19: 0 | AA19: 0 | AB19: =W19+X19 -> 0 | AC19: =Z19+AA19 -> 0 | AD19: =V19+AB19 -> 0 | AE19: =Y19+AC19 -> 0
C20: 5 | D20: BK5 | E20: 0 | F20: 417.257 | G20: 620.69 | H20: 0 | I20: =E20+F20+G20+H20 -> 1037.947 | J20: 2717.39 | K20: =I20+J20 -> 3755.337 | L20: 3122.9 | M20: 0 | N20: =L20+M20 -> 3122.9 | O20: 480.71 | P20: =O20+N20 -> 3603.61 | Q20: =MAX(K20-P20,0) -> 151.727 | R20: 0 | S20: 0 | T20: 0 | U20: 0 | V20: 0 | W20: 0 | X20: 0 | Y20: 0 | Z20: 0 | AA20: 0 | AB20: =W20+X20 -> 0 | AC20: =Z20+AA20 -> 0 | AD20: =V20+AB20 -> 0 | AE20: =Y20+AC20 -> 0
E21: =SUM(E16:E20) -> 0 | F21: =SUM(F16:F20) -> 2709.584 | G21: =SUM(G16:G20) -> 14286.85 | H21: =SUM(H16:H20) -> 0 | I21: =SUM(I16:I20) -> 16996.434 | J21: =SUM(J16:J20) -> 7389.74 | K21: =SUM(K16:K20) -> 24386.174 | L21: =SUM(L16:L20) -> 16011.13 | ... AE21: =SUM(AE16:AE20) -> 0
A23: 1 | B23: 1-3 | C23: 1 | D23: BK1 | E23: 0 | F23: 477.125 | G23: 1631.73 | H23: 0 | I23: =E23+F23+G23+H23 -> 2108.855 | J23: 2185.24 | K23: =I23+J23 -> 4294.095 | L23: 3160.99 | M23: 0 | N23: =L23+M23 -> 3160.99 | O23: 959.6 | P23: =O23+N23 -> 4120.59 | Q23: =MAX(K23-P23,0) -> 173.505 | R23: 1631.73 | S23: 0 | T23: 0 | U23: 0 | V23: 0 | W23: 0 | X23: 0 | Y23: 0 | Z23: 0 | AA23: 0 | AB23: =W23+X23 -> 0 | AC23: =Z23+AA23 -> 0 | AD23: =V23+AB23 -> 0 | AE23: =Y23+AC23 -> 0
C24: 2 | D24: BK2 | E24: 0 | F24: 587.693 | G24: 4303.24 | H24: 0 | I24: =E24+F24+G24+H24 -> 4890.933 | J24: 398.37 | K24: =I24+J24 -> 5289.303 | L24: 3231.37 | M24: 0 | N24: =L24+M24 -> 3231.37 | O24: 1844.24 | P24: =O24+N24 -> 5075.61 | Q24: =MAX(K24-P24,0) -> 213.693 | R24: 0 | S24: 0 | T24: 0 | U24: 0 | V24: 0 | W24: 0 | X24: 0 | Y24: 0 | Z24: 0 | AA24: 0 | AB24: =W24+X24 -> 0 | AC24: =Z24+AA24 -> 0 | AD24: =V24+AB24 -> 0 | AE24: =Y24+AC24 -> 0
C25: 3 | D25: BK3 | E25: 0 | F25: 513.847 | G25: 3379.72 | H25: 0 | I25: =E25+F25+G25+H25 -> 3893.567 | J25: 730.99 | K25: =I25+J25 -> 4624.557 | L25: 3184.36 | M25: 0 | N25: =L25+M25 -> 3184.36 | O25: 1253.34 | P25: =O25+N25 -> 4437.7 | Q25: =MAX(K25-P25,0) -> 186.857 | R25: 0 | S25: 0 | T25: 0 | U25: 0 | V25: 0 | W25: 0 | X25: 0 | Y25: 0 | Z25: 0 | AA25: 0 | AB25: =W25+X25 -> 0 | AC25: =Z25+AA25 -> 0 | AD25: =V25+AB25 -> 0 | AE25: =Y25+AC25 -> 0
C26: 4 | D26: BK4 | E26: 0 | F26: 713.662 | G26: 4351.47 | H26: 0 | I26: =E26+F26+G26+H26 -> 5065.132 | J26: 1357.75 | K26: =I26+J26 -> 6422.882 | L26: 3311.51 | M26: 0 | N26: =L26+M26 -> 3311.51 | O26: 2851.85 | P26: =O26+N26 -> 6163.36 | Q26: =MAX(K26-P26,0) -> 259.522 | R26: 0 | S26: 0 | T26: 0 | U26: 0 | V26: 0 | W26: 0 | X26: 0 | Y26: 0 | Z26: 0 | AA26: 0 | AB26: =W26+X26 -> 0 | AC26: =Z26+AA26 -> 0 | AD26: =V26+AB26 -> 0 | AE26: =Y26+AC26 -> 0
C27: 5 | D27: BK5 | E27: 0 | F27: 417.257 | G27: 620.69 | H27: 0 | I27: =E27+F27+G27+H27 -> 1037.947 | J27: 2717.39 | K27: =I27+J27 -> 3755.337 | L27: 3122.9 | M27: 0 | N27: =L27+M27 -> 3122.9 | O27: 480.71 | P27: =O27+N27 -> 3603.61 | Q27: =MAX(K27-P27,0) -> 151.727 | R27: 0 | S27: 0 | T27: 0 | U27: 0 | V27: 0 | W27: 0 | X27: 0 | Y27: 0 | Z27: 0 | AA27: 0 | AB27: =W27+X27 -> 0 | AC27: =Z27+AA27 -> 0 | AD27: =V27+AB27 -> 0 | AE27: =Y27+AC27 -> 0
E28: =SUM(E23:E27) -> 0 | F28: =SUM(F23:F27) -> 2709.584 | G28: =SUM(G23:G27) -> 14286.85 | H28: =SUM(H23:H27) -> 0 | I28: =SUM(I23:I27) -> 16996.434 | J28: =SUM(J23:J27) -> 7389.74 | K28: =SUM(K23:K27) -> 24386.174 | L28: =SUM(L23:L27) -> 16011.13 | ... AE28: =SUM(AE23:AE27) -> 0
A30: 1 | B30: 2-0 | C30: 1 | D30: BK1 | E30: 0 | F30: 477.125 | G30: 1631.73 | H30: 0 | I30: =E30+F30+G30+H30 -> 2108.855 | J30: 2185.24 | K30: =I30+J30 -> 4294.095 | L30: 3160.99 | M30: 0 | N30: =L30+M30 -> 3160.99 | O30: 959.6 | P30: =O30+N30 -> 4120.59 | Q30: =MAX(K30-P30,0) -> 173.505 | R30: 1631.73 | S30: 0 | T30: 0 | U30: 0 | V30: 0 | W30: 0 | X30: 0 | Y30: 0 | Z30: 0 | AA30: 0 | AB30: =W30+X30 -> 0 | AC30: =Z30+AA30 -> 0 | AD30: =V30+AB30 -> 0 | AE30: =Y30+AC30 -> 0
C31: 2 | D31: BK2 | E31: 0 | F31: 587.693 | G31: 4303.24 | H31: 0 | I31: =E31+F31+G31+H31 -> 4890.933 | J31: 398.37 | K31: =I31+J31 -> 5289.303 | L31: 3231.37 | M31: 0 | N31: =L31+M31 -> 3231.37 | O31: 1844.24 | P31: =O31+N31 -> 5075.61 | Q31: =MAX(K31-P31,0) -> 213.693 | R31: 0 | S31: 0 | T31: 0 | U31: 0 | V31: 0 | W31: 0 | X31: 0 | Y31: 0 | Z31: 0 | AA31: 0 | AB31: =W31+X31 -> 0 | AC31: =Z31+AA31 -> 0 | AD31: =V31+AB31 -> 0 | AE31: =Y31+AC31 -> 0
C32: 3 | D32: BK3 | E32: 0 | F32: 513.847 | G32: 3379.72 | H32: 0 | I32: =E32+F32+G32+H32 -> 3893.567 | J32: 730.99 | K32: =I32+J32 -> 4624.557 | L32: 3184.36 | M32: 0 | N32: =L32+M32 -> 3184.36 | O32: 1253.34 | P32: =O32+N32 -> 4437.7 | Q32: =MAX(K32-P32,0) -> 186.857 | R32: 0 | S32: 0 | T32: 0 | U32: 0 | V32: 0 | W32: 0 | X32: 0 | Y32: 0 | Z32: 0 | AA32: 0 | AB32: =W32+X32 -> 0 | AC32: =Z32+AA32 -> 0 | AD32: =V32+AB32 -> 0 | AE32: =Y32+AC32 -> 0
C33: 4 | D33: BK4 | E33: 0 | F33: 713.662 | G33: 4351.47 | H33: 0 | I33: =E33+F33+G33+H33 -> 5065.132 | J33: 1357.75 | K33: =I33+J33 -> 6422.882 | L33: 3311.51 | M33: 0 | N33: =L33+M33 -> 3311.51 | O33: 2851.85 | P33: =O33+N33 -> 6163.36 | Q33: =MAX(K33-P33,0) -> 259.522 | R33: 0 | S33: 0 | T33: 0 | U33: 0 | V33: 0 | W33: 0 | X33: 0 | Y33: 0 | Z33: 0 | AA33: 0 | AB33: =W33+X33 -> 0 | AC33: =Z33+AA33 -> 0 | AD33: =V33+AB33 -> 0 | AE33: =Y33+AC33 -> 0
C34: 5 | D34: BK5 | E34: 0 | F34: 417.257 | G34: 620.69 | H34: 0 | I34: =E34+F34+G34+H34 -> 1037.947 | J34: 2717.39 | K34: =I34+J34 -> 3755.337 | L34: 3122.9 | M34: 0 | N34: =L34+M34 -> 3122.9 | O34: 480.71 | P34: =O34+N34 -> 3603.61 | Q34: =MAX(K34-P34,0) -> 151.727 | R34: 0 | S34: 0 | T34: 0 | U34: 0 | V34: 0 | W34: 0 | X34: 0 | Y34: 0 | Z34: 0 | AA34: 0 | AB34: =W34+X34 -> 0 | AC34: =Z34+AA34 -> 0 | AD34: =V34+AB34 -> 0 | AE34: =Y34+AC34 -> 0
E35: =SUM(E30:E34) -> 0 | F35: =SUM(F30:F34) -> 2709.584 | G35: =SUM(G30:G34) -> 14286.85 | H35: =SUM(H30:H34) -> 0 | I35: =SUM(I30:I34) -> 16996.434 | J35: =SUM(J30:J34) -> 7389.74 | K35: =SUM(K30:K34) -> 24386.174 | L35: =SUM(L30:L34) -> 16011.13 | ... AE35: =SUM(AE30:AE34) -> 0
A37: 1 | B37: 2-1 | C37: 1 | D37: BK1 | E37: 0 | F37: 477.125 | G37: 0 | H37: 0 | I37: =E37+F37+G37+H37 -> 477.125 | J37: 2185.24 | K37: =I37+J37 -> 2662.365 | L37: 2042.355 | M37: 0 | N37: =L37+M37 -> 2042.355 | O37: 620.009 | P37: =O37+N37 -> 2662.364 | Q37: 0 | R37: 339.599 | S37: 0 | T37: 0 | U37: 1118.6423 | V37: 339.6 | W37: 0 | X37: 0 | Y37: 0 | Z37: 0 | AA37: 0 | AB37: =W37+X37 -> 0 | AC37: =Z37+AA37 -> 0 | AD37: =V37+AB37 -> 339.6 | AE37: =Y37+AC37 -> 0
C38: 2 | D38: BK2 | E38: 0 | F38: 587.693 | G38: 4303.24 | H38: 0 | I38: =E38+F38+G38+H38 -> 4890.933 | J38: 398.37 | K38: =I38+J38 -> 5289.303 | L38: 3231.37 | M38: 0 | N38: =L38+M38 -> 3231.37 | O38: 1844.24 | P38: =O38+N38 -> 5075.61 | Q38: 213.693 | R38: 0 | S38: 0 | T38: 0 | U38: 0 | V38: 0 | W38: 0 | X38: 0 | Y38: 0 | Z38: 0 | AA38: 0 | AB38: =W38+X38 -> 0 | AC38: =Z38+AA38 -> 0 | AD38: =V38+AB38 -> 0 | AE38: =Y38+AC38 -> 0
C39: 3 | D39: BK3 | E39: 0 | F39: 513.847 | G39: 3379.72 | H39: 0 | I39: =E39+F39+G39+H39 -> 3893.567 | J39: 730.99 | K39: =I39+J39 -> 4624.557 | L39: 3184.36 | M39: 0 | N39: =L39+M39 -> 3184.36 | O39: 1253.34 | P39: =O39+N39 -> 4437.7 | Q39: 186.857 | R39: 0 | S39: 0 | T39: 0 | U39: 0 | V39: 0 | W39: 0 | X39: 0 | Y39: 0 | Z39: 0 | AA39: 0 | AB39: =W39+X39 -> 0 | AC39: =Z39+AA39 -> 0 | AD39: =V39+AB39 -> 0 | AE39: =Y39+AC39 -> 0
C40: 4 | D40: BK4 | E40: 0 | F40: 713.662 | G40: 4351.47 | H40: 0 | I40: =E40+F40+G40+H40 -> 5065.132 | J40: 1357.75 | K40: =I40+J40 -> 6422.882 | L40: 3311.51 | M40: 0 | N40: =L40+M40 -> 3311.51 | O40: 2851.85 | P40: =O40+N40 -> 6163.36 | Q40: 259.522 | R40: 0 | S40: 0 | T40: 0 | U40: 0 | V40: 0 | W40: 0 | X40: 0 | Y40: 0 | Z40: 0 | AA40: 0 | AB40: =W40+X40 -> 0 | AC40: =Z40+AA40 -> 0 | AD40: =V40+AB40 -> 0 | AE40: =Y40+AC40 -> 0
C41: 5 | D41: BK5 | E41: 0 | F41: 417.257 | G41: 620.69 | H41: 0 | I41: =E41+F41+G41+H41 -> 1037.947 | J41: 2717.39 | K41: =I41+J41 -> 3755.337 | L41: 3122.9 | M41: 0 | N41: =L41+M41 -> 3122.9 | O41: 480.71 | P41: =O41+N41 -> 3603.61 | Q41: 151.727 | R41: 0 | S41: 0 | T41: 0 | U41: 0 | V41: 0 | W41: 0 | X41: 0 | Y41: 0 | Z41: 0 | AA41: 0 | AB41: =W41+X41 -> 0 | AC41: =Z41+AA41 -> 0 | AD41: =V41+AB41 -> 0 | AE41: =Y41+AC41 -> 0
E42: =SUM(E37:E41) -> 0 | F42: =SUM(F37:F41) -> 2709.584 | G42: =SUM(G37:G41) -> 12655.12 | H42: =SUM(H37:H41) -> 0 | I42: =SUM(I37:I41) -> 15364.704 | J42: =SUM(J37:J41) -> 7389.74 | K42: =SUM(K37:K41) -> 22754.444 | L42: =SUM(L37:L41) -> 14892.495 | ... AE42: =SUM(AE37:AE41) -> 0
A44: 1 | B44: 2-2 | C44: 1 | D44: BK1 | E44: 0 | F44: 477.125 | G44: 0 | H44: 0 | I44: =E44+F44+G44+H44 -> 477.125 | J44: 2185.24 | K44: =I44+J44 -> 2662.365 | L44: 2042.355 | M44: 0 | N44: =L44+M44 -> 2042.355 | O44: 620.009 | P44: =O44+N44 -> 2662.364 | Q44: 0 | R44: 339.599 | S44: 0 | T44: 0 | U44: 1118.6423 | V44: 339.6 | W44: 0 | X44: 0 | Y44: 0 | Z44: 0 | AA44: 0 | AB44: =W44+X44 -> 0 | AC44: =Z44+AA44 -> 0 | AD44: =V44+AB44 -> 339.6 | AE44: =Y44+AC44 -> 0
C45: 2 | D45: BK2 | E45: 0 | F45: 587.693 | G45: 4303.24 | H45: 0 | I45: =E45+F45+G45+H45 -> 4890.933 | J45: 398.37 | K45: =I45+J45 -> 5289.303 | L45: 3231.37 | M45: 0 | N45: =L45+M45 -> 3231.37 | O45: 1844.24 | P45: =O45+N45 -> 5075.61 | Q45: 213.693 | R45: 0 | S45: 0 | T45: 0 | U45: 0 | V45: 0 | W45: 0 | X45: 0 | Y45: 0 | Z45: 0 | AA45: 0 | AB45: =W45+X45 -> 0 | AC45: =Z45+AA45 -> 0 | AD45: =V45+AB45 -> 0 | AE45: =Y45+AC45 -> 0
C46: 3 | D46: BK3 | E46: 0 | F46: 513.847 | G46: 3379.72 | H46: 0 | I46: =E46+F46+G46+H46 -> 3893.567 | J46: 730.99 | K46: =I46+J46 -> 4624.557 | L46: 3184.36 | M46: 0 | N46: =L46+M46 -> 3184.36 | O46: 1253.34 | P46: =O46+N46 -> 4437.7 | Q46: 186.857 | R46: 0 | S46: 0 | T46: 0 | U46: 0 | V46: 0 | W46: 0 | X46: 0 | Y46: 0 | Z46: 0 | AA46: 0 | AB46: =W46+X46 -> 0 | AC46: =Z46+AA46 -> 0 | AD46: =V46+AB46 -> 0 | AE46: =Y46+AC46 -> 0
C47: 4 | D47: BK4 | E47: 0 | F47: 713.662 | G47: 4351.47 | H47: 0 | I47: =E47+F47+G47+H47 -> 5065.132 | J47: 1357.75 | K47: =I47+J47 -> 6422.882 | L47: 3311.51 | M47: 0 | N47: =L47+M47 -> 3311.51 | O47: 2851.85 | P47: =O47+N47 -> 6163.36 | Q47: 259.522 | R47: 0 | S47: 0 | T47: 0 | U47: 0 | V47: 0 | W47: 0 | X47: 0 | Y47: 0 | Z47: 0 | AA47: 0 | AB47: =W47+X47 -> 0 | AC47: =Z47+AA47 -> 0 | AD47: =V47+AB47 -> 0 | AE47: =Y47+AC47 -> 0
C48: 5 | D48: BK5 | E48: 0 | F48: 417.257 | G48: 620.69 | H48: 0 | I48: =E48+F48+G48+H48 -> 1037.947 | J48: 2717.39 | K48: =I48+J48 -> 3755.337 | L48: 3122.9 | M48: 0 | N48: =L48+M48 -> 3122.9 | O48: 480.71 | P48: =O48+N48 -> 3603.61 | Q48: 151.727 | R48: 0 | S48: 0 | T48: 0 | U48: 0 | V48: 0 | W48: 0 | X48: 0 | Y48: 0 | Z48: 0 | AA48: 0 | AB48: =W48+X48 -> 0 | AC48: =Z48+AA48 -> 0 | AD48: =V48+AB48 -> 0 | AE48: =Y48+AC48 -> 0
E49: =SUM(E44:E48) -> 0 | F49: =SUM(F44:F48) -> 2709.584 | G49: =SUM(G44:G48) -> 12655.12 | H49: =SUM(H44:H48) -> 0 | I49: =SUM(I44:I48) -> 15364.704 | J49: =SUM(J44:J48) -> 7389.74 | K49: =SUM(K44:K48) -> 22754.444 | L49: =SUM(L44:L48) -> 14892.495 | ... AE49: =SUM(AE44:AE48) -> 0
A51: 1 | B51: 3 | C51: 1 | D51: BK1 | E51: 0 | F51: 477.125 | G51: 0 | H51: 0 | I51: =E51+F51+G51+H51 -> 477.125 | J51: 2185.24 | K51: =I51+J51 -> 2662.365 | L51: 2042.355 | M51: 0 | N51: =L51+M51 -> 2042.355 | O51: 620.009 | P51: =O51+N51 -> 2662.364 | Q51: 0 | R51: 339.599 | S51: 0 | T51: 0 | U51: 1118.6423 | V51: 339.6 | W51: 0 | X51: 2185.24 | Y51: 0 | Z51: 0 | AA51: 0 | AB51: =W51+X51 -> 2185.24 | AC51: =Z51+AA51 -> 0 | AD51: =V51+AB51 -> 2524.84 | AE51: =Y51+AC51 -> 0
C52: 2 | D52: BK2 | E52: 0 | F52: 587.693 | G52: 4303.24 | H52: 0 | I52: =E52+F52+G52+H52 -> 4890.933 | J52: 398.37 | K52: =I52+J52 -> 5289.303 | L52: 3231.37 | M52: 0 | N52: =L52+M52 -> 3231.37 | O52: 1844.24 | P52: =O52+N52 -> 5075.61 | Q52: 213.693 | R52: 0 | S52: 0 | T52: 0 | U52: 0 | V52: 0 | W52: 0 | X52: 0 | Y52: 0 | Z52: 0 | AA52: 0 | AB52: =W52+X52 -> 0 | AC52: =Z52+AA52 -> 0 | AD52: =V52+AB52 -> 0 | AE52: =Y52+AC52 -> 0
C53: 3 | D53: BK3 | E53: 0 | F53: 513.847 | G53: 3379.72 | H53: 0 | I53: =E53+F53+G53+H53 -> 3893.567 | J53: 730.99 | K53: =I53+J53 -> 4624.557 | L53: 3184.36 | M53: 0 | N53: =L53+M53 -> 3184.36 | O53: 1253.34 | P53: =O53+N53 -> 4437.7 | Q53: 186.857 | R53: 0 | S53: 0 | T53: 0 | U53: 0 | V53: 0 | W53: 0 | X53: 0 | Y53: 0 | Z53: 0 | AA53: 0 | AB53: =W53+X53 -> 0 | AC53: =Z53+AA53 -> 0 | AD53: =V53+AB53 -> 0 | AE53: =Y53+AC53 -> 0
C54: 4 | D54: BK4 | E54: 0 | F54: 713.662 | G54: 4351.47 | H54: 0 | I54: =E54+F54+G54+H54 -> 5065.132 | J54: 1357.75 | K54: =I54+J54 -> 6422.882 | L54: 3311.51 | M54: 0 | N54: =L54+M54 -> 3311.51 | O54: 2851.85 | P54: =O54+N54 -> 6163.36 | Q54: 259.522 | R54: 0 | S54: 0 | T54: 0 | U54: 0 | V54: 0 | W54: 0 | X54: 0 | Y54: 0 | Z54: 0 | AA54: 0 | AB54: =W54+X54 -> 0 | AC54: =Z54+AA54 -> 0 | AD54: =V54+AB54 -> 0 | AE54: =Y54+AC54 -> 0
C55: 5 | D55: BK5 | E55: 0 | F55: 417.257 | G55: 620.69 | H55: 0 | I55: =E55+F55+G55+H55 -> 1037.947 | J55: 2717.39 | K55: =I55+J55 -> 3755.337 | L55: 3122.9 | M55: 0 | N55: =L55+M55 -> 3122.9 | O55: 480.71 | P55: =O55+N55 -> 3603.61 | Q55: 151.727 | R55: 0 | S55: 0 | T55: 0 | U55: 0 | V55: 0 | W55: 0 | X55: 0 | Y55: 0 | Z55: 0 | AA55: 0 | AB55: =W55+X55 -> 0 | AC55: =Z55+AA55 -> 0 | AD55: =V55+AB55 -> 0 | AE55: =Y55+AC55 -> 0
E56: =SUM(E51:E55) -> 0 | F56: =SUM(F51:F55) -> 2709.584 | G56: =SUM(G51:G55) -> 12655.12 | H56: =SUM(H51:H55) -> 0 | I56: =SUM(I51:I55) -> 15364.704 | J56: =SUM(J51:J55) -> 7389.74 | K56: =SUM(K51:K55) -> 22754.444 | L56: =SUM(L51:L55) -> 14892.495 | ... AE56: =SUM(AE51:AE55) -> 0
A58: 2 | B58: 0 | C58: 1 | D58: BK1 | E58: 0 | F58: 477.125 | G58: 0 | H58: 0 | I58: =E58+F58+G58+H58 -> 477.125 | J58: 2185.24 | K58: =I58+J58 -> 2662.365 | L58: 2042.355 | M58: 0 | N58: =L58+M58 -> 2042.355 | O58: 620.001 | P58: =O58+N58 -> 2662.356 | Q58: 0 | R58: 0 | S58: 0 | T58: 0 | U58: 0 | V58: 339.599 | W58: 0 | X58: 2185.24 | Y58: 0 | Z58: 0 | AA58: 0 | AB58: =W58+X58 -> 2185.24 | AC58: =Z58+AA58 -> 0 | AD58: =V58+AB58 -> 2524.839 | AE58: =Y58+AC58 -> 0
C59: 2 | D59: BK2 | E59: 0 | F59: 587.693 | G59: 4303.24 | H59: 0 | I59: =E59+F59+G59+H59 -> 4890.933 | J59: 398.37 | K59: =I59+J59 -> 5289.303 | L59: 3231.37 | M59: 0 | N59: =L59+M59 -> 3231.37 | O59: 1844.24 | P59: =O59+N59 -> 5075.61 | Q59: 213.693 | R59: 0 | S59: 0 | T59: 0 | U59: 0 | V59: 0 | W59: 0 | X59: 0 | Y59: 0 | Z59: 0 | AA59: 0 | AB59: =W59+X59 -> 0 | AC59: =Z59+AA59 -> 0 | AD59: =V59+AB59 -> 0 | AE59: =Y59+AC59 -> 0
C60: 3 | D60: BK3 | E60: 0 | F60: 513.847 | G60: 3379.72 | H60: 0 | I60: =E60+F60+G60+H60 -> 3893.567 | J60: 730.99 | K60: =I60+J60 -> 4624.557 | L60: 3184.36 | M60: 0 | N60: =L60+M60 -> 3184.36 | O60: 1253.34 | P60: =O60+N60 -> 4437.7 | Q60: 186.857 | R60: 0 | S60: 0 | T60: 0 | U60: 0 | V60: 0 | W60: 0 | X60: 0 | Y60: 0 | Z60: 0 | AA60: 0 | AB60: =W60+X60 -> 0 | AC60: =Z60+AA60 -> 0 | AD60: =V60+AB60 -> 0 | AE60: =Y60+AC60 -> 0
C61: 4 | D61: BK4 | E61: 0 | F61: 713.662 | G61: 4351.47 | H61: 0 | I61: =E61+F61+G61+H61 -> 5065.132 | J61: 1357.75 | K61: =I61+J61 -> 6422.882 | L61: 3311.51 | M61: 0 | N61: =L61+M61 -> 3311.51 | O61: 2851.85 | P61: =O61+N61 -> 6163.36 | Q61: 259.522 | R61: 0 | S61: 0 | T61: 0 | U61: 0 | V61: 0 | W61: 0 | X61: 0 | Y61: 0 | Z61: 0 | AA61: 0 | AB61: =W61+X61 -> 0 | AC61: =Z61+AA61 -> 0 | AD61: =V61+AB61 -> 0 | AE61: =Y61+AC61 -> 0
C62: 5 | D62: BK5 | E62: 0 | F62: 417.257 | G62: 620.69 | H62: 0 | I62: =E62+F62+G62+H62 -> 1037.947 | J62: 2717.39 | K62: =I62+J62 -> 3755.337 | L62: 3122.9 | M62: 0 | N62: =L62+M62 -> 3122.9 | O62: 480.71 | P62: =O62+N62 -> 3603.61 | Q62: 151.727 | R62: 0 | S62: 0 | T62: 0 | U62: 0 | V62: 0 | W62: 0 | X62: 0 | Y62: 0 | Z62: 0 | AA62: 0 | AB62: =W62+X62 -> 0 | AC62: =Z62+AA62 -> 0 | AD62: =V62+AB62 -> 0 | AE62: =Y62+AC62 -> 0
E63: =SUM(E58:E62) -> 0 | F63: =SUM(F58:F62) -> 2709.584 | G63: =SUM(G58:G62) -> 12655.12 | H63: =SUM(H58:H62) -> 0 | I63: =SUM(I58:I62) -> 15364.704 | J63: =SUM(J58:J62) -> 7389.74 | K63: =SUM(K58:K62) -> 22754.444 | L63: =SUM(L58:L62) -> 14892.495 | ... AE63: =SUM(AE58:AE62) -> 0
A65: 2 | B65: 1-1 | C65: 1 | D65: BK1 | E65: 0 | F65: 477.125 | G65: 0 | H65: 0 | I65: =E65+F65+G65+H65 -> 477.125 | J65: 2185.24 | K65: =I65+J65 -> 2662.365 | L65: 2042.355 | M65: 0 | N65: =L65+M65 -> 2042.355 | O65: 620.009 | P65: =O65+N65 -> 2662.364 | Q65: 0 | R65: 0 | S65: 0 | T65: 0 | U65: 0 | V65: 339.599 | W65: 0 | X65: 2185.24 | Y65: 0 | Z65: 0 | AA65: 0 | AB65: =W65+X65 -> 2185.24 | AC65: =Z65+AA65 -> 0 | AD65: =V65+AB65 -> 2524.839 | AE65: =Y65+AC65 -> 0
C66: 2 | D66: BK2 | E66: 0 | F66: 587.693 | G66: 4303.24 | H66: 0 | I66: =E66+F66+G66+H66 -> 4890.933 | J66: 398.37 | K66: =I66+J66 -> 5289.303 | L66: 3231.37 | M66: 0 | N66: =L66+M66 -> 3231.37 | O66: 1844.24 | P66: =O66+N66 -> 5075.61 | Q66: 213.693 | R66: 38.698 | S66: 0 | T66: 0 | U66: 0 | V66: 0 | W66: 0 | X66: 0 | Y66: 38.698 | Z66: 0 | AA66: 0 | AB66: =W66+X66 -> 0 | AC66: =Z66+AA66 -> 0 | AD66: =V66+AB66 -> 0 | AE66: =Y66+AC66 -> 38.698
C67: 3 | D67: BK3 | E67: 0 | F67: 513.847 | G67: 3379.72 | H67: 0 | I67: =E67+F67+G67+H67 -> 3893.567 | J67: 730.99 | K67: =I67+J67 -> 4624.557 | L67: 3184.36 | M67: 0 | N67: =L67+M67 -> 3184.36 | O67: 1253.34 | P67: =O67+N67 -> 4437.7 | Q67: 186.857 | R67: 258.688 | S67: 0 | T67: 0 | U67: 0 | V67: 0 | W67: 0 | X67: 0 | Y67: 258.688 | Z67: 0 | AA67: 0 | AB67: =W67+X67 -> 0 | AC67: =Z67+AA67 -> 0 | AD67: =V67+AB67 -> 0 | AE67: =Y67+AC67 -> 258.688
C68: 4 | D68: BK4 | E68: 0 | F68: 713.662 | G68: 4351.47 | H68: 0 | I68: =E68+F68+G68+H68 -> 5065.132 | J68: 1357.75 | K68: =I68+J68 -> 6422.882 | L68: 3311.51 | M68: 0 | N68: =L68+M68 -> 3311.51 | O68: 2851.85 | P68: =O68+N68 -> 6163.36 | Q68: 259.522 | R68: 42.205 | S68: 0 | T68: 0 | U68: 0 | V68: 0 | W68: 0 | X68: 0 | Y68: 42.205 | Z68: 0 | AA68: 0 | AB68: =W68+X68 -> 0 | AC68: =Z68+AA68 -> 0 | AD68: =V68+AB68 -> 0 | AE68: =Y68+AC68 -> 42.205
C69: 5 | D69: BK5 | E69: 0 | F69: 417.257 | G69: 620.69 | H69: 0 | I69: =E69+F69+G69+H69 -> 1037.947 | J69: 2717.39 | K69: =I69+J69 -> 3755.337 | L69: 3122.9 | M69: 0 | N69: =L69+M69 -> 3122.9 | O69: 480.71 | P69: =O69+N69 -> 3603.61 | Q69: 151.727 | R69: 0 | S69: 0 | T69: 0 | U69: 0 | V69: 0 | W69: 0 | X69: 0 | Y69: 0 | Z69: 0 | AA69: 0 | AB69: =W69+X69 -> 0 | AC69: =Z69+AA69 -> 0 | AD69: =V69+AB69 -> 0 | AE69: =Y69+AC69 -> 0
E70: =SUM(E65:E69) -> 0 | F70: =SUM(F65:F69) -> 2709.584 | G70: =SUM(G65:G69) -> 12655.12 | H70: =SUM(H65:H69) -> 0 | I70: =SUM(I65:I69) -> 15364.704 | J70: =SUM(J65:J69) -> 7389.74 | K70: =SUM(K65:K69) -> 22754.444 | L70: =SUM(L65:L69) -> 14892.495 | ... AE70: =SUM(AE65:AE69) -> 339.591
A72: 2 | B72: 1-3 | C72: 1 | D72: BK1 | E72: 0 | F72: 477.125 | G72: 0 | H72: 0 | I72: =E72+F72+G72+H72 -> 477.125 | J72: 2185.24 | K72: =J72+I72 -> 2662.365 | L72: 2042.355 | M72: 0 | N72: =L72+M72 -> 2042.355 | O72: 620.009 | P72: =O72+N72 -> 2662.364 | Q72: 0 | R72: 0 | S72: 0 | T72: 0 | U72: 0 | V72: 339.599 | W72: 0 | X72: 2185.24 | Y72: 0 | Z72: 0 | AA72: 0 | AB72: =W72+X72 -> 2185.24 | AC72: =Z72+AA72 -> 0 | AD72: =V72+AB72 -> 2524.839 | AE72: =Y72+AC72 -> 0
C73: 2 | D73: BK2 | E73: 0 | F73: 587.693 | G73: 4303.24 | H73: 0 | I73: =E73+F73+G73+H73 -> 4890.933 | J73: 398.37 | K73: =J73+I73 -> 5289.303 | L73: 3231.37 | M73: 0 | N73: =L73+M73 -> 3231.37 | O73: 1844.24 | P73: =O73+N73 -> 5075.61 | Q73: 213.693 | R73: 38.698 | S73: 1728.55 | T73: 0 | U73: 0 | V73: 0 | W73: 0 | X73: 0 | Y73: 38.698 | Z73: 0 | AA73: 1728.55 | AB73: =W73+X73 -> 0 | AC73: =Z73+AA73 -> 1728.55 | AD73: =V73+AB73 -> 0 | AE73: =Y73+AC73 -> 1767.248
C74: 3 | D74: BK3 | E74: 0 | F74: 513.847 | G74: 3379.72 | H74: 0 | I74: =E74+F74+G74+H74 -> 3893.567 | J74: 730.99 | K74: =J74+I74 -> 4624.557 | L74: 3184.36 | M74: 0 | N74: =L74+M74 -> 3184.36 | O74: 1253.34 | P74: =O74+N74 -> 4437.7 | Q74: 186.857 | R74: 258.688 | S74: 0 | T74: 0 | U74: 0 | V74: 0 | W74: 0 | X74: 0 | Y74: 258.688 | Z74: 0 | AA74: 0 | AB74: =W74+X74 -> 0 | AC74: =Z74+AA74 -> 0 | AD74: =V74+AB74 -> 0 | AE74: =Y74+AC74 -> 258.688
C75: 4 | D75: BK4 | E75: 0 | F75: 713.662 | G75: 4351.47 | H75: 0 | I75: =E75+F75+G75+H75 -> 5065.132 | J75: 1357.75 | K75: =J75+I75 -> 6422.882 | L75: 3311.51 | M75: 0 | N75: =L75+M75 -> 3311.51 | O75: 2851.85 | P75: =O75+N75 -> 6163.36 | Q75: 259.522 | R75: 42.205 | S75: 134.46 | T75: 0 | U75: 0 | V75: 0 | W75: 0 | X75: 0 | Y75: 42.205 | Z75: 0 | AA75: 134.46 | AB75: =W75+X75 -> 0 | AC75: =Z75+AA75 -> 134.46 | AD75: =V75+AB75 -> 0 | AE75: =Y75+AC75 -> 176.665
C76: 5 | D76: BK5 | E76: 0 | F76: 417.257 | G76: 620.69 | H76: 0 | I76: =E76+F76+G76+H76 -> 1037.947 | J76: 2717.39 | K76: =J76+I76 -> 3755.337 | L76: 3122.9 | M76: 0 | N76: =L76+M76 -> 3122.9 | O76: 480.71 | P76: =O76+N76 -> 3603.61 | Q76: 151.727 | R76: 0 | S76: 322.23 | T76: 0 | U76: 0 | V76: 0 | W76: 0 | X76: 0 | Y76: 0 | Z76: 0 | AA76: 322.23 | AB76: =W76+X76 -> 0 | AC76: =Z76+AA76 -> 322.23 | AD76: =V76+AB76 -> 0 | AE76: =Y76+AC76 -> 322.23
E77: =SUM(E72:E76) -> 0 | F77: =SUM(F72:F76) -> 2709.584 | G77: =SUM(G72:G76) -> 12655.12 | H77: =SUM(H72:H76) -> 0 | I77: =SUM(I72:I76) -> 15364.704 | J77: =SUM(J72:J76) -> 7389.74 | K77: =SUM(K72:K76) -> 22754.444 | L77: =SUM(L72:L76) -> 14892.495 | ... AE77: =SUM(AE72:AE76) -> 2524.831
A79: 2 | B79: 2-0 | C79: 1 | D79: BK1 | E79: 0 | F79: 477.125 | G79: 0 | H79: 0 | I79: =E79+F79+G79+H79 -> 477.125 | J79: 2185.24 | K79: =J79+I79 -> 2662.365 | L79: 2042.355 | M79: 0 | N79: =L79+M79 -> 2042.355 | O79: 620.009 | P79: =O79+N79 -> 2662.364 | Q79: 0 | R79: 0 | S79: 0 | T79: 0 | U79: 0 | V79: 0 | W79: 0 | X79: 0 | Y79: 0 | Z79: 0 | AA79: 0 | AB79: =W79+X79 -> 0 | AC79: =Z79+AA79 -> 0 | AD79: =V79+AB79 -> 0 | AE79: =Y79+AC79 -> 0
C80: 2 | D80: BK2 | E80: 0 | F80: 587.693 | G80: 4303.24 | H80: 0 | I80: =E80+F80+G80+H80 -> 4890.933 | J80: 398.37 | K80: =J80+I80 -> 5289.303 | L80: 3231.37 | M80: 0 | N80: =L80+M80 -> 3231.37 | O80: 1844.24 | P80: =O80+N80 -> 5075.61 | Q80: 213.693 | R80: 38.698 | S80: 1728.55 | T80: 0 | U80: 0 | V80: 0 | W80: 0 | X80: 0 | Y80: 0 | Z80: 0 | AA80: 0 | AB80: =W80+X80 -> 0 | AC80: =Z80+AA80 -> 0 | AD80: =V80+AB80 -> 0 | AE80: =Y80+AC80 -> 0
C81: 3 | D81: BK3 | E81: 0 | F81: 513.847 | G81: 3379.72 | H81: 0 | I81: =E81+F81+G81+H81 -> 3893.567 | J81: 730.99 | K81: =J81+I81 -> 4624.557 | L81: 3184.36 | M81: 0 | N81: =L81+M81 -> 3184.36 | O81: 1253.34 | P81: =O81+N81 -> 4437.7 | Q81: 186.857 | R81: 258.688 | S81: 0 | T81: 0 | U81: 0 | V81: 0 | W81: 0 | X81: 0 | Y81: 0 | Z81: 0 | AA81: 0 | AB81: =W81+X81 -> 0 | AC81: =Z81+AA81 -> 0 | AD81: =V81+AB81 -> 0 | AE81: =Y81+AC81 -> 0
C82: 4 | D82: BK4 | E82: 0 | F82: 713.662 | G82: 4351.47 | H82: 0 | I82: =E82+F82+G82+H82 -> 5065.132 | J82: 1357.75 | K82: =J82+I82 -> 6422.882 | L82: 3311.51 | M82: 0 | N82: =L82+M82 -> 3311.51 | O82: 2851.85 | P82: =O82+N82 -> 6163.36 | Q82: 259.522 | R82: 42.205 | S82: 134.46 | T82: 0 | U82: 0 | V82: 0 | W82: 0 | X82: 0 | Y82: 0 | Z82: 0 | AA82: 0 | AB82: =W82+X82 -> 0 | AC82: =Z82+AA82 -> 0 | AD82: =V82+AB82 -> 0 | AE82: =Y82+AC82 -> 0
C83: 5 | D83: BK5 | E83: 0 | F83: 417.257 | G83: 620.69 | H83: 0 | I83: =E83+F83+G83+H83 -> 1037.947 | J83: 2717.39 | K83: =J83+I83 -> 3755.337 | L83: 3122.9 | M83: 0 | N83: =L83+M83 -> 3122.9 | O83: 480.71 | P83: =O83+N83 -> 3603.61 | Q83: 151.727 | R83: 0 | S83: 322.23 | T83: 0 | U83: 0 | V83: 0 | W83: 0 | X83: 0 | Y83: 0 | Z83: 0 | AA83: 0 | AB83: =W83+X83 -> 0 | AC83: =Z83+AA83 -> 0 | AD83: =V83+AB83 -> 0 | AE83: =Y83+AC83 -> 0
E84: =SUM(E79:E83) -> 0 | F84: =SUM(F79:F83) -> 2709.584 | G84: =SUM(G79:G83) -> 12655.12 | H84: =SUM(H79:H83) -> 0 | I84: =SUM(I79:I83) -> 15364.704 | J84: =SUM(J79:J83) -> 7389.74 | K84: =SUM(K79:K83) -> 22754.444 | L84: =SUM(L79:L83) -> 14892.495 | ... AE84: =SUM(AE79:AE83) -> 0
A86: 2 | B86: 2-1 | C86: 1 | D86: BK1 | E86: 0 | F86: 477.125 | G86: 0 | H86: 0 | I86: =E86+F86+G86+H86 -> 477.125 | J86: 2185.24 | K86: =J86+I86 -> 2662.365 | L86: 2042.355 | M86: 0 | N86: =L86+M86 -> 2042.355 | O86: 620.009 | P86: =O86+N86 -> 2662.364 | Q86: 0 | R86: 0 | S86: 0 | T86: 0 | U86: 0 | V86: 0 | W86: 0 | X86: 0 | Y86: 0 | Z86: 0 | AA86: 0 | AB86: =W86+X86 -> 0 | AC86: =Z86+AA86 -> 0 | AD86: =V86+AB86 -> 0 | AE86: =Y86+AC86 -> 0
C87: 2 | D87: BK2 | E87: 0 | F87: 587.693 | G87: 4303.24 | H87: 0 | I87: =E87+F87+G87+H87 -> 4890.933 | J87: 359.67215 | K87: =J87+I87 -> 5250.6052 | L87: 3231.37 | M87: 0 | N87: =L87+M87 -> 3231.37 | O87: 1844.24 | P87: =O87+N87 -> 5075.61 | Q87: 174.98502 | R87: 38.698 | S87: 1728.55 | T87: 0 | U87: 0 | V87: 0 | W87: 0 | X87: 0 | Y87: 0 | Z87: 0 | AA87: 0 | AB87: =W87+X87 -> 0 | AC87: =Z87+AA87 -> 0 | AD87: =V87+AB87 -> 0 | AE87: =Y87+AC87 -> 0
C88: 3 | D88: BK3 | E88: 0 | F88: 513.847 | G88: 3379.72 | H88: 0 | I88: =E88+F88+G88+H88 -> 3893.567 | J88: 472.30005 | K88: =J88+I88 -> 4365.867 | L88: 3132.8074 | M88: 0 | N88: =L88+M88 -> 3132.8074 | O88: 1233.0492 | P88: =O88+N88 -> 4365.8566 | Q88: 0 | R88: 258.688 | S88: 0 | T88: 0 | U88: 51.552734 | V88: 20.209771 | W88: 0 | X88: 0 | Y88: 0 | Z88: 0 | AA88: 0 | AB88: =W88+X88 -> 0 | AC88: =Z88+AA88 -> 0 | AD88: =V88+AB88 -> 20.209771 | AE88: =Y88+AC88 -> 0
C89: 4 | D89: BK4 | E89: 0 | F89: 713.662 | G89: 4351.47 | H89: 0 | I89: =E89+F89+G89+H89 -> 5065.132 | J89: 1315.545 | K89: =J89+I89 -> 6380.677 | L89: 3311.51 | M89: 0 | N89: =L89+M89 -> 3311.51 | O89: 2851.85 | P89: =O89+N89 -> 6163.36 | Q89: 217.30754 | R89: 42.205 | S89: 134.46 | T89: 0 | U89: 0 | V89: 0 | W89: 0 | X89: 0 | Y89: 0 | Z89: 0 | AA89: 0 | AB89: =W89+X89 -> 0 | AC89: =Z89+AA89 -> 0 | AD89: =V89+AB89 -> 0 | AE89: =Y89+AC89 -> 0
C90: 5 | D90: BK5 | E90: 0 | F90: 417.257 | G90: 620.69 | H90: 0 | I90: =E90+F90+G90+H90 -> 1037.947 | J90: 2717.39 | K90: =J90+I90 -> 3755.337 | L90: 3122.9 | M90: 0 | N90: =L90+M90 -> 3122.9 | O90: 480.71 | P90: =O90+N90 -> 3603.61 | Q90: 151.727 | R90: 0 | S90: 322.23 | T90: 0 | U90: 0 | V90: 0 | W90: 0 | X90: 0 | Y90: 0 | Z90: 0 | AA90: 0 | AB90: =W90+X90 -> 0 | AC90: =Z90+AA90 -> 0 | AD90: =V90+AB90 -> 0 | AE90: =Y90+AC90 -> 0
E91: =SUM(E86:E90) -> 0 | F91: =SUM(F86:F90) -> 2709.584 | G91: =SUM(G86:G90) -> 12655.12 | H91: =SUM(H86:H90) -> 0 | I91: =SUM(I86:I90) -> 15364.704 | J91: =SUM(J86:J90) -> 7050.1472 | K91: =SUM(K86:K90) -> 22414.851 | L91: =SUM(L86:L90) -> 14840.942 | ... AE91: =SUM(AE86:AE90) -> 0
A93: 2 | B93: 2-2 | C93: 1 | D93: BK1 | E93: 0 | F93: 477.125 | G93: 0 | H93: 0 | I93: =E93+F93+G93+H93 -> 477.125 | J93: 2185.24 | K93: =J93+I93 -> 2662.365 | L93: 2042.355 | M93: 0 | N93: =L93+M93 -> 2042.355 | O93: 620.009 | P93: =O93+N93 -> 2662.364 | Q93: 0 | R93: 0 | S93: 0 | T93: 0 | U93: 0 | V93: 0 | W93: 0 | X93: 0 | Y93: 0 | Z93: 0 | AA93: 0 | AB93: =W93+X93 -> 0 | AC93: =Z93+AA93 -> 0 | AD93: =V93+AB93 -> 0 | AE93: =Y93+AC93 -> 0 | AG93: BK1 | AH93: 0 | AI93: 477.125 | AJ93: 0 | AK93: 0 | AL93: =AH93+AI93+AJ93+AK93 -> 477.125 | AM93: 2185.24 | AN93: =AM93+AL93 -> 2662.365 | AO93: 2042.355 | AP93: 0 | AQ93: =AO93+AP93 -> 2042.355 | AR93: 620.009 | AS93: =AR93+AQ93 -> 2662.364 | AT93: 0 | AU93: 0 | AV93: 0 | AW93: 0 | AX93: 0 | AY93: 339.599 | AZ93: 0 | BA93: 2185.24 | BB93: 0 | BC93: 0 | BD93: 0 | BE93: =AZ93+BA93 -> 2185.24 | BF93: =BC93+BD93 -> 0 | BG93: =AY93+BE93 -> 2524.839 | BH93: =BB93+BF93 -> 0
C94: 2 | D94: BK2 | E94: 0 | F94: 0 | G94: 3250.3828 | H94: 0 | I94: =E94+F94+G94+H94 -> 3250.3828 | J94: 271.67255 | K94: =J94+I94 -> 3522.0553 | L94: 3231.37 | M94: 0 | N94: =L94+M94 -> 3231.37 | O94: 115.68994 | P94: =O94+N94 -> 3347.0599 | Q94: 174.98502 | R94: 38.698 | S94: 1728.55 | T94: 1052.8574 | U94: 0 | V94: 0 | W94: 87.9996 | X94: 0 | Y94: 0 | Z94: 0 | AA94: 0 | AB94: =W94+X94 -> 87.9996 | AC94: =Z94+AA94 -> 0 | AD94: =V94+AB94 -> 87.9996 | AE94: =Y94+AC94 -> 0 | AG94: BK2 | AH94: 0 | AI94: 0 | AJ94: 3259.0488 | AK94: 0 | AL94: =AH94+AI94+AJ94+AK94 -> 3259.0488 | AM94: 301.70456 | AN94: =AM94+AL94 -> 3560.7534 | AO94: 3231.37 | AP94: 0 | AQ94: =AO94+AP94 -> 3231.37 | AR94: 115.68994 | AS94: =AR94+AQ94 -> 3347.0599 | AT94: 174.98502 | AU94: 38.698 | AV94: 1728.55 | AW94: 1044.1914 | AX94: 0 | AY94: 0 | AZ94: 96.665436 | BA94: 301.70456 | BB94: 38.698 | BC94: 0 | BD94: 1728.55 | BE94: =AZ94+BA94 -> 398.37 | BF94: =BC94+BD94 -> 1728.55 | BG94: =AY94+BE94 -> 398.37 | BH94: =BB94+BF94 -> 1767.248
C95: 3 | D95: BK3 | E95: 0 | F95: 513.847 | G95: 3379.72 | H95: 0 | I95: =E95+F95+G95+H95 -> 3893.567 | J95: 472.30005 | K95: =J95+I95 -> 4365.867 | L95: 3132.8074 | M95: 0 | N95: =L95+M95 -> 3132.8074 | O95: 1233.0492 | P95: =O95+N95 -> 4365.8566 | Q95: 0 | R95: 258.688 | S95: 0 | T95: 0 | U95: 51.552734 | V95: 20.209771 | W95: 0 | X95: 0 | Y95: 0 | Z95: 0 | AA95: 0 | AB95: =W95+X95 -> 0 | AC95: =Z95+AA95 -> 0 | AD95: =V95+AB95 -> 20.209771 | AE95: =Y95+AC95 -> 0 | AG95: BK3 | AH95: 0 | AI95: 513.847 | AJ95: 3379.72 | AK95: 0 | AL95: =AH95+AI95+AJ95+AK95 -> 3893.567 | AM95: 472.30005 | AN95: =AM95+AL95 -> 4365.867 | AO95: 3132.8074 | AP95: 0 | AQ95: =AO95+AP95 -> 3132.8074 | AR95: 1233.0492 | AS95: =AR95+AQ95 -> 4365.8566 | AT95: 0 | AU95: 258.688 | AV95: 0 | AW95: 0 | AX95: 51.552734 | AY95: 20.209771 | AZ95: 256.68994 | BA95: 472.3005 | BB95: 258.688 | BC95: 0 | BD95: 0 | BE95: =AZ95+BA95 -> 728.99044 | BF95: =BC95+BD95 -> 0 | BG95: =AY95+BE95 -> 749.20021 | BH95: =BB95+BF95 -> 258.688
C96: 4 | D96: BK4 | E96: 0 | F96: 579.20197 | G96: 4351.47 | H96: 0 | I96: =E96+F96+G96+H96 -> 4930.672 | J96: 1315.545 | K96: =J96+I96 -> 6246.217 | L96: 3311.51 | M96: 0 | N96: =L96+M96 -> 3311.51 | O96: 2717.39 | P96: =O96+N96 -> 6028.9 | Q96: 217.30754 | R96: 42.205 | S96: 134.46 | T96: 0 | U96: 0 | V96: 0 | W96: 0 | X96: 0 | Y96: 0 | Z96: 0 | AA96: 0 | AB96: =W96+X96 -> 0 | AC96: =Z96+AA96 -> 0 | AD96: =V96+AB96 -> 0 | AE96: =Y96+AC96 -> 0 | AG96: BK4 | AH96: 0 | AI96: 579.20197 | AJ96: 4351.47 | AK96: 0 | AL96: =AH96+AI96+AJ96+AK96 -> 4930.672 | AM96: 1315.545 | AN96: =AM96+AL96 -> 6246.217 | AO96: 3311.51 | AP96: 0 | AQ96: =AO96+AP96 -> 3311.51 | AR96: 2717.39 | AS96: =AR96+AQ96 -> 6028.9 | AT96: 217.30754 | AU96: 42.205 | AV96: 134.46 | AW96: 0 | AX96: 0 | AY96: 0 | AZ96: 42.204956 | BA96: 0 | BB96: 42.205 | BC96: 0 | BD96: 134.46 | BE96: =AZ96+BA96 -> 42.204956 | BF96: =BC96+BD96 -> 134.46 | BG96: =AY96+BE96 -> 42.204956 | BH96: =BB96+BF96 -> 176.665
C97: 5 | D97: BK5 | E97: 0 | F97: 95.02698 | G97: 620.69 | H97: 0 | I97: =E97+F97+G97+H97 -> 715.71698 | J97: 2717.39 | K97: =J97+I97 -> 3433.107 | L97: 3122.9 | M97: 0 | N97: =L97+M97 -> 3122.9 | O97: 158.48001 | P97: =O97+N97 -> 3281.38 | Q97: 151.727 | R97: 0 | S97: 322.23 | T97: 0 | U97: 0 | V97: 0 | W97: 0 | X97: 0 | Y97: 0 | Z97: 0 | AA97: 0 | AB97: =W97+X97 -> 0 | AC97: =Z97+AA97 -> 0 | AD97: =V97+AB97 -> 0 | AE97: =Y97+AC97 -> 0 | AG97: BK5 | AH97: 0 | AI97: 95.02698 | AJ97: 620.69 | AK97: 0 | AL97: =AH97+AI97+AJ97+AK97 -> 715.71698 | AM97: 2717.39 | AN97: =AM97+AL97 -> 3433.107 | AO97: 3122.9 | AP97: 0 | AQ97: =AO97+AP97 -> 3122.9 | AR97: 158.48001 | AS97: =AR97+AQ97 -> 3281.38 | AT97: 151.727 | AU97: 0 | AV97: 322.23 | AW97: 0 | AX97: 0 | AY97: 0 | AZ97: 0 | BA97: 0 | BB97: 0 | BC97: 0 | BD97: 322.23 | BE97: =AZ97+BA97 -> 0 | BF97: =BC97+BD97 -> 322.23 | BG97: =AY97+BE97 -> 0 | BH97: =BB97+BF97 -> 322.23
E98: =SUM(E93:E97) -> 0 | F98: =SUM(F93:F97) -> 1665.2009 | G98: =SUM(G93:G97) -> 11602.263 | H98: =SUM(H93:H97) -> 0 | I98: =SUM(I93:I97) -> 13267.464 | J98: =SUM(J93:J97) -> 6962.1476 | K98: =SUM(K93:K97) -> 20229.611 | L98: =SUM(L93:L97) -> 14840.942 | ... AE98: =SUM(AE93:AE97) -> 0 | AH98: =SUM(AH93:AH97) -> 0 | AI98: =SUM(AI93:AI97) -> 1665.2009 | AJ98: =SUM(AJ93:AJ97) -> 11610.929 | AK98: =SUM(AK93:AK97) -> 0 | AL98: =SUM(AL93:AL97) -> 13276.13 | AM98: =SUM(AM93:AM97) -> 6992.1796 | AN98: =SUM(AN93:AN97) -> 20268.309 | AO98: =SUM(AO93:AO97) -> 14840.942 | ... BH98: =SUM(BH93:BH97) -> 2524.831
A100: 2 | B100: 3 | C100: 1 | D100: BK1 | E100: 0 | F100: 477.125 | G100: 0 | H100: 0 | I100: =E100+F100+G100+H100 -> 477.125 | J100: 2185.24 | K100: =J100+I100 -> 2662.365 | L100: 2042.355 | M100: 0 | N100: =L100+M100 -> 2042.355 | O100: 620.009 | P100: =O100+N100 -> 2662.364 | Q100: 0 | R100: 0 | S100: 0 | T100: 0 | U100: 0 | V100: 0 | W100: 0 | X100: 0 | Y100: 0 | Z100: 0 | AA100: 0 | AB100: =W100+X100 -> 0 | AC100: =Z100+AA100 -> 0 | AD100: =V100+AB100 -> 0 | AE100: =Y100+AC100 -> 0
C101: 2 | D101: BK2 | E101: 0 | F101: 0 | G101: 3250.3828 | H101: 0 | I101: =E101+F101+G101+H101 -> 3250.3828 | J101: 271.67255 | K101: =J101+I101 -> 3522.0553 | L101: 3231.37 | M101: 0 | N101: =L101+M101 -> 3231.37 | O101: 115.68994 | P101: =O101+N101 -> 3347.0599 | Q101: 174.98502 | R101: 0 | S101: 0 | T101: 4303.24 | U101: 0 | V101: 0 | W101: 87.9996 | X101: 271.67255 | Y101: 0 | Z101: 0 | AA101: 0 | AB101: =W101+X101 -> 359.67215 | AC101: =Z101+AA101 -> 0 | AD101: =V101+AB101 -> 359.67215 | AE101: =Y101+AC101 -> 0
C102: 3 | D102: BK3 | E102: 0 | F102: 513.847 | G102: 3379.72 | H102: 0 | I102: =E102+F102+G102+H102 -> 3893.567 | J102: 472.30005 | K102: =J102+I102 -> 4365.867 | L102: 3132.8074 | M102: 0 | N102: =L102+M102 -> 3132.8074 | O102: 1233.0492 | P102: =O102+N102 -> 4365.8566 | Q102: 0 | R102: 0 | S102: 0 | T102: 3379.72 | U102: 51.552734 | V102: 20.209771 | W102: 0 | X102: 472.3005 | Y102: 0 | Z102: 0 | AA102: 0 | AB102: =W102+X102 -> 472.3005 | AC102: =Z102+AA102 -> 0 | AD102: =V102+AB102 -> 492.51027 | AE102: =Y102+AC102 -> 0
C103: 4 | D103: BK4 | E103: 0 | F103: 579.20197 | G103: 4351.47 | H103: 0 | I103: =E103+F103+G103+H103 -> 4930.672 | J103: 1315.545 | K103: =J103+I103 -> 6246.217 | L103: 3311.51 | M103: 0 | N103: =L103+M103 -> 3311.51 | O103: 2717.39 | P103: =O103+N103 -> 6028.9 | Q103: 217.30754 | R103: 0 | S103: 0 | T103: 0 | U103: 0 | V103: 0 | W103: 0 | X103: 0 | Y103: 0 | Z103: 0 | AA103: 0 | AB103: =W103+X103 -> 0 | AC103: =Z103+AA103 -> 0 | AD103: =V103+AB103 -> 0 | AE103: =Y103+AC103 -> 0
